Workbook
Name _DAT1: #REF!
Name _DAT10: #REF!
Name _DAT11: #REF!
Name _DAT12: #REF!
Name _DAT13: #REF!
Name _DAT14: #REF!
Name _DAT15: #REF!
Name _DAT16: #REF!
Name _DAT17: #REF!
Name _DAT18: #REF!
Name _DAT19: #REF!
Name _DAT2: #REF!
Name _DAT20: #REF!
Name _DAT21: #REF!
Name _DAT22: #REF!
Name _DAT23: #REF!
Name _DAT24: #REF!
Name _DAT25: #REF!
Name _DAT26: #REF!
Name _DAT27: #REF!
Name _DAT28: #REF!
Name _DAT29: #REF!
Name _DAT3: #REF!
Name _DAT30: #REF!
Name _DAT31: #REF!
Name _DAT4: #REF!
Name _DAT5: #REF!
Name _DAT6: #REF!
Name _DAT7: #REF!
Name _DAT8: #REF!
Name _DAT9: #REF!
Name RANGE10: #REF!
Name RANGE103: #REF!
Name RANGE105: #REF!
Name RANGE106: #REF!
Name RANGE107: #REF!
Name RANGE108: #REF!
Name RANGE11: #REF!
Name RANGE112: #REF!
Name RANGE113: #REF!
Name RANGE114: #REF!
Name RANGE115: #REF!
Name RANGE116: #REF!
Name RANGE117: #REF!
Name RANGE118: #REF!
Name RANGE119: #REF!
Name RANGE12: #REF!
Name RANGE120: #REF!
Name RANGE121: #REF!
Name RANGE122: #REF!
Name RANGE125: #REF!
Name RANGE127: #REF!
Name RANGE128: #REF!
Name RANGE129: #REF!
Name RANGE13: #REF!
Name RANGE130: #REF!
Name RANGE131: #REF!
Name RANGE132: #REF!
Name RANGE133: #REF!
Name RANGE134: #REF!

Sheet 后补
B3: 求和项:PE-后补 | D3: 创建月份 | K3: 目前待开票付款
B4: 邮箱 | C4: 客户 | D4: 4月已补建 | E4: 5月已补建 | F4: 6月已补建 | G4: 7月已补建 | H4: 8月建 | I4: 8月待建 | J4: 总计
B5: 曲盛涛 | C5: 贵阳鑫旺隆贸易有限公司 | D5: 3293.5162 | J5: 3293.5162 | K5: 3293.5162
C6: 上海文鑫网络科技有限公司 | D6: 33901.895 | G6: 35996.626 | J6: 69898.521 | K6: 32847.939
C7: 上海薪满翊商贸有限公司 | D7: 2646.6737 | J7: 2646.6737 | K7: 2646.6737
C8: 天宁区雕庄达途百货经营部 | I8: 45838.038 | J8: 45838.038
C9: 成都东森润园商贸有限公司 | I9: 1204.9545 | J9: 1204.9545
C10: 浙江省宁波三江 | I10: 11300 | J10: 11300
B11: 曲盛涛 汇总 | D11: 39842.085 | G11: 35996.626 | I11: 58342.993 | J11: 134181.7 | K11: =SUM(K5:K10) -> 38788.129
B12: 王金邦 | C12: 北京宝诚恒信科技有限公司 | G12: 73183.226 | J12: 73183.226
C13: 北京朝批中得商贸有限公司 | E13: 60325.229 | J13: 60325.229 | K13: 60293.925
C14: 北京泰和嘉华商贸有限公司 | D14: 990.47449 | H14: 5526.4306 | J14: 6516.9051
C15: 大连达博商贸有限公司 | D15: 10853.679 | J15: 10853.679 | K15: 10853.679
C16: 青岛聚鑫美商贸有限公司 | D16: 733.77547 | J16: 733.77547 | K16: 733.77547
C17: 西宁华松商贸有限公司 | D17: 6264.0345 | J17: 6264.0345 | K17: 1614.3421
C18: 大连隆欣商贸有限公司 | I18: 872.14861 | J18: 872.14861
C19: 黑龙江和盛祥供应链管理有限公司 | I19: 70.836576 | J19: 70.836576
C20: 北京卓腾商贸有限公司 | I20: 5669.9452 | J20: 5669.9452
C21: 新疆八点半供应链管理有限公司 | F21: 20143 | H21: 4385.8307 | J21: 24528.831 | K21: 20143
C22: 北京宝诚恒信商贸有限公司 | I22: 3642.5102 | J22: 3642.5102
C23: 伊犁紫金花商贸有限责任公司 | I23: 3092.6974 | J23: 3092.6974
C24: 青岛荣利鑫商贸有限公司 | I24: 328.84817 | J24: 328.84817
C25: 沈阳和盛祥供应链管理有限公司 | I25: 2601.4255 | J25: 2601.4255
C26: 济南华天新光商贸有限公司 | H26: 5999.9997 | J26: 5999.9997
C27: 常州领淘商贸有限公司 | I27: 20583.335 | J27: 20583.335
B28: 王金邦 汇总 | D28: 18841.964 | E28: 60325.229 | F28: 20143 | G28: 73183.226 | H28: 15912.261 | I28: 36861.746 | J28: 225267.43 | K28: =SUM(K12:K27) -> 93638.722
B29: 总计 | D29: 58684.049 | E29: 60325.229 | F29: 20143 | G29: 109179.85 | H29: 15912.261 | I29: 95204.739 | J29: 359449.13 | K29: =K11+K28 -> 132426.85
B39: 求和项:应补偿金额-不含税 | D39: 进度
B40: 邮箱 | C40: 客户 | D40: 待付款 | E40: 待开票付款 | F40: 总计
B41: 曲盛涛 | C41: 上海文鑫网络科技有限公司 | E41: 32847.939 | F41: 32847.939
B42: 曲盛涛 汇总 | E42: 32847.939 | F42: 32847.939
B43: 王金邦 | C43: 北京朝批中得商贸有限公司 | D43: 60293.925 | F43: 60293.925
C44: 西宁华松商贸有限公司 | E44: 1614.3421 | F44: 1614.3421
C45: 新疆八点半供应链管理有限公司 | E45: 20143 | F45: 20143
B46: 王金邦 汇总 | D46: 60293.925 | E46: 21757.342 | F46: 82051.267
B47: 总计 | D47: 60293.925 | E47: 54605.281 | F47: 114899.21

Sheet Offline TTL
A1: 公式 | B1: 公式 | C1: 公式 | E1: RKA销售填写 | F1: 销售填写 | G1: 公式 | H1: 公式 | I1: 公式 | J1: 销售填写 | K1: 公式 | L1: 公式 | M1: 公式 | N1: 公式 | O1: 公式 | P1: 公式 | Q1: 公式 | R1: 公式 | T1: 销售填写 | U1: 销售填写 | V1: 销售填写 | W1: 销售填写 | X1: 销售填写 | Y1: 销售填写 | Z1: 公式 | AA1: 销售填写 | AB1: RKA销售填写 | AC1: 公式 | AD1: NKA销售填写 | AE1: RKA销售填写 | AF1: 公式 | AG1: 公式 | AH1: NKA销售填写 | AI1: 公式 | AJ1: 公式 | AK1: 公式 | AL1: 公式 | AN1: 公式 | AO1: 公式 | AP1: 销售填写 | AQ1: 公式 | AR1: 公式 | AS1: 公式
AA2: 零售商 | AB2: 零售商 | AC2: 零售商 | AD2: 零售商 | AE2: 经销商 | AF2: 经销商 | AH2: 零售商 | AI2: 促销 | AL2: 0603更新
Q3: 未税 | R3: 未税 | T3: 零售价 | W3: 零售价权重 | AC3: 活动 | AD3: EDLP | AF3: 未税 | AG3: *% of GSV | AH3: *% of ISV | AI3: *% of ISV | AJ3: *% of GSV
A4: 客户&SKU | B4: 经销商&SKU | C4: 经销商&客户 | D4: channel | E4: 经销商 | F4: Client | G4: Category | H4: 注 | I4: Size | J4: Product-Code | K4: Material Code | L4: Barcode（EA） | M4: CN Description | N4: Material Name | O4: EA/Case | P4: Pack/EA | Q4: PR00/CS | R4: PR00/EA | T4: A级 | U4: B级-EDLP | V4: S级 | W4: A级 | X4: B级-EDLP | Y4: S级 | Z4: ASP | AA4: 前毛 | AB4: 后毛 | AC4: 促销供价 (未税） | AD4: EDLP供价 (未税） | AE4: 合同点数 | AF4: 经销商提货价 | AG4: PE% | AH4: SD% | AI4: 短促费用% | AJ4: SDR% | AK4: NSV (excl.VAT) | AL4: COGS% | AM4: DE% | AN4: GP | AO4: GP% | AP4: Total Volume (CS) | AQ4: Total NSV | AR4: Total GP | AS4: 2026 GSV
A5: =F5&J5 -> Sam's2169-00 | D5: NKA | F5: Sam's | G5: =VLOOKUP($J5,'mapping-Y26'!#REF!,2,0) -> #REF! | I5: =VLOOKUP($J5,'mapping-Y26'!$F:$L,5,0) -> 14018125 | J5: 2169-00 | K5: =VLOOKUP($J5,'mapping-Y26'!$F:$L,4,0) -> 216900舒洁®北海道牛乳系列乳霜纸面巾80抽6包装 | L5: =VLOOKUP($J5,'mapping-Y26'!#REF!,4,0) -> #REF! | M5: =VLOOKUP($J5,'mapping-Y26'!$H:$L,2,0) -> 216900舒洁®北海道牛乳系列乳霜纸面巾80抽6包装 | N5: =VLOOKUP($J5,'mapping-Y26'!$M:$N,3,0) -> #N/A | O5: =VLOOKUP($J5,'mapping-Y26'!$M:$N,5,0) -> #N/A | P5: =VLOOKUP($J5,'mapping-Y26'!$M:$N,6,0) -> #N/A | Q5: =VLOOKUP($J5,'mapping-Y26'!$M:$Q,7,0) -> #N/A | R5: =Q5/O5 -> #N/A | U5: 45.9 | X5: 1 | Z5: =T5*W5+U5*X5+V5*Y5 -> 45.9 | AA5: 0.1314 | AB5: 0 | AC5: =Z5*(1-AA5-AB5)/1.13 -> 35.282071 | AD5: =208.51245936/O5 -> #N/A | AG5: =(R5-AD5)/R5 -> #N/A | AH5: 0.0304 | AJ5: =(AH5+AI5)*AD5/R5+AG5 -> #N/A | AK5: =R5*(1-AJ5) -> #N/A | AL5: =VLOOKUP($J5,#REF!,12,0) -> #REF! | AM5: 0.027 | AN5: =AK5-R5*(AL5+AM5) -> #N/A | AO5: =AN5/AK5 -> #N/A | AQ5: =O5*AK5*AP5 -> #N/A | AR5: =AP5*AN5*O5 -> #N/A | AS5: =AP5*Q5 -> #N/A
A6: =F6&J6 -> Sam's2609-00 | D6: NKA | F6: Sam's | G6: =VLOOKUP($J6,'mapping-Y26'!#REF!,2,0) -> #REF! | H6: =VLOOKUP($J6,'mapping-Y26'!$F:$L,6,0) -> 8P-65gsm-山姆 | I6: =VLOOKUP($J6,'mapping-Y26'!$F:$L,5,0) -> 14018377 | J6: 2609-00 | K6: =VLOOKUP($J6,'mapping-Y26'!$F:$L,4,0) -> 260900舒洁湿厕纸(65gsm)8片x48包 | L6: =VLOOKUP($J6,'mapping-Y26'!#REF!,4,0) -> #REF! | M6: =VLOOKUP($J6,'mapping-Y26'!$H:$L,2,0) -> 260900舒洁湿厕纸(65gsm)8片x48包 | N6: =VLOOKUP($J6,'mapping-Y26'!M:N,3,0) -> #N/A | O6: =VLOOKUP($J6,'mapping-Y26'!$M:$N,5,0) -> #N/A | P6: =VLOOKUP($J6,'mapping-Y26'!$M:$N,6,0) -> #N/A | Q6: =VLOOKUP($J6,'mapping-Y26'!$M:$Q,7,0) -> #N/A | R6: =Q6/O6 -> #N/A | U6: 49.9 | X6: 1 | Z6: =T6*W6+U6*X6+V6*Y6 -> 49.9 | AA6: 0.13 | AB6: 0 | AC6: =Z6*(1-AA6-AB6)/1.13 -> 38.418584 | AD6: 37.8437 | AG6: =(R6-AD6)/R6 -> #N/A | AH6: 0.0304 | AJ6: =(AH6+AI6)*AD6/R6+AG6 -> #N/A | AK6: =R6*(1-AJ6) -> #N/A | AL6: =VLOOKUP($J6,#REF!,12,0) -> #REF! | AM6: 0.027 | AN6: =AK6-R6*(AL6+AM6) -> #N/A | AO6: =AN6/AK6 -> #N/A | AQ6: =O6*AK6*AP6 -> #N/A | AR6: =AP6*AN6*O6 -> #N/A | AS6: =AP6*Q6 -> #N/A
A7: =F7&J7 -> Walmart2155-03 | D7: NKA | F7: Walmart | G7: =VLOOKUP($J7,'mapping-Y26'!#REF!,2,0) -> #REF! | I7: =VLOOKUP($J7,'mapping-Y26'!$F:$L,5,0) -> 14016306 | J7: 2155-03 | K7: =VLOOKUP($J7,'mapping-Y26'!$F:$L,4,0) -> 215503舒洁®北海道轻牛乳系列乳霜纸面巾40抽3包装 | L7: =VLOOKUP($J7,'mapping-Y26'!#REF!,4,0) -> #REF! | M7: =VLOOKUP($J7,'mapping-Y26'!$H:$L,2,0) -> 215503舒洁®北海道轻牛乳系列乳霜纸面巾40抽3包装 | N7: =VLOOKUP($J7,'mapping-Y26'!M:N,3,0) -> #N/A | O7: =VLOOKUP($J7,'mapping-Y26'!$M:$N,5,0) -> #N/A | P7: =VLOOKUP($J7,'mapping-Y26'!$M:$N,6,0) -> #N/A | Q7: =VLOOKUP($J7,'mapping-Y26'!$M:$Q,7,0) -> #N/A | R7: =Q7/O7 -> #N/A | U7: 9.9 | V7: 7.9 | X7: 0.6 | Y7: 0.4 | Z7: =T7*W7+U7*X7+V7*Y7 -> 9.1 | AA7: 0.2 | AB7: 0 | AC7: =Z7*(1-AA7-AB7)/1.13 -> 6.4424779 | AG7: =(R7-AD7)/R7 -> #N/A | AJ7: =(AH7+AI7)*AD7/R7+AG7 -> #N/A | AK7: =R7*(1-AJ7) -> #N/A | AL7: =VLOOKUP($J7,#REF!,12,0) -> #REF! | AM7: 0.027 | AN7: =AK7-R7*(AL7+AM7) -> #N/A | AO7: =AN7/AK7 -> #N/A | AQ7: =O7*AK7*AP7 -> #N/A | AR7: =AP7*AN7*O7 -> #N/A | AS7: =AP7*Q7 -> #N/A
A8: =F8&J8 -> Watsons2660-10 | D8: NKA | F8: Watsons | G8: =VLOOKUP($J8,'mapping-Y26'!#REF!,2,0) -> #REF! | H8: =VLOOKUP($J8,'mapping-Y26'!$F:$L,6,0) -> 80P | I8: =VLOOKUP($J8,'mapping-Y26'!$F:$L,5,0) -> 14017865 | J8: 2660-10 | K8: =VLOOKUP($J8,'mapping-Y26'!$F:$L,4,0) -> 266010舒洁湿厕纸80片 | L8: =VLOOKUP($J8,'mapping-Y26'!#REF!,4,0) -> #REF! | M8: =VLOOKUP($J8,'mapping-Y26'!$H:$L,2,0) -> 266010舒洁湿厕纸80片 | N8: =VLOOKUP($J8,'mapping-Y26'!M:N,3,0) -> #N/A | O8: =VLOOKUP($J8,'mapping-Y26'!$M:$N,5,0) -> #N/A | P8: =VLOOKUP($J8,'mapping-Y26'!$M:$N,6,0) -> #N/A | Q8: =VLOOKUP($J8,'mapping-Y26'!$M:$Q,7,0) -> #N/A | R8: =Q8/O8 -> #N/A | U8: 10 | V8: =25/3 -> 8.3333333 | X8: 0.6 | Y8: 0.4 | Z8: =T8*W8+U8*X8+V8*Y8 -> 9.3333333 | AA8: 0.25 | AB8: 0 | AC8: =Z8*(1-AA8-AB8)/1.13 -> 6.1946903 | AD8: 11.414894 | AG8: =(R8-AD8)/R8 -> #N/A | AH8: =25%*AC8/R8 -> #N/A | AI8: =(AD8-AC8)/AD8 -> 0.45731511 | AJ8: =(AH8+AI8)*AD8/R8+AG8 -> #N/A | AK8: =R8*(1-AJ8) -> #N/A | AL8: =VLOOKUP($J8,#REF!,12,0) -> #REF! | AM8: 0.027 | AN8: =AK8-R8*(AL8+AM8) -> #N/A | AO8: =AN8/AK8 -> #N/A | AQ8: =O8*AK8*AP8 -> #N/A | AR8: =AP8*AN8*O8 -> #N/A | AS8: =AP8*Q8 -> #N/A
A9: =F9&J9 -> Watsons2694-50 | D9: NKA | F9: Watsons | G9: =VLOOKUP($J9,'mapping-Y26'!#REF!,2,0) -> #REF! | H9: =VLOOKUP($J9,'mapping-Y26'!$F:$L,6,0) -> 40P-55gsm | I9: =VLOOKUP($J9,'mapping-Y26'!$F:$L,5,0) -> 14017864 | J9: 2694-50 | K9: =VLOOKUP($J9,'mapping-Y26'!$F:$L,4,0) -> D269450舒洁湿厕纸家庭装40抽 | L9: =VLOOKUP($J9,'mapping-Y26'!#REF!,4,0) -> #REF! | M9: =VLOOKUP($J9,'mapping-Y26'!$H:$L,2,0) -> D269450舒洁湿厕纸家庭装40抽 | N9: =VLOOKUP($J9,'mapping-Y26'!M:N,3,0) -> #N/A | O9: =VLOOKUP($J9,'mapping-Y26'!$M:$N,5,0) -> #N/A | P9: =VLOOKUP($J9,'mapping-Y26'!$M:$N,6,0) -> #N/A | Q9: =VLOOKUP($J9,'mapping-Y26'!$M:$Q,7,0) -> #N/A | R9: =Q9/O9 -> #N/A | U9: 7.5 | V9: 6 | X9: 0.5 | Y9: 0.5 | Z9: =T9*W9+U9*X9+V9*Y9 -> 6.75 | AA9: 0.25 | AB9: 0 | AC9: =Z9*(1-AA9-AB9)/1.13 -> 4.4800885 | AD9: 9.188 | AG9: =(R9-AD9)/R9 -> #N/A | AH9: =25%*AC9/R9 -> #N/A | AI9: =(AD9-AC9)/AD9 -> 0.51239786 | AJ9: =(AH9+AI9)*AD9/R9+AG9 -> #N/A | AK9: =R9*(1-AJ9) -> #N/A | AL9: =VLOOKUP($J9,#REF!,12,0) -> #REF! | AM9: 0.027 | AN9: =AK9-R9*(AL9+AM9) -> #N/A | AO9: =AN9/AK9 -> #N/A | AQ9: =O9*AK9*AP9 -> #N/A | AR9: =AP9*AN9*O9 -> #N/A | AS9: =AP9*Q9 -> #N/A
A10: =F10&J10 -> Watsons2673-00 | D10: NKA | F10: Watsons | G10: =VLOOKUP($J10,'mapping-Y26'!#REF!,2,0) -> #REF! | H10: =VLOOKUP($J10,'mapping-Y26'!$F:$L,6,0) -> 60P | I10: =VLOOKUP($J10,'mapping-Y26'!$F:$L,5,0) -> 14016683 | J10: 2673-00 | K10: =VLOOKUP($J10,'mapping-Y26'!$F:$L,4,0) -> 267300舒洁®山茶花系列湿巾（湿厕纸）60片 | L10: =VLOOKUP($J10,'mapping-Y26'!#REF!,4,0) -> #REF! | M10: =VLOOKUP($J10,'mapping-Y26'!$H:$L,2,0) -> 267300舒洁®山茶花系列湿巾（湿厕纸）60片 | N10: =VLOOKUP($J10,'mapping-Y26'!M:N,3,0) -> #N/A | O10: =VLOOKUP($J10,'mapping-Y26'!$M:$N,5,0) -> #N/A | P10: =VLOOKUP($J10,'mapping-Y26'!$M:$N,6,0) -> #N/A | Q10: =VLOOKUP($J10,'mapping-Y26'!$M:$Q,7,0) -> #N/A | R10: =Q10/O10 -> #N/A | U10: 10 | V10: =25/3 -> 8.3333333 | X10: 0.6 | Y10: 0.4 | Z10: =T10*W10+U10*X10+V10*Y10 -> 9.3333333 | AA10: 0.25 | AB10: 0 | AC10: =Z10*(1-AA10-AB10)/1.13 -> 6.1946903 | AD10: =40.8/4 -> 10.2 | AG10: =(R10-AD10)/R10 -> #N/A | AH10: =25%*AC10/R10 -> #N/A | AI10: =(AD10-AC10)/AD10 -> 0.39267742 | AJ10: =(AH10+AI10)*AD10/R10+AG10 -> #N/A | AK10: =R10*(1-AJ10) -> #N/A | AL10: =VLOOKUP($J10,#REF!,12,0) -> #REF! | AM10: 0.027 | AN10: =AK10-R10*(AL10+AM10) -> #N/A | AO10: =AN10/AK10 -> #N/A | AQ10: =O10*AK10*AP10 -> #N/A | AR10: =AP10*AN10*O10 -> #N/A | AS10: =AP10*Q10 -> #N/A
A11: =F11&J11 -> Watsons2155-03 | D11: NKA | F11: Watsons | G11: =VLOOKUP($J11,'mapping-Y26'!#REF!,2,0) -> #REF! | I11: =VLOOKUP($J11,'mapping-Y26'!$F:$L,5,0) -> 14016306 | J11: 2155-03 | K11: =VLOOKUP($J11,'mapping-Y26'!$F:$L,4,0) -> 215503舒洁®北海道轻牛乳系列乳霜纸面巾40抽3包装 | L11: =VLOOKUP($J11,'mapping-Y26'!#REF!,4,0) -> #REF! | M11: =VLOOKUP($J11,'mapping-Y26'!$H:$L,2,0) -> 215503舒洁®北海道轻牛乳系列乳霜纸面巾40抽3包装 | N11: =VLOOKUP($J11,'mapping-Y26'!M:N,3,0) -> #N/A | O11: =VLOOKUP($J11,'mapping-Y26'!$M:$N,5,0) -> #N/A | P11: =VLOOKUP($J11,'mapping-Y26'!$M:$N,6,0) -> #N/A | Q11: =VLOOKUP($J11,'mapping-Y26'!$M:$Q,7,0) -> #N/A | R11: =Q11/O11 -> #N/A | U11: 12.5 | V11: 9.9 | X11: 0.5 | Y11: 0.5 | Z11: =T11*W11+U11*X11+V11*Y11 -> 11.2 | AA11: 0.25 | AB11: 0 | AC11: =Z11*(1-AA11-AB11)/1.13 -> 7.4336283 | AD11: =R11 -> #N/A | AG11: =(R11-AD11)/R11 -> #N/A | AH11: =25%*AC11/R11 -> #N/A | AI11: =(AD11-AC11)/AD11 -> #N/A | AJ11: =(AH11+AI11)*AD11/R11+AG11 -> #N/A | AK11: =R11*(1-AJ11) -> #N/A | AL11: =VLOOKUP($J11,#REF!,12,0) -> #REF! | AM11: 0.027 | AN11: =AK11-R11*(AL11+AM11) -> #N/A | AO11: =AN11/AK11 -> #N/A | AQ11: =O11*AK11*AP11 -> #N/A | AR11: =AP11*AN11*O11 -> #N/A | AS11: =AP11*Q11 -> #N/A
A12: =F12&J12 -> Watsons2653-00 | D12: NKA | F12: Watsons | G12: =VLOOKUP($J12,'mapping-Y26'!#REF!,2,0) -> #REF! | H12: =VLOOKUP($J12,'mapping-Y26'!$F:$L,6,0) -> 40P-小熊 | I12: =VLOOKUP($J12,'mapping-Y26'!$F:$L,5,0) -> 14018677 | J12: 2653-00 | K12: =VLOOKUP($J12,'mapping-Y26'!$F:$L,4,0) -> 2653-00舒洁小熊湿厕纸40片 | L12: =VLOOKUP($J12,'mapping-Y26'!#REF!,4,0) -> #REF! | M12: =VLOOKUP($J12,'mapping-Y26'!$H:$L,2,0) -> 2653-00舒洁小熊湿厕纸40片 | N12: =VLOOKUP($J12,'mapping-Y26'!M:N,3,0) -> #N/A | O12: =VLOOKUP($J12,'mapping-Y26'!$M:$N,5,0) -> #N/A | P12: =VLOOKUP($J12,'mapping-Y26'!$M:$N,6,0) -> #N/A | Q12: =VLOOKUP($J12,'mapping-Y26'!$M:$Q,7,0) -> #N/A | R12: =Q12/O12 -> #N/A | Z12: =T12*W12+U12*X12+V12*Y12 -> 0 | AA12: 0.25 | AB12: 0 | AC12: =Z12*(1-AA12-AB12)/1.13 -> 0 | AG12: =(R12-AD12)/R12 -> #N/A | AJ12: =(AH12+AI12)*AD12/R12+AG12 -> #N/A | AK12: =R12*(1-AJ12) -> #N/A | AL12: =VLOOKUP($J12,#REF!,12,0) -> #REF! | AM12: 0.027 | AN12: =AK12-R12*(AL12+AM12) -> #N/A | AO12: =AN12/AK12 -> #N/A | AQ12: =O12*AK12*AP12 -> #N/A | AR12: =AP12*AN12*O12 -> #N/A | AS12: =AP12*Q12 -> #N/A
A13: =F13&J13 -> Watsons2657-00 | D13: NKA | F13: Watsons | G13: =VLOOKUP($J13,'mapping-Y26'!#REF!,2,0) -> #REF! | H13: =VLOOKUP($J13,'mapping-Y26'!$F:$L,6,0) -> 80P-小熊 | I13: =VLOOKUP($J13,'mapping-Y26'!$F:$L,5,0) -> 14018689 | J13: 2657-00 | K13: =VLOOKUP($J13,'mapping-Y26'!$F:$L,4,0) -> 2657-00舒洁小熊湿厕纸80片 | L13: =VLOOKUP($J13,'mapping-Y26'!#REF!,4,0) -> #REF! | M13: =VLOOKUP($J13,'mapping-Y26'!$H:$L,2,0) -> 2657-00舒洁小熊湿厕纸80片 | N13: =VLOOKUP($J13,'mapping-Y26'!M:N,3,0) -> #N/A | O13: =VLOOKUP($J13,'mapping-Y26'!$M:$N,5,0) -> #N/A | P13: =VLOOKUP($J13,'mapping-Y26'!$M:$N,6,0) -> #N/A | Q13: =VLOOKUP($J13,'mapping-Y26'!$M:$Q,7,0) -> #N/A | R13: =Q13/O13 -> #N/A | Z13: =T13*W13+U13*X13+V13*Y13 -> 0 | AA13: 0.25 | AB13: 0 | AC13: =Z13*(1-AA13-AB13)/1.13 -> 0 | AG13: =(R13-AD13)/R13 -> #N/A | AJ13: =(AH13+AI13)*AD13/R13+AG13 -> #N/A | AK13: =R13*(1-AJ13) -> #N/A | AL13: =VLOOKUP($J13,#REF!,12,0) -> #REF! | AN13: =AK13-R13*(AL13+AM13) -> #N/A | AO13: =AN13/AK13 -> #N/A | AQ13: =O13*AK13*AP13 -> #N/A | AR13: =AP13*AN13*O13 -> #N/A | AS13: =AP13*Q13 -> #N/A
A14: =F14&J14 -> Metro2662-10 | D14: NKA | F14: Metro | G14: =VLOOKUP($J14,'mapping-Y26'!#REF!,2,0) -> #REF! | H14: =VLOOKUP($J14,'mapping-Y26'!$F:$L,6,0) -> 80P | I14: =VLOOKUP($J14,'mapping-Y26'!$F:$L,5,0) -> 14017868 | J14: 2662-10 | K14: =VLOOKUP($J14,'mapping-Y26'!$F:$L,4,0) -> 266210舒洁湿厕纸80片x6包 | L14: =VLOOKUP($J14,'mapping-Y26'!#REF!,4,0) -> #REF! | M14: =VLOOKUP($J14,'mapping-Y26'!$H:$L,2,0) -> 266210舒洁湿厕纸80片x6包 | N14: =VLOOKUP($J14,'mapping-Y26'!M:N,3,0) -> #N/A | O14: =VLOOKUP($J14,'mapping-Y26'!$M:$N,5,0) -> #N/A | P14: =VLOOKUP($J14,'mapping-Y26'!$M:$N,6,0) -> #N/A | Q14: =VLOOKUP($J14,'mapping-Y26'!$M:$Q,7,0) -> #N/A | R14: =Q14/O14 -> #N/A | U14: 44.9 | X14: 1 | Z14: =T14*W14+U14*X14+V14*Y14 -> 44.9 | AA14: 0.175 | AB14: 0 | AC14: =Z14*(1-AA14-AB14)/1.13 -> 32.780973 | AD14: =37/1.13 -> 32.743363 | AG14: =(R14-AD14)/R14 -> #N/A | AH14: =11.87%*0.25+16.5%*0.75 -> 0.153425 | AJ14: =(AH14+AI14)*AD14/R14+AG14 -> #N/A | AK14: =R14*(1-AJ14) -> #N/A | AL14: =VLOOKUP($J14,#REF!,12,0) -> #REF! | AM14: 0.027 | AN14: =AK14-R14*(AL14+AM14) -> #N/A | AO14: =AN14/AK14 -> #N/A | AQ14: =O14*AK14*AP14 -> #N/A | AR14: =AP14*AN14*O14 -> #N/A | AS14: =AP14*Q14 -> #N/A
A15: =F15&J15 -> 大润发东区2660-10 | D15: NKA | F15: 大润发东区 | G15: =VLOOKUP($J15,'mapping-Y26'!#REF!,2,0) -> #REF! | H15: =VLOOKUP($J15,'mapping-Y26'!$F:$L,6,0) -> 80P | I15: =VLOOKUP($J15,'mapping-Y26'!$F:$L,5,0) -> 14017865 | J15: 2660-10 | K15: =VLOOKUP($J15,'mapping-Y26'!$F:$L,4,0) -> 266010舒洁湿厕纸80片 | L15: =VLOOKUP($J15,'mapping-Y26'!#REF!,4,0) -> #REF! | M15: =VLOOKUP($J15,'mapping-Y26'!$H:$L,2,0) -> 266010舒洁湿厕纸80片 | N15: =VLOOKUP($J15,'mapping-Y26'!M:N,3,0) -> #N/A | O15: =VLOOKUP($J15,'mapping-Y26'!$M:$N,5,0) -> #N/A | P15: =VLOOKUP($J15,'mapping-Y26'!$M:$N,6,0) -> #N/A | Q15: =VLOOKUP($J15,'mapping-Y26'!$M:$Q,7,0) -> #N/A | R15: =Q15/O15 -> #N/A | U15: 9.9 | X15: 1 | Z15: =T15*W15+U15*X15+V15*Y15 -> 9.9 | AA15: 0.1 | AB15: 0 | AC15: =Z15*(1-AA15-AB15)/1.13 -> 7.8849558 | AG15: =(R15-AD15)/R15 -> #N/A | AJ15: =(AH15+AI15)*AD15/R15+AG15 -> #N/A | AK15: =R15*(1-AJ15) -> #N/A | AL15: =VLOOKUP($J15,#REF!,12,0) -> #REF! | AM15: 0.027 | AN15: =AK15-R15*(AL15+AM15) -> #N/A | AO15: =AN15/AK15 -> #N/A | AQ15: =O15*AK15*AP15 -> #N/A | AR15: =AP15*AN15*O15 -> #N/A | AS15: =AP15*Q15 -> #N/A
A16: =F16&J16 -> 大润发东区2694-50 | D16: NKA | F16: 大润发东区 | G16: =VLOOKUP($J16,'mapping-Y26'!#REF!,2,0) -> #REF! | H16: =VLOOKUP($J16,'mapping-Y26'!$F:$L,6,0) -> 40P-55gsm | I16: =VLOOKUP($J16,'mapping-Y26'!$F:$L,5,0) -> 14017864 | J16: 2694-50 | K16: =VLOOKUP($J16,'mapping-Y26'!$F:$L,4,0) -> D269450舒洁湿厕纸家庭装40抽 | L16: =VLOOKUP($J16,'mapping-Y26'!#REF!,4,0) -> #REF! | M16: =VLOOKUP($J16,'mapping-Y26'!$H:$L,2,0) -> D269450舒洁湿厕纸家庭装40抽 | N16: =VLOOKUP($J16,'mapping-Y26'!M:N,3,0) -> #N/A | O16: =VLOOKUP($J16,'mapping-Y26'!$M:$N,5,0) -> #N/A | P16: =VLOOKUP($J16,'mapping-Y26'!$M:$N,6,0) -> #N/A | Q16: =VLOOKUP($J16,'mapping-Y26'!$M:$Q,7,0) -> #N/A | R16: =Q16/O16 -> #N/A | U16: 6.9 | X16: 1 | Z16: =T16*W16+U16*X16+V16*Y16 -> 6.9 | AA16: 0.1 | AB16: 0 | AC16: =Z16*(1-AA16-AB16)/1.13 -> 5.4955752 | AG16: =(R16-AD16)/R16 -> #N/A | AJ16: =(AH16+AI16)*AD16/R16+AG16 -> #N/A | AK16: =R16*(1-AJ16) -> #N/A | AL16: =VLOOKUP($J16,#REF!,12,0) -> #REF! | AM16: 0.027 | AN16: =AK16-R16*(AL16+AM16) -> #N/A | AO16: =AN16/AK16 -> #N/A | AQ16: =O16*AK16*AP16 -> #N/A | AR16: =AP16*AN16*O16 -> #N/A | AS16: =AP16*Q16 -> #N/A
A17: =F17&J17 -> 大润发东区2291-60 | D17: NKA | F17: 大润发东区 | G17: =VLOOKUP($J17,'mapping-Y26'!#REF!,2,0) -> #REF! | I17: =VLOOKUP($J17,'mapping-Y26'!$F:$L,5,0) -> 14014479 | J17: 2291-60 | K17: =VLOOKUP($J17,'mapping-Y26'!$F:$L,4,0) -> 229160舒洁绿茶洋甘菊印花清香卷纸10粒 | L17: =VLOOKUP($J17,'mapping-Y26'!#REF!,4,0) -> #REF! | M17: =VLOOKUP($J17,'mapping-Y26'!$H:$L,2,0) -> 229160舒洁绿茶洋甘菊印花清香卷纸10粒 | N17: =VLOOKUP($J17,'mapping-Y26'!M:N,3,0) -> #N/A | O17: =VLOOKUP($J17,'mapping-Y26'!$M:$N,5,0) -> #N/A | P17: =VLOOKUP($J17,'mapping-Y26'!$M:$N,6,0) -> #N/A | Q17: =VLOOKUP($J17,'mapping-Y26'!$M:$Q,7,0) -> #N/A | R17: =Q17/O17 -> #N/A | U17: 32.9 | X17: 1 | Z17: =T17*W17+U17*X17+V17*Y17 -> 32.9 | AA17: 0.1 | AB17: 0 | AC17: =Z17*(1-AA17-AB17)/1.13 -> 26.20354 | AG17: =(R17-AD17)/R17 -> #N/A | AJ17: =(AH17+AI17)*AD17/R17+AG17 -> #N/A | AK17: =R17*(1-AJ17) -> #N/A | AL17: =VLOOKUP($J17,#REF!,12,0) -> #REF! | AM17: 0.027 | AN17: =AK17-R17*(AL17+AM17) -> #N/A | AO17: =AN17/AK17 -> #N/A | AQ17: =O17*AK17*AP17 -> #N/A | AR17: =AP17*AN17*O17 -> #N/A | AS17: =AP17*Q17 -> #N/A
A18: =F18&J18 -> 大润发南区2660-10 | D18: NKA | F18: 大润发南区 | G18: =VLOOKUP($J18,'mapping-Y26'!#REF!,2,0) -> #REF! | H18: =VLOOKUP($J18,'mapping-Y26'!$F:$L,6,0) -> 80P | I18: =VLOOKUP($J18,'mapping-Y26'!$F:$L,5,0) -> 14017865 | J18: 2660-10 | K18: =VLOOKUP($J18,'mapping-Y26'!$F:$L,4,0) -> 266010舒洁湿厕纸80片 | L18: =VLOOKUP($J18,'mapping-Y26'!#REF!,4,0) -> #REF! | M18: =VLOOKUP($J18,'mapping-Y26'!$H:$L,2,0) -> 266010舒洁湿厕纸80片 | N18: =VLOOKUP($J18,'mapping-Y26'!M:N,3,0) -> #N/A | O18: =VLOOKUP($J18,'mapping-Y26'!$M:$N,5,0) -> #N/A | P18: =VLOOKUP($J18,'mapping-Y26'!$M:$N,6,0) -> #N/A | Q18: =VLOOKUP($J18,'mapping-Y26'!$M:$Q,7,0) -> #N/A | R18: =Q18/O18 -> #N/A | U18: 19.9 | X18: 1 | Z18: =T18*W18+U18*X18+V18*Y18 -> 19.9 | AA18: 0.1 | AB18: 0 | AC18: =Z18*(1-AA18-AB18)/1.13 -> 15.849558 | AG18: =(R18-AD18)/R18 -> #N/A | AJ18: =(AH18+AI18)*AD18/R18+AG18 -> #N/A | AK18: =R18*(1-AJ18) -> #N/A | AL18: =VLOOKUP($J18,#REF!,12,0) -> #REF! | AM18: 0.027 | AN18: =AK18-R18*(AL18+AM18) -> #N/A | AO18: =AN18/AK18 -> #N/A | AQ18: =O18*AK18*AP18 -> #N/A | AR18: =AP18*AN18*O18 -> #N/A | AS18: =AP18*Q18 -> #N/A
A19: =F19&J19 -> 大润发南区2694-50 | D19: NKA | F19: 大润发南区 | G19: =VLOOKUP($J19,'mapping-Y26'!#REF!,2,0) -> #REF! | H19: =VLOOKUP($J19,'mapping-Y26'!$F:$L,6,0) -> 40P-55gsm | I19: =VLOOKUP($J19,'mapping-Y26'!$F:$L,5,0) -> 14017864 | J19: 2694-50 | K19: =VLOOKUP($J19,'mapping-Y26'!$F:$L,4,0) -> D269450舒洁湿厕纸家庭装40抽 | L19: =VLOOKUP($J19,'mapping-Y26'!#REF!,4,0) -> #REF! | M19: =VLOOKUP($J19,'mapping-Y26'!$H:$L,2,0) -> D269450舒洁湿厕纸家庭装40抽 | N19: =VLOOKUP($J19,'mapping-Y26'!M:N,3,0) -> #N/A | O19: =VLOOKUP($J19,'mapping-Y26'!$M:$N,5,0) -> #N/A | P19: =VLOOKUP($J19,'mapping-Y26'!$M:$N,6,0) -> #N/A | Q19: =VLOOKUP($J19,'mapping-Y26'!$M:$Q,7,0) -> #N/A | R19: =Q19/O19 -> #N/A | U19: 6.9 | X19: 1 | Z19: =T19*W19+U19*X19+V19*Y19 -> 6.9 | AA19: 0.1 | AB19: 0 | AC19: =Z19*(1-AA19-AB19)/1.13 -> 5.4955752 | AG19: =(R19-AD19)/R19 -> #N/A | AJ19: =(AH19+AI19)*AD19/R19+AG19 -> #N/A | AK19: =R19*(1-AJ19) -> #N/A | AL19: =VLOOKUP($J19,#REF!,12,0) -> #REF! | AM19: 0.027 | AN19: =AK19-R19*(AL19+AM19) -> #N/A | AO19: =AN19/AK19 -> #N/A | AQ19: =O19*AK19*AP19 -> #N/A | AR19: =AP19*AN19*O19 -> #N/A | AS19: =AP19*Q19 -> #N/A
A20: =F20&J20 -> 大润发南区2661-10 | D20: NKA | F20: 大润发南区 | G20: =VLOOKUP($J20,'mapping-Y26'!#REF!,2,0) -> #REF! | H20: =VLOOKUP($J20,'mapping-Y26'!$F:$L,6,0) -> 80P-55gsm | I20: =VLOOKUP($J20,'mapping-Y26'!$F:$L,5,0) -> 14017866 | J20: 2661-10 | K20: =VLOOKUP($J20,'mapping-Y26'!$F:$L,4,0) -> 266110舒洁湿厕纸80片x3包 | L20: =VLOOKUP($J20,'mapping-Y26'!#REF!,4,0) -> #REF! | M20: =VLOOKUP($J20,'mapping-Y26'!$H:$L,2,0) -> 266110舒洁湿厕纸80片x3包 | N20: =VLOOKUP($J20,'mapping-Y26'!M:N,3,0) -> #N/A | O20: =VLOOKUP($J20,'mapping-Y26'!$M:$N,5,0) -> #N/A | P20: =VLOOKUP($J20,'mapping-Y26'!$M:$N,6,0) -> #N/A | Q20: =VLOOKUP($J20,'mapping-Y26'!$M:$Q,7,0) -> #N/A | R20: =Q20/O20 -> #N/A | U20: 29.9 | X20: 1 | Z20: =T20*W20+U20*X20+V20*Y20 -> 29.9 | AA20: 0.1 | AB20: 0 | AC20: =Z20*(1-AA20-AB20)/1.13 -> 23.814159 | AG20: =(R20-AD20)/R20 -> #N/A | AJ20: =(AH20+AI20)*AD20/R20+AG20 -> #N/A | AK20: =R20*(1-AJ20) -> #N/A | AL20: =VLOOKUP($J20,#REF!,12,0) -> #REF! | AM20: 0.027 | AN20: =AK20-R20*(AL20+AM20) -> #N/A | AO20: =AN20/AK20 -> #N/A | AQ20: =O20*AK20*AP20 -> #N/A | AR20: =AP20*AN20*O20 -> #N/A | AS20: =AP20*Q20 -> #N/A
A21: =F21&J21 -> 大润发南区2162-08 | D21: NKA | F21: 大润发南区 | G21: =VLOOKUP($J21,'mapping-Y26'!#REF!,2,0) -> #REF! | I21: =VLOOKUP($J21,'mapping-Y26'!$F:$L,5,0) -> 14015110 | J21: 2162-08 | K21: =VLOOKUP($J21,'mapping-Y26'!$F:$L,4,0) -> 216208舒洁®北海道牛乳系列乳霜纸面巾20抽8包装 | L21: =VLOOKUP($J21,'mapping-Y26'!#REF!,4,0) -> #REF! | M21: =VLOOKUP($J21,'mapping-Y26'!$H:$L,2,0) -> 216208舒洁®北海道牛乳系列乳霜纸面巾20抽8包装 | N21: =VLOOKUP($J21,'mapping-Y26'!M:N,3,0) -> #N/A | O21: =VLOOKUP($J21,'mapping-Y26'!$M:$N,5,0) -> #N/A | P21: =VLOOKUP($J21,'mapping-Y26'!$M:$N,6,0) -> #N/A | Q21: =VLOOKUP($J21,'mapping-Y26'!$M:$Q,7,0) -> #N/A | R21: =Q21/O21 -> #N/A | U21: 21.9 | X21: 1 | Z21: =T21*W21+U21*X21+V21*Y21 -> 21.9 | AA21: 0.1 | AB21: 0 | AC21: =Z21*(1-AA21-AB21)/1.13 -> 17.442478 | AG21: =(R21-AD21)/R21 -> #N/A | AJ21: =(AH21+AI21)*AD21/R21+AG21 -> #N/A | AK21: =R21*(1-AJ21) -> #N/A | AL21: =VLOOKUP($J21,#REF!,12,0) -> #REF! | AM21: 0.027 | AN21: =AK21-R21*(AL21+AM21) -> #N/A | AO21: =AN21/AK21 -> #N/A | AQ21: =O21*AK21*AP21 -> #N/A | AR21: =AP21*AN21*O21 -> #N/A | AS21: =AP21*Q21 -> #N/A
A22: =F22&J22 -> 大润发南区2103-90 | D22: NKA | F22: 大润发南区 | G22: =VLOOKUP($J22,'mapping-Y26'!#REF!,2,0) -> #REF! | I22: =VLOOKUP($J22,'mapping-Y26'!$F:$L,5,0) -> 14016868 | J22: 2103-90 | K22: =VLOOKUP($J22,'mapping-Y26'!$F:$L,4,0) -> 210390舒洁小熊印花抽纸3层80抽4包FSC mix70% | L22: =VLOOKUP($J22,'mapping-Y26'!#REF!,4,0) -> #REF! | M22: =VLOOKUP($J22,'mapping-Y26'!$H:$L,2,0) -> 210390舒洁小熊印花抽纸3层80抽4包FSC mix70% | N22: =VLOOKUP($J22,'mapping-Y26'!M:N,3,0) -> #N/A | O22: =VLOOKUP($J22,'mapping-Y26'!$M:$N,5,0) -> #N/A | P22: =VLOOKUP($J22,'mapping-Y26'!$M:$N,6,0) -> #N/A | Q22: =VLOOKUP($J22,'mapping-Y26'!$M:$Q,7,0) -> #N/A | R22: =Q22/O22 -> #N/A | U22: 15.5 | X22: 1 | Z22: =T22*W22+U22*X22+V22*Y22 -> 15.5 | AA22: 0.1 | AB22: 0 | AC22: =Z22*(1-AA22-AB22)/1.13 -> 12.345133 | AG22: =(R22-AD22)/R22 -> #N/A | AJ22: =(AH22+AI22)*AD22/R22+AG22 -> #N/A | AK22: =R22*(1-AJ22) -> #N/A | AL22: =VLOOKUP($J22,#REF!,12,0) -> #REF! | AM22: 0.027 | AN22: =AK22-R22*(AL22+AM22) -> #N/A | AO22: =AN22/AK22 -> #N/A | AQ22: =O22*AK22*AP22 -> #N/A | AR22: =AP22*AN22*O22 -> #N/A | AS22: =AP22*Q22 -> #N/A
A23: =F23&J23 -> 大润发南区2107-61 | D23: NKA | F23: 大润发南区 | G23: =VLOOKUP($J23,'mapping-Y26'!#REF!,2,0) -> #REF! | I23: =VLOOKUP($J23,'mapping-Y26'!$F:$L,5,0) -> 14014470 | J23: 2107-61 | K23: =VLOOKUP($J23,'mapping-Y26'!$F:$L,4,0) -> 210761舒洁卡通系列抽纸200抽3包 FSC mix70% | L23: =VLOOKUP($J23,'mapping-Y26'!#REF!,4,0) -> #REF! | M23: =VLOOKUP($J23,'mapping-Y26'!$H:$L,2,0) -> 210761舒洁卡通系列抽纸200抽3包 FSC mix70% | N23: =VLOOKUP($J23,'mapping-Y26'!M:N,3,0) -> #N/A | O23: =VLOOKUP($J23,'mapping-Y26'!$M:$N,5,0) -> #N/A | P23: =VLOOKUP($J23,'mapping-Y26'!$M:$N,6,0) -> #N/A | Q23: =VLOOKUP($J23,'mapping-Y26'!$M:$Q,7,0) -> #N/A | R23: =Q23/O23 -> #N/A | U23: 20.9 | X23: 1 | Z23: =T23*W23+U23*X23+V23*Y23 -> 20.9 | AA23: 0.1 | AB23: 0 | AC23: =Z23*(1-AA23-AB23)/1.13 -> 16.646018 | AG23: =(R23-AD23)/R23 -> #N/A | AJ23: =(AH23+AI23)*AD23/R23+AG23 -> #N/A | AK23: =R23*(1-AJ23) -> #N/A | AL23: =VLOOKUP($J23,#REF!,12,0) -> #REF! | AM23: 0.027 | AN23: =AK23-R23*(AL23+AM23) -> #N/A | AO23: =AN23/AK23 -> #N/A | AQ23: =O23*AK23*AP23 -> #N/A | AR23: =AP23*AN23*O23 -> #N/A | AS23: =AP23*Q23 -> #N/A
A24: =F24&J24 -> 大润发南区2312-16 | D24: NKA | F24: 大润发南区 | G24: =VLOOKUP($J24,'mapping-Y26'!#REF!,2,0) -> #REF! | I24: =VLOOKUP($J24,'mapping-Y26'!$F:$L,5,0) -> 14014482 | J24: 2312-16 | K24: =VLOOKUP($J24,'mapping-Y26'!$F:$L,4,0) -> 231216 舒洁马蹄莲盒面纸200抽3盒 FSC mix70% | L24: =VLOOKUP($J24,'mapping-Y26'!#REF!,4,0) -> #REF! | M24: =VLOOKUP($J24,'mapping-Y26'!$H:$L,2,0) -> 231216 舒洁马蹄莲盒面纸200抽3盒 FSC mix70% | N24: =VLOOKUP($J24,'mapping-Y26'!M:N,3,0) -> #N/A | O24: =VLOOKUP($J24,'mapping-Y26'!$M:$N,5,0) -> #N/A | P24: =VLOOKUP($J24,'mapping-Y26'!$M:$N,6,0) -> #N/A | Q24: =VLOOKUP($J24,'mapping-Y26'!$M:$Q,7,0) -> #N/A | R24: =Q24/O24 -> #N/A | U24: 29.7 | X24: 1 | Z24: =T24*W24+U24*X24+V24*Y24 -> 29.7 | AA24: 0.1 | AB24: 0 | AC24: =Z24*(1-AA24-AB24)/1.13 -> 23.654867 | AG24: =(R24-AD24)/R24 -> #N/A | AJ24: =(AH24+AI24)*AD24/R24+AG24 -> #N/A | AK24: =R24*(1-AJ24) -> #N/A | AL24: =VLOOKUP($J24,#REF!,12,0) -> #REF! | AM24: 0.027 | AN24: =AK24-R24*(AL24+AM24) -> #N/A | AO24: =AN24/AK24 -> #N/A | AQ24: =O24*AK24*AP24 -> #N/A | AR24: =AP24*AN24*O24 -> #N/A | AS24: =AP24*Q24 -> #N/A
A25: =F25&J25 -> 大润发南区2701-90 | D25: NKA | F25: 大润发南区 | G25: =VLOOKUP($J25,'mapping-Y26'!#REF!,2,0) -> #REF! | I25: =VLOOKUP($J25,'mapping-Y26'!$F:$L,5,0) -> 14016871 | J25: 2701-90 | K25: =VLOOKUP($J25,'mapping-Y26'!$F:$L,4,0) -> 270190舒洁小熊印花手帕纸3层10包FSC mix70% | L25: =VLOOKUP($J25,'mapping-Y26'!#REF!,4,0) -> #REF! | M25: =VLOOKUP($J25,'mapping-Y26'!$H:$L,2,0) -> 270190舒洁小熊印花手帕纸3层10包FSC mix70% | N25: =VLOOKUP($J25,'mapping-Y26'!M:N,3,0) -> #N/A | O25: =VLOOKUP($J25,'mapping-Y26'!$M:$N,5,0) -> #N/A | P25: =VLOOKUP($J25,'mapping-Y26'!$M:$N,6,0) -> #N/A | Q25: =VLOOKUP($J25,'mapping-Y26'!$M:$Q,7,0) -> #N/A | R25: =Q25/O25 -> #N/A | U25: 7.3 | X25: 1 | Z25: =T25*W25+U25*X25+V25*Y25 -> 7.3 | AA25: 0.1 | AB25: 0 | AC25: =Z25*(1-AA25-AB25)/1.13 -> 5.8141593 | AG25: =(R25-AD25)/R25 -> #N/A | AJ25: =(AH25+AI25)*AD25/R25+AG25 -> #N/A | AK25: =R25*(1-AJ25) -> #N/A | AL25: =VLOOKUP($J25,#REF!,12,0) -> #REF! | AM25: 0.027 | AN25: =AK25-R25*(AL25+AM25) -> #N/A | AO25: =AN25/AK25 -> #N/A | AQ25: =O25*AK25*AP25 -> #N/A | AR25: =AP25*AN25*O25 -> #N/A | AS25: =AP25*Q25 -> #N/A
A26: =F26&J26 -> 大润发南区2613-00 | D26: NKA | F26: 大润发南区 | G26: =VLOOKUP($J26,'mapping-Y26'!#REF!,2,0) -> #REF! | I26: =VLOOKUP($J26,'mapping-Y26'!$F:$L,5,0) -> 14004626 | J26: 2613-00 | K26: =VLOOKUP($J26,'mapping-Y26'!$F:$L,4,0) -> 261300舒洁无香湿巾单包装 | L26: =VLOOKUP($J26,'mapping-Y26'!#REF!,4,0) -> #REF! | M26: =VLOOKUP($J26,'mapping-Y26'!$H:$L,2,0) -> 261300舒洁无香湿巾单包装 | N26: =VLOOKUP($J26,'mapping-Y26'!M:N,3,0) -> #N/A | O26: =VLOOKUP($J26,'mapping-Y26'!$M:$N,5,0) -> #N/A | P26: =VLOOKUP($J26,'mapping-Y26'!$M:$N,6,0) -> #N/A | Q26: =VLOOKUP($J26,'mapping-Y26'!$M:$Q,7,0) -> #N/A | R26: =Q26/O26 -> #N/A | U26: 3.7 | X26: 1 | Z26: =T26*W26+U26*X26+V26*Y26 -> 3.7 | AA26: 0.1 | AB26: 0 | AC26: =Z26*(1-AA26-AB26)/1.13 -> 2.9469027 | AG26: =(R26-AD26)/R26 -> #N/A | AJ26: =(AH26+AI26)*AD26/R26+AG26 -> #N/A | AK26: =R26*(1-AJ26) -> #N/A | AL26: =VLOOKUP($J26,#REF!,12,0) -> #REF! | AM26: 0.027 | AN26: =AK26-R26*(AL26+AM26) -> #N/A | AO26: =AN26/AK26 -> #N/A | AQ26: =O26*AK26*AP26 -> #N/A | AR26: =AP26*AN26*O26 -> #N/A | AS26: =AP26*Q26 -> #N/A
A27: =F27&J27 -> 大润发东北区2694-50 | D27: NKA | F27: 大润发东北区 | G27: =VLOOKUP($J27,'mapping-Y26'!#REF!,2,0) -> #REF! | H27: =VLOOKUP($J27,'mapping-Y26'!$F:$L,6,0) -> 40P-55gsm | I27: =VLOOKUP($J27,'mapping-Y26'!$F:$L,5,0) -> 14017864 | J27: 2694-50 | K27: =VLOOKUP($J27,'mapping-Y26'!$F:$L,4,0) -> D269450舒洁湿厕纸家庭装40抽 | L27: =VLOOKUP($J27,'mapping-Y26'!#REF!,4,0) -> #REF! | M27: =VLOOKUP($J27,'mapping-Y26'!$H:$L,2,0) -> D269450舒洁湿厕纸家庭装40抽 | N27: =VLOOKUP($J27,'mapping-Y26'!M:N,3,0) -> #N/A | O27: =VLOOKUP($J27,'mapping-Y26'!$M:$N,5,0) -> #N/A | P27: =VLOOKUP($J27,'mapping-Y26'!$M:$N,6,0) -> #N/A | Q27: =VLOOKUP($J27,'mapping-Y26'!$M:$Q,7,0) -> #N/A | R27: =Q27/O27 -> #N/A | U27: 6.9 | X27: 1 | Z27: =T27*W27+U27*X27+V27*Y27 -> 6.9 | AA27: 0.1 | AB27: 0 | AC27: =Z27*(1-AA27-AB27)/1.13 -> 5.4955752 | AG27: =(R27-AD27)/R27 -> #N/A | AJ27: =(AH27+AI27)*AD27/R27+AG27 -> #N/A | AK27: =R27*(1-AJ27) -> #N/A | AL27: =VLOOKUP($J27,#REF!,12,0) -> #REF! | AM27: 0.027 | AN27: =AK27-R27*(AL27+AM27) -> #N/A | AO27: =AN27/AK27 -> #N/A | AQ27: =O27*AK27*AP27 -> #N/A | AR27: =AP27*AN27*O27 -> #N/A | AS27: =AP27*Q27 -> #N/A
A28: =F28&J28 -> 大润发东北区2673-00 | D28: NKA | F28: 大润发东北区 | G28: =VLOOKUP($J28,'mapping-Y26'!#REF!,2,0) -> #REF! | H28: =VLOOKUP($J28,'mapping-Y26'!$F:$L,6,0) -> 60P | I28: =VLOOKUP($J28,'mapping-Y26'!$F:$L,5,0) -> 14016683 | J28: 2673-00 | K28: =VLOOKUP($J28,'mapping-Y26'!$F:$L,4,0) -> 267300舒洁®山茶花系列湿巾（湿厕纸）60片 | L28: =VLOOKUP($J28,'mapping-Y26'!#REF!,4,0) -> #REF! | M28: =VLOOKUP($J28,'mapping-Y26'!$H:$L,2,0) -> 267300舒洁®山茶花系列湿巾（湿厕纸）60片 | N28: =VLOOKUP($J28,'mapping-Y26'!M:N,3,0) -> #N/A | O28: =VLOOKUP($J28,'mapping-Y26'!$M:$N,5,0) -> #N/A | P28: =VLOOKUP($J28,'mapping-Y26'!$M:$N,6,0) -> #N/A | Q28: =VLOOKUP($J28,'mapping-Y26'!$M:$Q,7,0) -> #N/A | R28: =Q28/O28 -> #N/A | U28: 8.9 | X28: 1 | Z28: =T28*W28+U28*X28+V28*Y28 -> 8.9 | AA28: 0.1 | AB28: 0 | AC28: =Z28*(1-AA28-AB28)/1.13 -> 7.0884956 | AG28: =(R28-AD28)/R28 -> #N/A | AJ28: =(AH28+AI28)*AD28/R28+AG28 -> #N/A | AK28: =R28*(1-AJ28) -> #N/A | AL28: =VLOOKUP($J28,#REF!,12,0) -> #REF! | AM28: 0.027 | AN28: =AK28-R28*(AL28+AM28) -> #N/A | AO28: =AN28/AK28 -> #N/A | AQ28: =O28*AK28*AP28 -> #N/A | AR28: =AP28*AN28*O28 -> #N/A | AS28: =AP28*Q28 -> #N/A
A29: =F29&J29 -> 大润发东北区2103-90 | D29: NKA | F29: 大润发东北区 | G29: =VLOOKUP($J29,'mapping-Y26'!#REF!,2,0) -> #REF! | I29: =VLOOKUP($J29,'mapping-Y26'!$F:$L,5,0) -> 14016868 | J29: 2103-90 | K29: =VLOOKUP($J29,'mapping-Y26'!$F:$L,4,0) -> 210390舒洁小熊印花抽纸3层80抽4包FSC mix70% | L29: =VLOOKUP($J29,'mapping-Y26'!#REF!,4,0) -> #REF! | M29: =VLOOKUP($J29,'mapping-Y26'!$H:$L,2,0) -> 210390舒洁小熊印花抽纸3层80抽4包FSC mix70% | N29: =VLOOKUP($J29,'mapping-Y26'!M:N,3,0) -> #N/A | O29: =VLOOKUP($J29,'mapping-Y26'!$M:$N,5,0) -> #N/A | P29: =VLOOKUP($J29,'mapping-Y26'!$M:$N,6,0) -> #N/A | Q29: =VLOOKUP($J29,'mapping-Y26'!$M:$Q,7,0) -> #N/A | R29: =Q29/O29 -> #N/A | U29: 12.8 | X29: 1 | Z29: =T29*W29+U29*X29+V29*Y29 -> 12.8 | AA29: 0.1 | AB29: 0 | AC29: =Z29*(1-AA29-AB29)/1.13 -> 10.19469 | AG29: =(R29-AD29)/R29 -> #N/A | AJ29: =(AH29+AI29)*AD29/R29+AG29 -> #N/A | AK29: =R29*(1-AJ29) -> #N/A | AL29: =VLOOKUP($J29,#REF!,12,0) -> #REF! | AM29: 0.027 | AN29: =AK29-R29*(AL29+AM29) -> #N/A | AO29: =AN29/AK29 -> #N/A | AQ29: =O29*AK29*AP29 -> #N/A | AR29: =AP29*AN29*O29 -> #N/A | AS29: =AP29*Q29 -> #N/A
A30: =F30&J30 -> 大润发东北区2701-90 | D30: NKA | F30: 大润发东北区 | G30: =VLOOKUP($J30,'mapping-Y26'!#REF!,2,0) -> #REF! | I30: =VLOOKUP($J30,'mapping-Y26'!$F:$L,5,0) -> 14016871 | J30: 2701-90 | K30: =VLOOKUP($J30,'mapping-Y26'!$F:$L,4,0) -> 270190舒洁小熊印花手帕纸3层10包FSC mix70% | L30: =VLOOKUP($J30,'mapping-Y26'!#REF!,4,0) -> #REF! | M30: =VLOOKUP($J30,'mapping-Y26'!$H:$L,2,0) -> 270190舒洁小熊印花手帕纸3层10包FSC mix70% | N30: =VLOOKUP($J30,'mapping-Y26'!M:N,3,0) -> #N/A | O30: =VLOOKUP($J30,'mapping-Y26'!$M:$N,5,0) -> #N/A | P30: =VLOOKUP($J30,'mapping-Y26'!$M:$N,6,0) -> #N/A | Q30: =VLOOKUP($J30,'mapping-Y26'!$M:$Q,7,0) -> #N/A | R30: =Q30/O30 -> #N/A | U30: 6.6 | X30: 1 | Z30: =T30*W30+U30*X30+V30*Y30 -> 6.6 | AA30: 0.1 | AB30: 0 | AC30: =Z30*(1-AA30-AB30)/1.13 -> 5.2566372 | AG30: =(R30-AD30)/R30 -> #N/A | AJ30: =(AH30+AI30)*AD30/R30+AG30 -> #N/A | AK30: =R30*(1-AJ30) -> #N/A | AL30: =VLOOKUP($J30,#REF!,12,0) -> #REF! | AM30: 0.027 | AN30: =AK30-R30*(AL30+AM30) -> #N/A | AO30: =AN30/AK30 -> #N/A | AQ30: =O30*AK30*AP30 -> #N/A | AR30: =AP30*AN30*O30 -> #N/A | AS30: =AP30*Q30 -> #N/A
A31: =F31&J31 -> 大润发华北区2660-10 | D31: NKA | F31: 大润发华北区 | G31: =VLOOKUP($J31,'mapping-Y26'!#REF!,2,0) -> #REF! | H31: =VLOOKUP($J31,'mapping-Y26'!$F:$L,6,0) -> 80P | I31: =VLOOKUP($J31,'mapping-Y26'!$F:$L,5,0) -> 14017865 | J31: 2660-10 | K31: =VLOOKUP($J31,'mapping-Y26'!$F:$L,4,0) -> 266010舒洁湿厕纸80片 | L31: =VLOOKUP($J31,'mapping-Y26'!#REF!,4,0) -> #REF! | M31: =VLOOKUP($J31,'mapping-Y26'!$H:$L,2,0) -> 266010舒洁湿厕纸80片 | N31: =VLOOKUP($J31,'mapping-Y26'!M:N,3,0) -> #N/A | O31: =VLOOKUP($J31,'mapping-Y26'!$M:$N,5,0) -> #N/A | P31: =VLOOKUP($J31,'mapping-Y26'!$M:$N,6,0) -> #N/A | Q31: =VLOOKUP($J31,'mapping-Y26'!$M:$Q,7,0) -> #N/A | R31: =Q31/O31 -> #N/A | U31: 10.9 | X31: 1 | Z31: =T31*W31+U31*X31+V31*Y31 -> 10.9 | AA31: 0.1 | AB31: 0 | AC31: =Z31*(1-AA31-AB31)/1.13 -> 8.6814159 | AG31: =(R31-AD31)/R31 -> #N/A | AJ31: =(AH31+AI31)*AD31/R31+AG31 -> #N/A | AK31: =R31*(1-AJ31) -> #N/A | AL31: =VLOOKUP($J31,#REF!,12,0) -> #REF! | AM31: 0.027 | AN31: =AK31-R31*(AL31+AM31) -> #N/A | AO31: =AN31/AK31 -> #N/A | AQ31: =O31*AK31*AP31 -> #N/A | AR31: =AP31*AN31*O31 -> #N/A | AS31: =AP31*Q31 -> #N/A
A32: =F32&J32 -> 大润发华北区2666-00 | D32: NKA | F32: 大润发华北区 | G32: =VLOOKUP($J32,'mapping-Y26'!#REF!,2,0) -> #REF! | I32: =VLOOKUP($J32,'mapping-Y26'!$F:$L,5,0) -> 14016486 | J32: 2666-00 | K32: =VLOOKUP($J32,'mapping-Y26'!$F:$L,4,0) -> 266600舒洁湿厕纸100片x6包 | L32: =VLOOKUP($J32,'mapping-Y26'!#REF!,4,0) -> #REF! | M32: =VLOOKUP($J32,'mapping-Y26'!$H:$L,2,0) -> 266600舒洁湿厕纸100片x6包 | N32: =VLOOKUP($J32,'mapping-Y26'!M:N,3,0) -> #N/A | O32: =VLOOKUP($J32,'mapping-Y26'!$M:$N,5,0) -> #N/A | P32: =VLOOKUP($J32,'mapping-Y26'!$M:$N,6,0) -> #N/A | Q32: =VLOOKUP($J32,'mapping-Y26'!$M:$Q,7,0) -> #N/A | R32: =Q32/O32 -> #N/A | U32: 14.9 | X32: 1 | Z32: =T32*W32+U32*X32+V32*Y32 -> 14.9 | AA32: 0.1 | AB32: 0 | AC32: =Z32*(1-AA32-AB32)/1.13 -> 11.867257 | AG32: =(R32-AD32)/R32 -> #N/A | AJ32: =(AH32+AI32)*AD32/R32+AG32 -> #N/A | AK32: =R32*(1-AJ32) -> #N/A | AL32: =VLOOKUP($J32,#REF!,12,0) -> #REF! | AM32: 0.027 | AN32: =AK32-R32*(AL32+AM32) -> #N/A | AO32: =AN32/AK32 -> #N/A | AQ32: =O32*AK32*AP32 -> #N/A | AR32: =AP32*AN32*O32 -> #N/A | AS32: =AP32*Q32 -> #N/A
A33: =F33&J33 -> 大润发华北区2155-03 | D33: NKA | F33: 大润发华北区 | G33: =VLOOKUP($J33,'mapping-Y26'!#REF!,2,0) -> #REF! | I33: =VLOOKUP($J33,'mapping-Y26'!$F:$L,5,0) -> 14016306 | J33: 2155-03 | K33: =VLOOKUP($J33,'mapping-Y26'!$F:$L,4,0) -> 215503舒洁®北海道轻牛乳系列乳霜纸面巾40抽3包装 | L33: =VLOOKUP($J33,'mapping-Y26'!#REF!,4,0) -> #REF! | M33: =VLOOKUP($J33,'mapping-Y26'!$H:$L,2,0) -> 215503舒洁®北海道轻牛乳系列乳霜纸面巾40抽3包装 | N33: =VLOOKUP($J33,'mapping-Y26'!M:N,3,0) -> #N/A | O33: =VLOOKUP($J33,'mapping-Y26'!$M:$N,5,0) -> #N/A | P33: =VLOOKUP($J33,'mapping-Y26'!$M:$N,6,0) -> #N/A | Q33: =VLOOKUP($J33,'mapping-Y26'!$M:$Q,7,0) -> #N/A | R33: =Q33/O33 -> #N/A | Z33: =T33*W33+U33*X33+V33*Y33 -> 0 | AA33: 0.1 | AB33: 0 | AC33: =Z33*(1-AA33-AB33)/1.13 -> 0 | AG33: =(R33-AD33)/R33 -> #N/A | AJ33: =(AH33+AI33)*AD33/R33+AG33 -> #N/A | AK33: =R33*(1-AJ33) -> #N/A | AL33: =VLOOKUP($J33,#REF!,12,0) -> #REF! | AM33: 0.027 | AN33: =AK33-R33*(AL33+AM33) -> #N/A | AO33: =AN33/AK33 -> #N/A | AQ33: =O33*AK33*AP33 -> #N/A | AR33: =AP33*AN33*O33 -> #N/A | AS33: =AP33*Q33 -> #N/A
A34: =F34&J34 -> 大润发华北区2162-08 | D34: NKA | F34: 大润发华北区 | G34: =VLOOKUP($J34,'mapping-Y26'!#REF!,2,0) -> #REF! | I34: =VLOOKUP($J34,'mapping-Y26'!$F:$L,5,0) -> 14015110 | J34: 2162-08 | K34: =VLOOKUP($J34,'mapping-Y26'!$F:$L,4,0) -> 216208舒洁®北海道牛乳系列乳霜纸面巾20抽8包装 | L34: =VLOOKUP($J34,'mapping-Y26'!#REF!,4,0) -> #REF! | M34: =VLOOKUP($J34,'mapping-Y26'!$H:$L,2,0) -> 216208舒洁®北海道牛乳系列乳霜纸面巾20抽8包装 | N34: =VLOOKUP($J34,'mapping-Y26'!M:N,3,0) -> #N/A | O34: =VLOOKUP($J34,'mapping-Y26'!$M:$N,5,0) -> #N/A | P34: =VLOOKUP($J34,'mapping-Y26'!$M:$N,6,0) -> #N/A | Q34: =VLOOKUP($J34,'mapping-Y26'!$M:$Q,7,0) -> #N/A | R34: =Q34/O34 -> #N/A | U34: 23.9 | X34: 1 | Z34: =T34*W34+U34*X34+V34*Y34 -> 23.9 | AA34: 0.1 | AB34: 0 | AC34: =Z34*(1-AA34-AB34)/1.13 -> 19.035398 | AG34: =(R34-AD34)/R34 -> #N/A | AJ34: =(AH34+AI34)*AD34/R34+AG34 -> #N/A | AK34: =R34*(1-AJ34) -> #N/A | AL34: =VLOOKUP($J34,#REF!,12,0) -> #REF! | AM34: 0.027 | AN34: =AK34-R34*(AL34+AM34) -> #N/A | AO34: =AN34/AK34 -> #N/A | AQ34: =O34*AK34*AP34 -> #N/A | AR34: =AP34*AN34*O34 -> #N/A | AS34: =AP34*Q34 -> #N/A
A35: =F35&J35 -> 大润发华北区2103-90 | D35: NKA | F35: 大润发华北区 | G35: =VLOOKUP($J35,'mapping-Y26'!#REF!,2,0) -> #REF! | I35: =VLOOKUP($J35,'mapping-Y26'!$F:$L,5,0) -> 14016868 | J35: 2103-90 | K35: =VLOOKUP($J35,'mapping-Y26'!$F:$L,4,0) -> 210390舒洁小熊印花抽纸3层80抽4包FSC mix70% | L35: =VLOOKUP($J35,'mapping-Y26'!#REF!,4,0) -> #REF! | M35: =VLOOKUP($J35,'mapping-Y26'!$H:$L,2,0) -> 210390舒洁小熊印花抽纸3层80抽4包FSC mix70% | N35: =VLOOKUP($J35,'mapping-Y26'!M:N,3,0) -> #N/A | O35: =VLOOKUP($J35,'mapping-Y26'!$M:$N,5,0) -> #N/A | P35: =VLOOKUP($J35,'mapping-Y26'!$M:$N,6,0) -> #N/A | Q35: =VLOOKUP($J35,'mapping-Y26'!$M:$Q,7,0) -> #N/A | R35: =Q35/O35 -> #N/A | U35: 13.9 | X35: 1 | Z35: =T35*W35+U35*X35+V35*Y35 -> 13.9 | AA35: 0.1 | AB35: 0 | AC35: =Z35*(1-AA35-AB35)/1.13 -> 11.070796 | AG35: =(R35-AD35)/R35 -> #N/A | AJ35: =(AH35+AI35)*AD35/R35+AG35 -> #N/A | AK35: =R35*(1-AJ35) -> #N/A | AL35: =VLOOKUP($J35,#REF!,12,0) -> #REF! | AM35: 0.027 | AN35: =AK35-R35*(AL35+AM35) -> #N/A | AO35: =AN35/AK35 -> #N/A | AQ35: =O35*AK35*AP35 -> #N/A | AR35: =AP35*AN35*O35 -> #N/A | AS35: =AP35*Q35 -> #N/A
A36: =F36&J36 -> 大润发华北区2107-61 | D36: NKA | F36: 大润发华北区 | G36: =VLOOKUP($J36,'mapping-Y26'!#REF!,2,0) -> #REF! | I36: =VLOOKUP($J36,'mapping-Y26'!$F:$L,5,0) -> 14014470 | J36: 2107-61 | K36: =VLOOKUP($J36,'mapping-Y26'!$F:$L,4,0) -> 210761舒洁卡通系列抽纸200抽3包 FSC mix70% | L36: =VLOOKUP($J36,'mapping-Y26'!#REF!,4,0) -> #REF! | M36: =VLOOKUP($J36,'mapping-Y26'!$H:$L,2,0) -> 210761舒洁卡通系列抽纸200抽3包 FSC mix70% | N36: =VLOOKUP($J36,'mapping-Y26'!M:N,3,0) -> #N/A | O36: =VLOOKUP($J36,'mapping-Y26'!$M:$N,5,0) -> #N/A | P36: =VLOOKUP($J36,'mapping-Y26'!$M:$N,6,0) -> #N/A | Q36: =VLOOKUP($J36,'mapping-Y26'!$M:$Q,7,0) -> #N/A | R36: =Q36/O36 -> #N/A | U36: 15.9 | X36: 1 | Z36: =T36*W36+U36*X36+V36*Y36 -> 15.9 | AA36: 0.1 | AB36: 0 | AC36: =Z36*(1-AA36-AB36)/1.13 -> 12.663717 | AG36: =(R36-AD36)/R36 -> #N/A | AJ36: =(AH36+AI36)*AD36/R36+AG36 -> #N/A | AK36: =R36*(1-AJ36) -> #N/A | AL36: =VLOOKUP($J36,#REF!,12,0) -> #REF! | AM36: 0.027 | AN36: =AK36-R36*(AL36+AM36) -> #N/A | AO36: =AN36/AK36 -> #N/A | AQ36: =O36*AK36*AP36 -> #N/A | AR36: =AP36*AN36*O36 -> #N/A | AS36: =AP36*Q36 -> #N/A
A37: =F37&J37 -> 大润发华北区2701-90 | D37: NKA | F37: 大润发华北区 | G37: =VLOOKUP($J37,'mapping-Y26'!#REF!,2,0) -> #REF! | I37: =VLOOKUP($J37,'mapping-Y26'!$F:$L,5,0) -> 14016871 | J37: 2701-90 | K37: =VLOOKUP($J37,'mapping-Y26'!$F:$L,4,0) -> 270190舒洁小熊印花手帕纸3层10包FSC mix70% | L37: =VLOOKUP($J37,'mapping-Y26'!#REF!,4,0) -> #REF! | M37: =VLOOKUP($J37,'mapping-Y26'!$H:$L,2,0) -> 270190舒洁小熊印花手帕纸3层10包FSC mix70% | N37: =VLOOKUP($J37,'mapping-Y26'!M:N,3,0) -> #N/A | O37: =VLOOKUP($J37,'mapping-Y26'!$M:$N,5,0) -> #N/A | P37: =VLOOKUP($J37,'mapping-Y26'!$M:$N,6,0) -> #N/A | Q37: =VLOOKUP($J37,'mapping-Y26'!$M:$Q,7,0) -> #N/A | R37: =Q37/O37 -> #N/A | U37: 6.9 | X37: 1 | Z37: =T37*W37+U37*X37+V37*Y37 -> 6.9 | AA37: 0.1 | AB37: 0 | AC37: =Z37*(1-AA37-AB37)/1.13 -> 5.4955752 | AG37: =(R37-AD37)/R37 -> #N/A | AJ37: =(AH37+AI37)*AD37/R37+AG37 -> #N/A | AK37: =R37*(1-AJ37) -> #N/A | AL37: =VLOOKUP($J37,#REF!,12,0) -> #REF! | AM37: 0.027 | AN37: =AK37-R37*(AL37+AM37) -> #N/A | AO37: =AN37/AK37 -> #N/A | AQ37: =O37*AK37*AP37 -> #N/A | AR37: =AP37*AN37*O37 -> #N/A | AS37: =AP37*Q37 -> #N/A
A38: =F38&J38 -> Hema2660-10 | D38: NKA | F38: Hema | G38: =VLOOKUP($J38,'mapping-Y26'!#REF!,2,0) -> #REF! | H38: =VLOOKUP($J38,'mapping-Y26'!$F:$L,6,0) -> 80P | I38: =VLOOKUP($J38,'mapping-Y26'!$F:$L,5,0) -> 14017865 | J38: 2660-10 | K38: =VLOOKUP($J38,'mapping-Y26'!$F:$L,4,0) -> 266010舒洁湿厕纸80片 | L38: =VLOOKUP($J38,'mapping-Y26'!#REF!,4,0) -> #REF! | M38: =VLOOKUP($J38,'mapping-Y26'!$H:$L,2,0) -> 266010舒洁湿厕纸80片 | N38: =VLOOKUP($J38,'mapping-Y26'!M:N,3,0) -> #N/A | O38: =VLOOKUP($J38,'mapping-Y26'!$M:$N,5,0) -> #N/A | P38: =VLOOKUP($J38,'mapping-Y26'!$M:$N,6,0) -> #N/A | Q38: =VLOOKUP($J38,'mapping-Y26'!$M:$Q,7,0) -> #N/A | R38: =Q38/O38 -> #N/A | U38: 14.9 | X38: 1 | Z38: =T38*W38+U38*X38+V38*Y38 -> 14.9 | AA38: 0.36845638 | AB38: 0 | AC38: =Z38*(1-AA38-AB38)/1.13 -> 8.3274336 | AG38: =(R38-AD38)/R38 -> #N/A | AJ38: =(AH38+AI38)*AD38/R38+AG38 -> #N/A | AK38: =R38*(1-AJ38) -> #N/A | AL38: =VLOOKUP($J38,#REF!,12,0) -> #REF! | AM38: 0.027 | AN38: =AK38-R38*(AL38+AM38) -> #N/A | AO38: =AN38/AK38 -> #N/A | AQ38: =O38*AK38*AP38 -> #N/A | AR38: =AP38*AN38*O38 -> #N/A | AS38: =AP38*Q38 -> #N/A
A39: =F39&J39 -> Hema2661-10 | D39: NKA | F39: Hema | G39: =VLOOKUP($J39,'mapping-Y26'!#REF!,2,0) -> #REF! | H39: =VLOOKUP($J39,'mapping-Y26'!$F:$L,6,0) -> 80P-55gsm | I39: =VLOOKUP($J39,'mapping-Y26'!$F:$L,5,0) -> 14017866 | J39: 2661-10 | K39: =VLOOKUP($J39,'mapping-Y26'!$F:$L,4,0) -> 266110舒洁湿厕纸80片x3包 | L39: =VLOOKUP($J39,'mapping-Y26'!#REF!,4,0) -> #REF! | M39: =VLOOKUP($J39,'mapping-Y26'!$H:$L,2,0) -> 266110舒洁湿厕纸80片x3包 | N39: =VLOOKUP($J39,'mapping-Y26'!M:N,3,0) -> #N/A | O39: =VLOOKUP($J39,'mapping-Y26'!$M:$N,5,0) -> #N/A | P39: =VLOOKUP($J39,'mapping-Y26'!$M:$N,6,0) -> #N/A | Q39: =VLOOKUP($J39,'mapping-Y26'!$M:$Q,7,0) -> #N/A | R39: =Q39/O39 -> #N/A | U39: 33.9 | X39: 1 | Z39: =T39*W39+U39*X39+V39*Y39 -> 33.9 | AA39: 0.25006143 | AB39: 0 | AC39: =Z39*(1-AA39-AB39)/1.13 -> 22.498157 | AG39: =(R39-AD39)/R39 -> #N/A | AJ39: =(AH39+AI39)*AD39/R39+AG39 -> #N/A | AK39: =R39*(1-AJ39) -> #N/A | AL39: =VLOOKUP($J39,#REF!,12,0) -> #REF! | AM39: 0.027 | AN39: =AK39-R39*(AL39+AM39) -> #N/A | AO39: =AN39/AK39 -> #N/A | AQ39: =O39*AK39*AP39 -> #N/A | AR39: =AP39*AN39*O39 -> #N/A | AS39: =AP39*Q39 -> #N/A
A40: =F40&J40 -> Hema2670-40 | D40: NKA | F40: Hema | G40: =VLOOKUP($J40,'mapping-Y26'!#REF!,2,0) -> #REF! | H40: =VLOOKUP($J40,'mapping-Y26'!$F:$L,6,0) -> 10P-55gsm | I40: =VLOOKUP($J40,'mapping-Y26'!$F:$L,5,0) -> 14017871 | J40: 2670-40 | K40: =VLOOKUP($J40,'mapping-Y26'!$F:$L,4,0) -> D267040舒洁湿厕纸旅行装10包装 | L40: =VLOOKUP($J40,'mapping-Y26'!#REF!,4,0) -> #REF! | M40: =VLOOKUP($J40,'mapping-Y26'!$H:$L,2,0) -> D267040舒洁湿厕纸旅行装10包装 | N40: =VLOOKUP($J40,'mapping-Y26'!M:N,3,0) -> #N/A | O40: =VLOOKUP($J40,'mapping-Y26'!$M:$N,5,0) -> #N/A | P40: =VLOOKUP($J40,'mapping-Y26'!$M:$N,6,0) -> #N/A | Q40: =VLOOKUP($J40,'mapping-Y26'!$M:$Q,7,0) -> #N/A | R40: =Q40/O40 -> #N/A | U40: 21.9 | X40: 1 | Z40: =T40*W40+U40*X40+V40*Y40 -> 21.9 | AA40: 0.18 | AB40: 0 | AC40: =Z40*(1-AA40-AB40)/1.13 -> 15.892035 | AG40: =(R40-AD40)/R40 -> #N/A | AJ40: =(AH40+AI40)*AD40/R40+AG40 -> #N/A | AK40: =R40*(1-AJ40) -> #N/A | AL40: =VLOOKUP($J40,#REF!,12,0) -> #REF! | AM40: 0.027 | AN40: =AK40-R40*(AL40+AM40) -> #N/A | AO40: =AN40/AK40 -> #N/A | AQ40: =O40*AK40*AP40 -> #N/A | AR40: =AP40*AN40*O40 -> #N/A | AS40: =AP40*Q40 -> #N/A
A41: =F41&J41 -> Hema2156-10 | D41: NKA | F41: Hema | G41: =VLOOKUP($J41,'mapping-Y26'!#REF!,2,0) -> #REF! | I41: =VLOOKUP($J41,'mapping-Y26'!$F:$L,5,0) -> 14016307 | J41: 2156-10 | K41: =VLOOKUP($J41,'mapping-Y26'!$F:$L,4,0) -> 215610舒洁®北海道轻牛乳系列乳霜纸面巾100抽3包装 | L41: =VLOOKUP($J41,'mapping-Y26'!#REF!,4,0) -> #REF! | M41: =VLOOKUP($J41,'mapping-Y26'!$H:$L,2,0) -> 215610舒洁®北海道轻牛乳系列乳霜纸面巾100抽3包装 | N41: =VLOOKUP($J41,'mapping-Y26'!M:N,3,0) -> #N/A | O41: =VLOOKUP($J41,'mapping-Y26'!$M:$N,5,0) -> #N/A | P41: =VLOOKUP($J41,'mapping-Y26'!$M:$N,6,0) -> #N/A | Q41: =VLOOKUP($J41,'mapping-Y26'!$M:$Q,7,0) -> #N/A | R41: =Q41/O41 -> #N/A | U41: 29.9 | X41: 1 | Z41: =T41*W41+U41*X41+V41*Y41 -> 29.9 | AA41: 0.149 | AB41: 0 | AC41: =Z41*(1-AA41-AB41)/1.13 -> 22.517611 | AG41: =(R41-AD41)/R41 -> #N/A | AJ41: =(AH41+AI41)*AD41/R41+AG41 -> #N/A | AK41: =R41*(1-AJ41) -> #N/A | AL41: =VLOOKUP($J41,#REF!,12,0) -> #REF! | AM41: 0.027 | AN41: =AK41-R41*(AL41+AM41) -> #N/A | AO41: =AN41/AK41 -> #N/A | AQ41: =O41*AK41*AP41 -> #N/A | AR41: =AP41*AN41*O41 -> #N/A | AS41: =AP41*Q41 -> #N/A
D42: NKA | F42: Hema | G42: =VLOOKUP($J42,'mapping-Y26'!#REF!,2,0) -> #REF! | H42: =VLOOKUP($J42,'mapping-Y26'!$F:$L,6,0) -> 80P-小熊 | I42: =VLOOKUP($J42,'mapping-Y26'!$F:$L,5,0) -> 14018689 | J42: 2657-00 | M42: =VLOOKUP($J42,'mapping-Y26'!$H:$L,2,0) -> 2657-00舒洁小熊湿厕纸80片 | O42: =VLOOKUP($J42,'mapping-Y26'!$M:$N,5,0) -> #N/A | P42: =VLOOKUP($J42,'mapping-Y26'!$M:$N,6,0) -> #N/A | Q42: =VLOOKUP($J42,'mapping-Y26'!$M:$Q,7,0) -> #N/A | R42: =Q42/O42 -> #N/A | T42: =9.9*0.9 -> 8.91 | U42: =9.9-1 -> 8.9 | V42: =9.9*0.85 -> 8.415 | W42: 0.35 | X42: 0.3 | Y42: 0.35 | Z42: =T42*W42+U42*X42+V42*Y42 -> 8.73375 | AA42: 0.27 | AB42: 0 | AC42: =Z42*(1-AA42-AB42)/1.13 -> 5.6421571 | AD42: =9.9*(1-AA42)/1.13 -> 6.3955752 | AG42: =(R42-AD42)/R42 -> #N/A | AH42: 0.15 | AI42: =(AD42-AC42)/AD42 -> 0.11780303 | AJ42: =(AH42+AI42)*AD42/R42+AG42 -> #N/A | AK42: =R42*(1-AJ42) -> #N/A | AL42: =VLOOKUP($J42,#REF!,12,0) -> #REF! | AM42: 0.027 | AN42: =AK42-R42*(AL42+AM42) -> #N/A | AO42: =AN42/AK42 -> #N/A | AP42: =20000/24 -> 833.33333 | AQ42: =O42*AK42*AP42 -> #N/A | AR42: =AP42*AN42*O42 -> #N/A | AS42: =AP42*Q42 -> #N/A
A43: =F43&J43 -> Ole2694-50 | D43: NKA | F43: Ole | G43: =VLOOKUP($J43,'mapping-Y26'!#REF!,2,0) -> #REF! | H43: =VLOOKUP($J43,'mapping-Y26'!$F:$L,6,0) -> 40P-55gsm | I43: =VLOOKUP($J43,'mapping-Y26'!$F:$L,5,0) -> 14017864 | J43: 2694-50 | K43: =VLOOKUP($J43,'mapping-Y26'!$F:$L,4,0) -> D269450舒洁湿厕纸家庭装40抽 | L43: =VLOOKUP($J43,'mapping-Y26'!#REF!,4,0) -> #REF! | M43: =VLOOKUP($J43,'mapping-Y26'!$H:$L,2,0) -> D269450舒洁湿厕纸家庭装40抽 | N43: =VLOOKUP($J43,'mapping-Y26'!M:N,3,0) -> #N/A | O43: =VLOOKUP($J43,'mapping-Y26'!$M:$N,5,0) -> #N/A | P43: =VLOOKUP($J43,'mapping-Y26'!$M:$N,6,0) -> #N/A | Q43: =VLOOKUP($J43,'mapping-Y26'!$M:$Q,7,0) -> #N/A | R43: =Q43/O43 -> #N/A | Z43: =T43*W43+U43*X43+V43*Y43 -> 0 | AB43: 0 | AC43: =Z43*(1-AA43-AB43)/1.13 -> 0 | AG43: =(R43-AF43)/R43 -> #N/A | AJ43: =(AH43+AI43)*AD43/R43+AG43 -> #N/A | AK43: =R43*(1-AJ43) -> #N/A | AL43: =VLOOKUP($J43,#REF!,12,0) -> #REF! | AM43: 0.027 | AN43: =AK43-R43*(AL43+AM43) -> #N/A | AO43: =AN43/AK43 -> #N/A | AQ43: =O43*AK43*AP43 -> #N/A | AR43: =AP43*AN43*O43 -> #N/A | AS43: =AP43*Q43 -> #N/A
A44: =F44&J44 -> Ole2661-10 | D44: NKA | F44: Ole | G44: =VLOOKUP($J44,'mapping-Y26'!#REF!,2,0) -> #REF! | H44: =VLOOKUP($J44,'mapping-Y26'!$F:$L,6,0) -> 80P-55gsm | I44: =VLOOKUP($J44,'mapping-Y26'!$F:$L,5,0) -> 14017866 | J44: 2661-10 | K44: =VLOOKUP($J44,'mapping-Y26'!$F:$L,4,0) -> 266110舒洁湿厕纸80片x3包 | L44: =VLOOKUP($J44,'mapping-Y26'!#REF!,4,0) -> #REF! | M44: =VLOOKUP($J44,'mapping-Y26'!$H:$L,2,0) -> 266110舒洁湿厕纸80片x3包 | N44: =VLOOKUP($J44,'mapping-Y26'!M:N,3,0) -> #N/A | O44: =VLOOKUP($J44,'mapping-Y26'!$M:$N,5,0) -> #N/A | P44: =VLOOKUP($J44,'mapping-Y26'!$M:$N,6,0) -> #N/A | Q44: =VLOOKUP($J44,'mapping-Y26'!$M:$Q,7,0) -> #N/A | R44: =Q44/O44 -> #N/A | Z44: =T44*W44+U44*X44+V44*Y44 -> 0 | AB44: 0 | AC44: =Z44*(1-AA44-AB44)/1.13 -> 0 | AG44: =(R44-AF44)/R44 -> #N/A | AJ44: =(AH44+AI44)*AD44/R44+AG44 -> #N/A | AK44: =R44*(1-AJ44) -> #N/A | AL44: =VLOOKUP($J44,#REF!,12,0) -> #REF! | AM44: 0.027 | AN44: =AK44-R44*(AL44+AM44) -> #N/A | AO44: =AN44/AK44 -> #N/A | AQ44: =O44*AK44*AP44 -> #N/A | AR44: =AP44*AN44*O44 -> #N/A | AS44: =AP44*Q44 -> #N/A
A45: =F45&J45 -> Ole2655-10 | D45: NKA | F45: Ole | G45: =VLOOKUP($J45,'mapping-Y26'!#REF!,2,0) -> #REF! | H45: =VLOOKUP($J45,'mapping-Y26'!$F:$L,6,0) -> 7P-55gsm | I45: =VLOOKUP($J45,'mapping-Y26'!$F:$L,5,0) -> 14017863 | J45: 2655-10 | K45: =VLOOKUP($J45,'mapping-Y26'!$F:$L,4,0) -> 265510舒洁湿厕纸7抽6包装 | L45: =VLOOKUP($J45,'mapping-Y26'!#REF!,4,0) -> #REF! | M45: =VLOOKUP($J45,'mapping-Y26'!$H:$L,2,0) -> 265510舒洁湿厕纸7抽6包装 | N45: =VLOOKUP($J45,'mapping-Y26'!M:N,3,0) -> #N/A | O45: =VLOOKUP($J45,'mapping-Y26'!$M:$N,5,0) -> #N/A | P45: =VLOOKUP($J45,'mapping-Y26'!$M:$N,6,0) -> #N/A | Q45: =VLOOKUP($J45,'mapping-Y26'!$M:$Q,7,0) -> #N/A | R45: =Q45/O45 -> #N/A | Z45: =T45*W45+U45*X45+V45*Y45 -> 0 | AB45: 0 | AC45: =Z45*(1-AA45-AB45)/1.13 -> 0 | AG45: =(R45-AF45)/R45 -> #N/A | AJ45: =(AH45+AI45)*AD45/R45+AG45 -> #N/A | AK45: =R45*(1-AJ45) -> #N/A | AL45: =VLOOKUP($J45,#REF!,12,0) -> #REF! | AM45: 0.027 | AN45: =AK45-R45*(AL45+AM45) -> #N/A | AO45: =AN45/AK45 -> #N/A | AQ45: =O45*AK45*AP45 -> #N/A | AR45: =AP45*AN45*O45 -> #N/A | AS45: =AP45*Q45 -> #N/A
A46: =F46&J46 -> Ole2155-03 | D46: NKA | F46: Ole | G46: =VLOOKUP($J46,'mapping-Y26'!#REF!,2,0) -> #REF! | I46: =VLOOKUP($J46,'mapping-Y26'!$F:$L,5,0) -> 14016306 | J46: 2155-03 | K46: =VLOOKUP($J46,'mapping-Y26'!$F:$L,4,0) -> 215503舒洁®北海道轻牛乳系列乳霜纸面巾40抽3包装 | L46: =VLOOKUP($J46,'mapping-Y26'!#REF!,4,0) -> #REF! | M46: =VLOOKUP($J46,'mapping-Y26'!$H:$L,2,0) -> 215503舒洁®北海道轻牛乳系列乳霜纸面巾40抽3包装 | N46: =VLOOKUP($J46,'mapping-Y26'!M:N,3,0) -> #N/A | O46: =VLOOKUP($J46,'mapping-Y26'!$M:$N,5,0) -> #N/A | P46: =VLOOKUP($J46,'mapping-Y26'!$M:$N,6,0) -> #N/A | Q46: =VLOOKUP($J46,'mapping-Y26'!$M:$Q,7,0) -> #N/A | R46: =Q46/O46 -> #N/A | Z46: =T46*W46+U46*X46+V46*Y46 -> 0 | AB46: 0 | AC46: =Z46*(1-AA46-AB46)/1.13 -> 0 | AG46: =(R46-AF46)/R46 -> #N/A | AJ46: =(AH46+AI46)*AD46/R46+AG46 -> #N/A | AK46: =R46*(1-AJ46) -> #N/A | AL46: =VLOOKUP($J46,#REF!,12,0) -> #REF! | AM46: 0.027 | AN46: =AK46-R46*(AL46+AM46) -> #N/A | AO46: =AN46/AK46 -> #N/A | AQ46: =O46*AK46*AP46 -> #N/A | AR46: =AP46*AN46*O46 -> #N/A | AS46: =AP46*Q46 -> #N/A
A47: =F47&J47 -> Ole2156-10 | D47: NKA | F47: Ole | G47: =VLOOKUP($J47,'mapping-Y26'!#REF!,2,0) -> #REF! | I47: =VLOOKUP($J47,'mapping-Y26'!$F:$L,5,0) -> 14016307 | J47: 2156-10 | K47: =VLOOKUP($J47,'mapping-Y26'!$F:$L,4,0) -> 215610舒洁®北海道轻牛乳系列乳霜纸面巾100抽3包装 | L47: =VLOOKUP($J47,'mapping-Y26'!#REF!,4,0) -> #REF! | M47: =VLOOKUP($J47,'mapping-Y26'!$H:$L,2,0) -> 215610舒洁®北海道轻牛乳系列乳霜纸面巾100抽3包装 | N47: =VLOOKUP($J47,'mapping-Y26'!M:N,3,0) -> #N/A | O47: =VLOOKUP($J47,'mapping-Y26'!$M:$N,5,0) -> #N/A | P47: =VLOOKUP($J47,'mapping-Y26'!$M:$N,6,0) -> #N/A | Q47: =VLOOKUP($J47,'mapping-Y26'!$M:$Q,7,0) -> #N/A | R47: =Q47/O47 -> #N/A | Z47: =T47*W47+U47*X47+V47*Y47 -> 0 | AB47: 0 | AC47: =Z47*(1-AA47-AB47)/1.13 -> 0 | AG47: =(R47-AF47)/R47 -> #N/A | AJ47: =(AH47+AI47)*AD47/R47+AG47 -> #N/A | AK47: =R47*(1-AJ47) -> #N/A | AL47: =VLOOKUP($J47,#REF!,12,0) -> #REF! | AM47: 0.027 | AN47: =AK47-R47*(AL47+AM47) -> #N/A | AO47: =AN47/AK47 -> #N/A | AQ47: =O47*AK47*AP47 -> #N/A | AR47: =AP47*AN47*O47 -> #N/A | AS47: =AP47*Q47 -> #N/A
A48: =F48&J48 -> Ole2103-90 | D48: NKA | F48: Ole | G48: =VLOOKUP($J48,'mapping-Y26'!#REF!,2,0) -> #REF! | I48: =VLOOKUP($J48,'mapping-Y26'!$F:$L,5,0) -> 14016868 | J48: 2103-90 | K48: =VLOOKUP($J48,'mapping-Y26'!$F:$L,4,0) -> 210390舒洁小熊印花抽纸3层80抽4包FSC mix70% | L48: =VLOOKUP($J48,'mapping-Y26'!#REF!,4,0) -> #REF! | M48: =VLOOKUP($J48,'mapping-Y26'!$H:$L,2,0) -> 210390舒洁小熊印花抽纸3层80抽4包FSC mix70% | N48: =VLOOKUP($J48,'mapping-Y26'!M:N,3,0) -> #N/A | O48: =VLOOKUP($J48,'mapping-Y26'!$M:$N,5,0) -> #N/A | P48: =VLOOKUP($J48,'mapping-Y26'!$M:$N,6,0) -> #N/A | Q48: =VLOOKUP($J48,'mapping-Y26'!$M:$Q,7,0) -> #N/A | R48: =Q48/O48 -> #N/A | T48: 16.9 | U48: 14.9 | V48: 13.9 | W48: 0.15 | X48: 0.6 | Y48: 0.25 | Z48: =T48*W48+U48*X48+V48*Y48 -> 14.95 | AA48: 0.25 | AB48: 0 | AC48: =Z48*(1-AA48-AB48)/1.13 -> 9.9225664 | AF48: 8.7169412 | AG48: =(R48-AF48)/R48 -> #N/A | AI48: =0.8741295625/1.13/AF48 -> 0.088742824 | AJ48: =(AH48+AI48)*AF48/R48+AG48 -> #N/A | AK48: =R48*(1-AJ48) -> #N/A | AL48: =VLOOKUP($J48,#REF!,12,0) -> #REF! | AM48: 0.027 | AN48: =AK48-R48*(AL48+AM48) -> #N/A | AO48: =AN48/AK48 -> #N/A | AQ48: =O48*AK48*AP48 -> #N/A | AR48: =AP48*AN48*O48 -> #N/A | AS48: =AP48*Q48 -> #N/A
A49: =F49&J49 -> Ole2701-90 | D49: NKA | F49: Ole | G49: =VLOOKUP($J49,'mapping-Y26'!#REF!,2,0) -> #REF! | I49: =VLOOKUP($J49,'mapping-Y26'!$F:$L,5,0) -> 14016871 | J49: 2701-90 | K49: =VLOOKUP($J49,'mapping-Y26'!$F:$L,4,0) -> 270190舒洁小熊印花手帕纸3层10包FSC mix70% | L49: =VLOOKUP($J49,'mapping-Y26'!#REF!,4,0) -> #REF! | M49: =VLOOKUP($J49,'mapping-Y26'!$H:$L,2,0) -> 270190舒洁小熊印花手帕纸3层10包FSC mix70% | N49: =VLOOKUP($J49,'mapping-Y26'!M:N,3,0) -> #N/A | O49: =VLOOKUP($J49,'mapping-Y26'!$M:$N,5,0) -> #N/A | P49: =VLOOKUP($J49,'mapping-Y26'!$M:$N,6,0) -> #N/A | Q49: =VLOOKUP($J49,'mapping-Y26'!$M:$Q,7,0) -> #N/A | R49: =Q49/O49 -> #N/A | Z49: =T49*W49+U49*X49+V49*Y49 -> 0 | AB49: 0 | AC49: =Z49*(1-AA49-AB49)/1.13 -> 0 | AG49: =(R49-AF49)/R49 -> #N/A | AJ49: =(AH49+AI49)*AD49/R49+AG49 -> #N/A | AK49: =R49*(1-AJ49) -> #N/A | AL49: =VLOOKUP($J49,#REF!,12,0) -> #REF! | AM49: 0.027 | AN49: =AK49-R49*(AL49+AM49) -> #N/A | AO49: =AN49/AK49 -> #N/A | AQ49: =O49*AK49*AP49 -> #N/A | AR49: =AP49*AN49*O49 -> #N/A | AS49: =AP49*Q49 -> #N/A
A50: =F50&J50 -> Ole2291-60 | D50: NKA | F50: Ole | G50: =VLOOKUP($J50,'mapping-Y26'!#REF!,2,0) -> #REF! | I50: =VLOOKUP($J50,'mapping-Y26'!$F:$L,5,0) -> 14014479 | J50: 2291-60 | K50: =VLOOKUP($J50,'mapping-Y26'!$F:$L,4,0) -> 229160舒洁绿茶洋甘菊印花清香卷纸10粒 | L50: =VLOOKUP($J50,'mapping-Y26'!#REF!,4,0) -> #REF! | M50: =VLOOKUP($J50,'mapping-Y26'!$H:$L,2,0) -> 229160舒洁绿茶洋甘菊印花清香卷纸10粒 | N50: =VLOOKUP($J50,'mapping-Y26'!M:N,3,0) -> #N/A | O50: =VLOOKUP($J50,'mapping-Y26'!$M:$N,5,0) -> #N/A | P50: =VLOOKUP($J50,'mapping-Y26'!$M:$N,6,0) -> #N/A | Q50: =VLOOKUP($J50,'mapping-Y26'!$M:$Q,7,0) -> #N/A | R50: =Q50/O50 -> #N/A | Z50: =T50*W50+U50*X50+V50*Y50 -> 0 | AB50: 0 | AC50: =Z50*(1-AA50-AB50)/1.13 -> 0 | AG50: =(R50-AF50)/R50 -> #N/A | AJ50: =(AH50+AI50)*AD50/R50+AG50 -> #N/A | AK50: =R50*(1-AJ50) -> #N/A | AL50: =VLOOKUP($J50,#REF!,12,0) -> #REF! | AM50: 0.027 | AN50: =AK50-R50*(AL50+AM50) -> #N/A | AO50: =AN50/AK50 -> #N/A | AQ50: =O50*AK50*AP50 -> #N/A | AR50: =AP50*AN50*O50 -> #N/A | AS50: =AP50*Q50 -> #N/A
A51: =F51&J51 -> 711全家2694-50 | B51: =E51&J51 -> 上海薪满翊2694-50 | C51: =E51&F51 -> 上海薪满翊711全家 | D51: RLKA | E51: 上海薪满翊 | F51: 711全家 | G51: =VLOOKUP($J51,'mapping-Y26'!#REF!,2,0) -> #REF! | H51: =VLOOKUP($J51,'mapping-Y26'!$F:$L,6,0) -> 40P-55gsm | I51: =VLOOKUP($J51,'mapping-Y26'!$F:$L,5,0) -> 14017864 | J51: 2694-50 | K51: =VLOOKUP($J51,'mapping-Y26'!$F:$L,4,0) -> D269450舒洁湿厕纸家庭装40抽 | L51: =VLOOKUP($J51,'mapping-Y26'!#REF!,4,0) -> #REF! | M51: =VLOOKUP($J51,'mapping-Y26'!$H:$L,2,0) -> D269450舒洁湿厕纸家庭装40抽 | N51: =VLOOKUP($J51,'mapping-Y26'!M:N,3,0) -> #N/A | O51: =VLOOKUP($J51,'mapping-Y26'!$M:$N,5,0) -> #N/A | P51: =VLOOKUP($J51,'mapping-Y26'!$M:$N,6,0) -> #N/A | Q51: =VLOOKUP($J51,'mapping-Y26'!$M:$Q,7,0) -> #N/A | R51: =Q51/O51 -> #N/A | U51: 11.9 | V51: 6.45 | X51: 0.6 | Y51: 0.4 | Z51: =T51*W51+U51*X51+V51*Y51 -> 9.72 | AA51: 0.38 | AB51: 0.15 | AC51: =Z51*(1-AA51-AB51)/1.13 -> 4.0428319 | AE51: 0.15 | AF51: =AD51*(1-AE51) -> 0 | AG51: =(R51-AF51)/R51 -> #N/A | AH51: 0 | AI51: 0.04 | AJ51: =(AH51+AI51)*AF51/R51+AG51 -> #N/A | AK51: =R51*(1-AJ51) -> #N/A | AL51: =VLOOKUP($J51,#REF!,12,0) -> #REF! | AM51: 0.027 | AN51: =AK51-R51*(AL51+AM51) -> #N/A | AO51: =AN51/AK51 -> #N/A | AP51: 500 | AQ51: =O51*AK51*AP51 -> #N/A | AR51: =AP51*AN51*O51 -> #N/A | AS51: =AP51*Q51 -> #N/A
A52: =F52&J52 -> 711全家2103-90 | B52: =E52&J52 -> 上海薪满翊2103-90 | C52: =E52&F52 -> 上海薪满翊711全家 | D52: RLKA | E52: 上海薪满翊 | F52: 711全家 | G52: =VLOOKUP($J52,'mapping-Y26'!#REF!,2,0) -> #REF! | I52: =VLOOKUP($J52,'mapping-Y26'!$F:$L,5,0) -> 14016868 | J52: 2103-90 | K52: =VLOOKUP($J52,'mapping-Y26'!$F:$L,4,0) -> 210390舒洁小熊印花抽纸3层80抽4包FSC mix70% | L52: =VLOOKUP($J52,'mapping-Y26'!#REF!,4,0) -> #REF! | M52: =VLOOKUP($J52,'mapping-Y26'!$H:$L,2,0) -> 210390舒洁小熊印花抽纸3层80抽4包FSC mix70% | N52: =VLOOKUP($J52,'mapping-Y26'!M:N,3,0) -> #N/A | O52: =VLOOKUP($J52,'mapping-Y26'!$M:$N,5,0) -> #N/A | P52: =VLOOKUP($J52,'mapping-Y26'!$M:$N,6,0) -> #N/A | Q52: =VLOOKUP($J52,'mapping-Y26'!$M:$Q,7,0) -> #N/A | R52: =Q52/O52 -> #N/A | U52: 29.9 | V52: 22.425 | X52: 0.6 | Y52: 0.4 | Z52: =T52*W52+U52*X52+V52*Y52 -> 26.91 | AA52: 0.38 | AB52: 0.15 | AC52: =Z52*(1-AA52-AB52)/1.13 -> 11.192655 | AE52: 0.15 | AF52: =AD52*(1-AE52) -> 0 | AG52: =(R52-AF52)/R52 -> #N/A | AH52: 0 | AI52: 0.04 | AJ52: =(AH52+AI52)*AF52/R52+AG52 -> #N/A | AK52: =R52*(1-AJ52) -> #N/A | AL52: =VLOOKUP($J52,#REF!,12,0) -> #REF! | AM52: 0.027 | AN52: =AK52-R52*(AL52+AM52) -> #N/A | AO52: =AN52/AK52 -> #N/A | AP52: 400 | AQ52: =O52*AK52*AP52 -> #N/A | AR52: =AP52*AN52*O52 -> #N/A | AS52: =AP52*Q52 -> #N/A
A53: =F53&J53 -> 711全家2167-10 | B53: =E53&J53 -> 上海薪满翊2167-10 | C53: =E53&F53 -> 上海薪满翊711全家 | D53: RLKA | E53: 上海薪满翊 | F53: 711全家 | G53: =VLOOKUP($J53,'mapping-Y26'!#REF!,2,0) -> #REF! | I53: =VLOOKUP($J53,'mapping-Y26'!$F:$L,5,0) -> 14016042 | J53: 2167-10 | K53: =VLOOKUP($J53,'mapping-Y26'!$F:$L,4,0) -> 216710舒洁®牛乳系列乳霜纸面巾口袋包7抽10包装 | L53: =VLOOKUP($J53,'mapping-Y26'!#REF!,4,0) -> #REF! | M53: =VLOOKUP($J53,'mapping-Y26'!$H:$L,2,0) -> 216710舒洁®牛乳系列乳霜纸面巾口袋包7抽10包装 | N53: =VLOOKUP($J53,'mapping-Y26'!M:N,3,0) -> #N/A | O53: =VLOOKUP($J53,'mapping-Y26'!$M:$N,5,0) -> #N/A | P53: =VLOOKUP($J53,'mapping-Y26'!$M:$N,6,0) -> #N/A | Q53: =VLOOKUP($J53,'mapping-Y26'!$M:$Q,7,0) -> #N/A | R53: =Q53/O53 -> #N/A | U53: 33.9 | V53: 25.425 | X53: 0.6 | Y53: 0.4 | Z53: =T53*W53+U53*X53+V53*Y53 -> 30.51 | AA53: 0.38 | AB53: 0.15 | AC53: =Z53*(1-AA53-AB53)/1.13 -> 12.69 | AE53: 0.15 | AF53: =AD53*(1-AE53) -> 0 | AG53: =(R53-AF53)/R53 -> #N/A | AH53: 0 | AI53: 0.04 | AJ53: =(AH53+AI53)*AF53/R53+AG53 -> #N/A | AK53: =R53*(1-AJ53) -> #N/A | AL53: =VLOOKUP($J53,#REF!,12,0) -> #REF! | AM53: 0.027 | AN53: =AK53-R53*(AL53+AM53) -> #N/A | AO53: =AN53/AK53 -> #N/A | AP53: 240 | AQ53: =O53*AK53*AP53 -> #N/A | AR53: =AP53*AN53*O53 -> #N/A | AS53: =AP53*Q53 -> #N/A
A54: =F54&J54 -> 711全家2613-00 | B54: =E54&J54 -> 上海薪满翊2613-00 | C54: =E54&F54 -> 上海薪满翊711全家 | D54: RLKA | E54: 上海薪满翊 | F54: 711全家 | G54: =VLOOKUP($J54,'mapping-Y26'!#REF!,2,0) -> #REF! | I54: =VLOOKUP($J54,'mapping-Y26'!$F:$L,5,0) -> 14004626 | J54: 2613-00 | K54: =VLOOKUP($J54,'mapping-Y26'!$F:$L,4,0) -> 261300舒洁无香湿巾单包装 | L54: =VLOOKUP($J54,'mapping-Y26'!#REF!,4,0) -> #REF! | M54: =VLOOKUP($J54,'mapping-Y26'!$H:$L,2,0) -> 261300舒洁无香湿巾单包装 | N54: =VLOOKUP($J54,'mapping-Y26'!M:N,3,0) -> #N/A | O54: =VLOOKUP($J54,'mapping-Y26'!$M:$N,5,0) -> #N/A | P54: =VLOOKUP($J54,'mapping-Y26'!$M:$N,6,0) -> #N/A | Q54: =VLOOKUP($J54,'mapping-Y26'!$M:$Q,7,0) -> #N/A | R54: =Q54/O54 -> #N/A | U54: 5.4 | V54: 3.2 | X54: 0.6 | Y54: 0.4 | Z54: =T54*W54+U54*X54+V54*Y54 -> 4.52 | AA54: 0.38 | AB54: 0.15 | AC54: =Z54*(1-AA54-AB54)/1.13 -> 1.88 | AE54: 0.15 | AF54: =AD54*(1-AE54) -> 0 | AG54: =(R54-AF54)/R54 -> #N/A | AH54: 0 | AI54: 0.04 | AJ54: =(AH54+AI54)*AF54/R54+AG54 -> #N/A | AK54: =R54*(1-AJ54) -> #N/A | AL54: =VLOOKUP($J54,#REF!,12,0) -> #REF! | AM54: 0.027 | AN54: =AK54-R54*(AL54+AM54) -> #N/A | AO54: =AN54/AK54 -> #N/A | AP54: 1200 | AQ54: =O54*AK54*AP54 -> #N/A | AR54: =AP54*AN54*O54 -> #N/A | AS54: =AP54*Q54 -> #N/A
A55: =F55&J55 -> 711全家2107-61 | B55: =E55&J55 -> 上海薪满翊2107-61 | C55: =E55&F55 -> 上海薪满翊711全家 | D55: RLKA | E55: 上海薪满翊 | F55: 711全家 | G55: =VLOOKUP($J55,'mapping-Y26'!#REF!,2,0) -> #REF! | I55: =VLOOKUP($J55,'mapping-Y26'!$F:$L,5,0) -> 14014470 | J55: 2107-61 | K55: =VLOOKUP($J55,'mapping-Y26'!$F:$L,4,0) -> 210761舒洁卡通系列抽纸200抽3包 FSC mix70% | L55: =VLOOKUP($J55,'mapping-Y26'!#REF!,4,0) -> #REF! | M55: =VLOOKUP($J55,'mapping-Y26'!$H:$L,2,0) -> 210761舒洁卡通系列抽纸200抽3包 FSC mix70% | N55: =VLOOKUP($J55,'mapping-Y26'!M:N,3,0) -> #N/A | O55: =VLOOKUP($J55,'mapping-Y26'!$M:$N,5,0) -> #N/A | P55: =VLOOKUP($J55,'mapping-Y26'!$M:$N,6,0) -> #N/A | Q55: =VLOOKUP($J55,'mapping-Y26'!$M:$Q,7,0) -> #N/A | R55: =Q55/O55 -> #N/A | U55: 46.9 | V55: 35.175 | X55: 0.6 | Y55: 0.4 | Z55: =T55*W55+U55*X55+V55*Y55 -> 42.21 | AA55: 0.38 | AB55: 0.235 | AC55: =Z55*(1-AA55-AB55)/1.13 -> 14.381283 | AE55: 0.15 | AF55: =AD55*(1-AE55) -> 0 | AG55: =(R55-AF55)/R55 -> #N/A | AH55: 0 | AI55: 0.04 | AJ55: =(AH55+AI55)*AF55/R55+AG55 -> #N/A | AK55: =R55*(1-AJ55) -> #N/A | AL55: =VLOOKUP($J55,#REF!,12,0) -> #REF! | AM55: 0.027 | AN55: =AK55-R55*(AL55+AM55) -> #N/A | AO55: =AN55/AK55 -> #N/A | AP55: 4000 | AQ55: =O55*AK55*AP55 -> #N/A | AR55: =AP55*AN55*O55 -> #N/A | AS55: =AP55*Q55 -> #N/A
A56: =F56&J56 -> 薪满翊others2216-35 | B56: =E56&J56 -> 上海薪满翊2216-35 | C56: =E56&F56 -> 上海薪满翊薪满翊others | D56: RLKA | E56: 上海薪满翊 | F56: 薪满翊others | G56: =VLOOKUP($J56,'mapping-Y26'!#REF!,2,0) -> #REF! | I56: =VLOOKUP($J56,'mapping-Y26'!$F:$L,5,0) -> 14015861 | J56: 2216-35 | K56: =VLOOKUP($J56,'mapping-Y26'!$F:$L,4,0) -> 221635舒洁卷纸3层纯白10粒（蓝色） | L56: =VLOOKUP($J56,'mapping-Y26'!#REF!,4,0) -> #REF! | M56: =VLOOKUP($J56,'mapping-Y26'!$H:$L,2,0) -> 221635舒洁卷纸3层纯白10粒（蓝色） | N56: =VLOOKUP($J56,'mapping-Y26'!M:N,3,0) -> #N/A | O56: =VLOOKUP($J56,'mapping-Y26'!$M:$N,5,0) -> #N/A | P56: =VLOOKUP($J56,'mapping-Y26'!$M:$N,6,0) -> #N/A | Q56: =VLOOKUP($J56,'mapping-Y26'!$M:$Q,7,0) -> #N/A | R56: =Q56/O56 -> #N/A | U56: 35.9 | V56: 26.925 | X56: 0.6 | Y56: 0.4 | Z56: =T56*W56+U56*X56+V56*Y56 -> 32.31 | AA56: 0.2 | AB56: 0.1 | AC56: =Z56*(1-AA56-AB56)/1.13 -> 20.015044 | AE56: 0.15 | AF56: =AD56*(1-AE56) -> 0 | AG56: =(R56-AF56)/R56 -> #N/A | AH56: 0 | AI56: 0.04 | AJ56: =(AH56+AI56)*AF56/R56+AG56 -> #N/A | AK56: =R56*(1-AJ56) -> #N/A | AL56: =VLOOKUP($J56,#REF!,12,0) -> #REF! | AM56: 0.027 | AN56: =AK56-R56*(AL56+AM56) -> #N/A | AO56: =AN56/AK56 -> #N/A | AP56: 70 | AQ56: =O56*AK56*AP56 -> #N/A | AR56: =AP56*AN56*O56 -> #N/A | AS56: =AP56*Q56 -> #N/A
A57: =F57&J57 -> 薪满翊others2701-90 | B57: =E57&J57 -> 上海薪满翊2701-90 | C57: =E57&F57 -> 上海薪满翊薪满翊others | D57: RLKA | E57: 上海薪满翊 | F57: 薪满翊others | G57: =VLOOKUP($J57,'mapping-Y26'!#REF!,2,0) -> #REF! | I57: =VLOOKUP($J57,'mapping-Y26'!$F:$L,5,0) -> 14016871 | J57: 2701-90 | K57: =VLOOKUP($J57,'mapping-Y26'!$F:$L,4,0) -> 270190舒洁小熊印花手帕纸3层10包FSC mix70% | L57: =VLOOKUP($J57,'mapping-Y26'!#REF!,4,0) -> #REF! | M57: =VLOOKUP($J57,'mapping-Y26'!$H:$L,2,0) -> 270190舒洁小熊印花手帕纸3层10包FSC mix70% | N57: =VLOOKUP($J57,'mapping-Y26'!M:N,3,0) -> #N/A | O57: =VLOOKUP($J57,'mapping-Y26'!$M:$N,5,0) -> #N/A | P57: =VLOOKUP($J57,'mapping-Y26'!$M:$N,6,0) -> #N/A | Q57: =VLOOKUP($J57,'mapping-Y26'!$M:$Q,7,0) -> #N/A | R57: =Q57/O57 -> #N/A | U57: 8.9 | V57: 6.675 | X57: 0.6 | Y57: 0.4 | Z57: =T57*W57+U57*X57+V57*Y57 -> 8.01 | AA57: 0.2 | AB57: 0.1 | AC57: =Z57*(1-AA57-AB57)/1.13 -> 4.9619469 | AE57: 0.15 | AF57: =AD57*(1-AE57) -> 0 | AG57: =(R57-AF57)/R57 -> #N/A | AH57: 0 | AI57: 0.04 | AJ57: =(AH57+AI57)*AF57/R57+AG57 -> #N/A | AK57: =R57*(1-AJ57) -> #N/A | AL57: =VLOOKUP($J57,#REF!,12,0) -> #REF! | AM57: 0.027 | AN57: =AK57-R57*(AL57+AM57) -> #N/A | AO57: =AN57/AK57 -> #N/A | AP57: 30 | AQ57: =O57*AK57*AP57 -> #N/A | AR57: =AP57*AN57*O57 -> #N/A | AS57: =AP57*Q57 -> #N/A
A58: =F58&J58 -> 薪满翊others2162-08 | B58: =E58&J58 -> 上海薪满翊2162-08 | C58: =E58&F58 -> 上海薪满翊薪满翊others | D58: RLKA | E58: 上海薪满翊 | F58: 薪满翊others | G58: =VLOOKUP($J58,'mapping-Y26'!#REF!,2,0) -> #REF! | I58: =VLOOKUP($J58,'mapping-Y26'!$F:$L,5,0) -> 14015110 | J58: 2162-08 | K58: =VLOOKUP($J58,'mapping-Y26'!$F:$L,4,0) -> 216208舒洁®北海道牛乳系列乳霜纸面巾20抽8包装 | L58: =VLOOKUP($J58,'mapping-Y26'!#REF!,4,0) -> #REF! | M58: =VLOOKUP($J58,'mapping-Y26'!$H:$L,2,0) -> 216208舒洁®北海道牛乳系列乳霜纸面巾20抽8包装 | N58: =VLOOKUP($J58,'mapping-Y26'!M:N,3,0) -> #N/A | O58: =VLOOKUP($J58,'mapping-Y26'!$M:$N,5,0) -> #N/A | P58: =VLOOKUP($J58,'mapping-Y26'!$M:$N,6,0) -> #N/A | Q58: =VLOOKUP($J58,'mapping-Y26'!$M:$Q,7,0) -> #N/A | R58: =Q58/O58 -> #N/A | U58: 32.9 | V58: 24.675 | X58: 0.6 | Y58: 0.4 | Z58: =T58*W58+U58*X58+V58*Y58 -> 29.61 | AA58: 0.2 | AB58: 0.1 | AC58: =Z58*(1-AA58-AB58)/1.13 -> 18.342478 | AE58: 0.15 | AF58: =AD58*(1-AE58) -> 0 | AG58: =(R58-AF58)/R58 -> #N/A | AH58: 0 | AI58: 0.04 | AJ58: =(AH58+AI58)*AF58/R58+AG58 -> #N/A | AK58: =R58*(1-AJ58) -> #N/A | AL58: =VLOOKUP($J58,#REF!,12,0) -> #REF! | AM58: 0.027 | AN58: =AK58-R58*(AL58+AM58) -> #N/A | AO58: =AN58/AK58 -> #N/A | AP58: 150 | AQ58: =O58*AK58*AP58 -> #N/A | AR58: =AP58*AN58*O58 -> #N/A | AS58: =AP58*Q58 -> #N/A
A59: =F59&J59 -> 京客隆2694-50 | B59: =E59&J59 -> 北京朝批2694-50 | C59: =E59&F59 -> 北京朝批京客隆 | D59: RLKA | E59: 北京朝批 | F59: 京客隆 | G59: =VLOOKUP($J59,'mapping-Y26'!#REF!,2,0) -> #REF! | H59: =VLOOKUP($J59,'mapping-Y26'!$F:$L,6,0) -> 40P-55gsm | I59: =VLOOKUP($J59,'mapping-Y26'!$F:$L,5,0) -> 14017864 | J59: 2694-50 | K59: =VLOOKUP($J59,'mapping-Y26'!$F:$L,4,0) -> D269450舒洁湿厕纸家庭装40抽 | L59: =VLOOKUP($J59,'mapping-Y26'!#REF!,4,0) -> #REF! | M59: =VLOOKUP($J59,'mapping-Y26'!$H:$L,2,0) -> D269450舒洁湿厕纸家庭装40抽 | N59: =VLOOKUP($J59,'mapping-Y26'!M:N,3,0) -> #N/A | O59: =VLOOKUP($J59,'mapping-Y26'!$M:$N,5,0) -> #N/A | P59: =VLOOKUP($J59,'mapping-Y26'!$M:$N,6,0) -> #N/A | Q59: =VLOOKUP($J59,'mapping-Y26'!$M:$Q,7,0) -> #N/A | R59: =Q59/O59 -> #N/A | T59: 6.9 | U59: 5.9 | V59: 5 | W59: 0.5 | X59: 0.2 | Y59: 0.3 | Z59: =T59*W59+U59*X59+V59*Y59 -> 6.13 | AA59: 0.15 | AB59: 0.1 | AC59: =Z59*(1-AA59-AB59)/1.13 -> 4.0685841 | AE59: 0.093 | AF59: =AD59*(1-AE59) -> 0 | AG59: =(R59-AF59)/R59 -> #N/A | AH59: 0 | AI59: 0.04 | AJ59: =(AH59+AI59)*AF59/R59+AG59 -> #N/A | AK59: =R59*(1-AJ59) -> #N/A | AL59: =VLOOKUP($J59,#REF!,12,0) -> #REF! | AM59: 0.027 | AN59: =AK59-R59*(AL59+AM59) -> #N/A | AO59: =AN59/AK59 -> #N/A | AP59: 620 | AQ59: =O59*AK59*AP59 -> #N/A | AR59: =AP59*AN59*O59 -> #N/A | AS59: =AP59*Q59 -> #N/A
A60: =F60&J60 -> 京客隆2103-90 | B60: =E60&J60 -> 北京朝批2103-90 | C60: =E60&F60 -> 北京朝批京客隆 | D60: RLKA | E60: 北京朝批 | F60: 京客隆 | G60: =VLOOKUP($J60,'mapping-Y26'!#REF!,2,0) -> #REF! | I60: =VLOOKUP($J60,'mapping-Y26'!$F:$L,5,0) -> 14016868 | J60: 2103-90 | K60: =VLOOKUP($J60,'mapping-Y26'!$F:$L,4,0) -> 210390舒洁小熊印花抽纸3层80抽4包FSC mix70% | L60: =VLOOKUP($J60,'mapping-Y26'!#REF!,4,0) -> #REF! | M60: =VLOOKUP($J60,'mapping-Y26'!$H:$L,2,0) -> 210390舒洁小熊印花抽纸3层80抽4包FSC mix70% | N60: =VLOOKUP($J60,'mapping-Y26'!M:N,3,0) -> #N/A | O60: =VLOOKUP($J60,'mapping-Y26'!$M:$N,5,0) -> #N/A | P60: =VLOOKUP($J60,'mapping-Y26'!$M:$N,6,0) -> #N/A | Q60: =VLOOKUP($J60,'mapping-Y26'!$M:$Q,7,0) -> #N/A | R60: =Q60/O60 -> #N/A | T60: 14.9 | U60: 12.9 | V60: 9.9 | W60: 0.2 | X60: 0.6 | Y60: 0.2 | Z60: =T60*W60+U60*X60+V60*Y60 -> 12.7 | AA60: 0.15 | AB60: 0.1 | AC60: =Z60*(1-AA60-AB60)/1.13 -> 8.4292035 | AE60: 0.093 | AF60: =AD60*(1-AE60) -> 0 | AG60: =(R60-AF60)/R60 -> #N/A | AH60: 0 | AI60: 0.04 | AJ60: =(AH60+AI60)*AF60/R60+AG60 -> #N/A | AK60: =R60*(1-AJ60) -> #N/A | AL60: =VLOOKUP($J60,#REF!,12,0) -> #REF! | AM60: 0.027 | AN60: =AK60-R60*(AL60+AM60) -> #N/A | AO60: =AN60/AK60 -> #N/A | AP60: 420 | AQ60: =O60*AK60*AP60 -> #N/A | AR60: =AP60*AN60*O60 -> #N/A | AS60: =AP60*Q60 -> #N/A
A61: =F61&J61 -> 京客隆2701-90 | B61: =E61&J61 -> 北京朝批2701-90 | C61: =E61&F61 -> 北京朝批京客隆 | D61: RLKA | E61: 北京朝批 | F61: 京客隆 | G61: =VLOOKUP($J61,'mapping-Y26'!#REF!,2,0) -> #REF! | I61: =VLOOKUP($J61,'mapping-Y26'!$F:$L,5,0) -> 14016871 | J61: 2701-90 | K61: =VLOOKUP($J61,'mapping-Y26'!$F:$L,4,0) -> 270190舒洁小熊印花手帕纸3层10包FSC mix70% | L61: =VLOOKUP($J61,'mapping-Y26'!#REF!,4,0) -> #REF! | M61: =VLOOKUP($J61,'mapping-Y26'!$H:$L,2,0) -> 270190舒洁小熊印花手帕纸3层10包FSC mix70% | N61: =VLOOKUP($J61,'mapping-Y26'!M:N,3,0) -> #N/A | O61: =VLOOKUP($J61,'mapping-Y26'!$M:$N,5,0) -> #N/A | P61: =VLOOKUP($J61,'mapping-Y26'!$M:$N,6,0) -> #N/A | Q61: =VLOOKUP($J61,'mapping-Y26'!$M:$Q,7,0) -> #N/A | R61: =Q61/O61 -> #N/A | T61: 7.9 | U61: 7.5 | V61: 6.9 | W61: 0.3 | X61: 0.5 | Y61: 0.2 | Z61: =T61*W61+U61*X61+V61*Y61 -> 7.5 | AA61: 0.15 | AB61: 0.1 | AC61: =Z61*(1-AA61-AB61)/1.13 -> 4.9778761 | AE61: 0.093 | AF61: =AD61*(1-AE61) -> 0 | AG61: =(R61-AF61)/R61 -> #N/A | AH61: 0 | AI61: 0.04 | AJ61: =(AH61+AI61)*AF61/R61+AG61 -> #N/A | AK61: =R61*(1-AJ61) -> #N/A | AL61: =VLOOKUP($J61,#REF!,12,0) -> #REF! | AM61: 0.027 | AN61: =AK61-R61*(AL61+AM61) -> #N/A | AO61: =AN61/AK61 -> #N/A | AP61: 300 | AQ61: =O61*AK61*AP61 -> #N/A | AR61: =AP61*AN61*O61 -> #N/A | AS61: =AP61*Q61 -> #N/A
A62: =F62&J62 -> 超市发2694-50 | B62: =E62&J62 -> 北京朝批2694-50 | C62: =E62&F62 -> 北京朝批超市发 | D62: RLKA | E62: 北京朝批 | F62: 超市发 | G62: =VLOOKUP($J62,'mapping-Y26'!#REF!,2,0) -> #REF! | H62: =VLOOKUP($J62,'mapping-Y26'!$F:$L,6,0) -> 40P-55gsm | I62: =VLOOKUP($J62,'mapping-Y26'!$F:$L,5,0) -> 14017864 | J62: 2694-50 | K62: =VLOOKUP($J62,'mapping-Y26'!$F:$L,4,0) -> D269450舒洁湿厕纸家庭装40抽 | L62: =VLOOKUP($J62,'mapping-Y26'!#REF!,4,0) -> #REF! | M62: =VLOOKUP($J62,'mapping-Y26'!$H:$L,2,0) -> D269450舒洁湿厕纸家庭装40抽 | N62: =VLOOKUP($J62,'mapping-Y26'!M:N,3,0) -> #N/A | O62: =VLOOKUP($J62,'mapping-Y26'!$M:$N,5,0) -> #N/A | P62: =VLOOKUP($J62,'mapping-Y26'!$M:$N,6,0) -> #N/A | Q62: =VLOOKUP($J62,'mapping-Y26'!$M:$Q,7,0) -> #N/A | R62: =Q62/O62 -> #N/A | T62: 6.9 | U62: 5.9 | V62: 5 | W62: 0.5 | X62: 0.35 | Y62: 0.15 | Z62: =T62*W62+U62*X62+V62*Y62 -> 6.265 | AA62: 0.15 | AB62: 0.1 | AC62: =Z62*(1-AA62-AB62)/1.13 -> 4.1581858 | AE62: 0.093 | AF62: =AD62*(1-AE62) -> 0 | AG62: =(R62-AF62)/R62 -> #N/A | AH62: 0 | AI62: 0.04 | AJ62: =(AH62+AI62)*AF62/R62+AG62 -> #N/A | AK62: =R62*(1-AJ62) -> #N/A | AL62: =VLOOKUP($J62,#REF!,12,0) -> #REF! | AM62: 0.027 | AN62: =AK62-R62*(AL62+AM62) -> #N/A | AO62: =AN62/AK62 -> #N/A | AP62: 500 | AQ62: =O62*AK62*AP62 -> #N/A | AR62: =AP62*AN62*O62 -> #N/A | AS62: =AP62*Q62 -> #N/A
A63: =F63&J63 -> 首航2694-50 | B63: =E63&J63 -> 北京朝批2694-50 | C63: =E63&F63 -> 北京朝批首航 | D63: RLKA | E63: 北京朝批 | F63: 首航 | G63: =VLOOKUP($J63,'mapping-Y26'!#REF!,2,0) -> #REF! | H63: =VLOOKUP($J63,'mapping-Y26'!$F:$L,6,0) -> 40P-55gsm | I63: =VLOOKUP($J63,'mapping-Y26'!$F:$L,5,0) -> 14017864 | J63: 2694-50 | K63: =VLOOKUP($J63,'mapping-Y26'!$F:$L,4,0) -> D269450舒洁湿厕纸家庭装40抽 | L63: =VLOOKUP($J63,'mapping-Y26'!#REF!,4,0) -> #REF! | M63: =VLOOKUP($J63,'mapping-Y26'!$H:$L,2,0) -> D269450舒洁湿厕纸家庭装40抽 | N63: =VLOOKUP($J63,'mapping-Y26'!M:N,3,0) -> #N/A | O63: =VLOOKUP($J63,'mapping-Y26'!$M:$N,5,0) -> #N/A | P63: =VLOOKUP($J63,'mapping-Y26'!$M:$N,6,0) -> #N/A | Q63: =VLOOKUP($J63,'mapping-Y26'!$M:$Q,7,0) -> #N/A | R63: =Q63/O63 -> #N/A | T63: 6.9 | U63: 5.9 | V63: 5 | W63: 0.5 | X63: 0.35 | Y63: 0.15 | Z63: =T63*W63+U63*X63+V63*Y63 -> 6.265 | AA63: 0.15 | AB63: 0.1 | AC63: =Z63*(1-AA63-AB63)/1.13 -> 4.1581858 | AE63: 0.093 | AF63: =AD63*(1-AE63) -> 0 | AG63: =(R63-AF63)/R63 -> #N/A | AH63: 0 | AI63: 0.04 | AJ63: =(AH63+AI63)*AF63/R63+AG63 -> #N/A | AK63: =R63*(1-AJ63) -> #N/A | AL63: =VLOOKUP($J63,#REF!,12,0) -> #REF! | AM63: 0.027 | AN63: =AK63-R63*(AL63+AM63) -> #N/A | AO63: =AN63/AK63 -> #N/A | AP63: 150 | AQ63: =O63*AK63*AP63 -> #N/A | AR63: =AP63*AN63*O63 -> #N/A | AS63: =AP63*Q63 -> #N/A
A64: =F64&J64 -> 首航2660-10 | B64: =E64&J64 -> 北京朝批2660-10 | C64: =E64&F64 -> 北京朝批首航 | D64: RLKA | E64: 北京朝批 | F64: 首航 | G64: =VLOOKUP($J64,'mapping-Y26'!#REF!,2,0) -> #REF! | H64: =VLOOKUP($J64,'mapping-Y26'!$F:$L,6,0) -> 80P | I64: =VLOOKUP($J64,'mapping-Y26'!$F:$L,5,0) -> 14017865 | J64: 2660-10 | K64: =VLOOKUP($J64,'mapping-Y26'!$F:$L,4,0) -> 266010舒洁湿厕纸80片 | L64: =VLOOKUP($J64,'mapping-Y26'!#REF!,4,0) -> #REF! | M64: =VLOOKUP($J64,'mapping-Y26'!$H:$L,2,0) -> 266010舒洁湿厕纸80片 | N64: =VLOOKUP($J64,'mapping-Y26'!M:N,3,0) -> #N/A | O64: =VLOOKUP($J64,'mapping-Y26'!$M:$N,5,0) -> #N/A | P64: =VLOOKUP($J64,'mapping-Y26'!$M:$N,6,0) -> #N/A | Q64: =VLOOKUP($J64,'mapping-Y26'!$M:$Q,7,0) -> #N/A | R64: =Q64/O64 -> #N/A | T64: 9.9 | U64: 8.9 | V64: 8.9 | W64: 0.6 | X64: 0.4 | Y64: 0 | Z64: =T64*W64+U64*X64+V64*Y64 -> 9.5 | AA64: 0.15 | AB64: 0.1 | AC64: =Z64*(1-AA64-AB64)/1.13 -> 6.3053097 | AE64: 0.093 | AF64: =AD64*(1-AE64) -> 0 | AG64: =(R64-AF64)/R64 -> #N/A | AH64: 0 | AI64: 0.04 | AJ64: =(AH64+AI64)*AF64/R64+AG64 -> #N/A | AK64: =R64*(1-AJ64) -> #N/A | AL64: =VLOOKUP($J64,#REF!,12,0) -> #REF! | AM64: 0.027 | AN64: =AK64-R64*(AL64+AM64) -> #N/A | AO64: =AN64/AK64 -> #N/A | AP64: 200 | AQ64: =O64*AK64*AP64 -> #N/A | AR64: =AP64*AN64*O64 -> #N/A | AS64: =AP64*Q64 -> #N/A
A65: =F65&J65 -> 全家2694-50 | B65: =E65&J65 -> 北京朝批2694-50 | C65: =E65&F65 -> 北京朝批全家 | D65: RLKA | E65: 北京朝批 | F65: 全家 | G65: =VLOOKUP($J65,'mapping-Y26'!#REF!,2,0) -> #REF! | H65: =VLOOKUP($J65,'mapping-Y26'!$F:$L,6,0) -> 40P-55gsm | I65: =VLOOKUP($J65,'mapping-Y26'!$F:$L,5,0) -> 14017864 | J65: 2694-50 | K65: =VLOOKUP($J65,'mapping-Y26'!$F:$L,4,0) -> D269450舒洁湿厕纸家庭装40抽 | L65: =VLOOKUP($J65,'mapping-Y26'!#REF!,4,0) -> #REF! | M65: =VLOOKUP($J65,'mapping-Y26'!$H:$L,2,0) -> D269450舒洁湿厕纸家庭装40抽 | N65: =VLOOKUP($J65,'mapping-Y26'!M:N,3,0) -> #N/A | O65: =VLOOKUP($J65,'mapping-Y26'!$M:$N,5,0) -> #N/A | P65: =VLOOKUP($J65,'mapping-Y26'!$M:$N,6,0) -> #N/A | Q65: =VLOOKUP($J65,'mapping-Y26'!$M:$Q,7,0) -> #N/A | R65: =Q65/O65 -> #N/A | T65: 11.925 | U65: 8.45 | V65: 8.45 | W65: 0.5 | X65: 0.5 | Y65: 0 | Z65: =T65*W65+U65*X65+V65*Y65 -> 10.1875 | AA65: 0.367 | AB65: 0.07 | AC65: =Z65*(1-AA65-AB65)/1.13 -> 5.075719 | AE65: 0.093 | AF65: =AD65*(1-AE65) -> 0 | AG65: =(R65-AF65)/R65 -> #N/A | AH65: 0 | AI65: 0.04 | AJ65: =(AH65+AI65)*AF65/R65+AG65 -> #N/A | AK65: =R65*(1-AJ65) -> #N/A | AL65: =VLOOKUP($J65,#REF!,12,0) -> #REF! | AM65: 0.027 | AN65: =AK65-R65*(AL65+AM65) -> #N/A | AO65: =AN65/AK65 -> #N/A | AP65: 300 | AQ65: =O65*AK65*AP65 -> #N/A | AR65: =AP65*AN65*O65 -> #N/A | AS65: =AP65*Q65 -> #N/A
A66: =F66&J66 -> 朝批others2694-50 | B66: =E66&J66 -> 北京朝批2694-50 | C66: =E66&F66 -> 北京朝批朝批others | D66: RLKA | E66: 北京朝批 | F66: 朝批others | G66: =VLOOKUP($J66,'mapping-Y26'!#REF!,2,0) -> #REF! | H66: =VLOOKUP($J66,'mapping-Y26'!$F:$L,6,0) -> 40P-55gsm | I66: =VLOOKUP($J66,'mapping-Y26'!$F:$L,5,0) -> 14017864 | J66: 2694-50 | K66: =VLOOKUP($J66,'mapping-Y26'!$F:$L,4,0) -> D269450舒洁湿厕纸家庭装40抽 | L66: =VLOOKUP($J66,'mapping-Y26'!#REF!,4,0) -> #REF! | M66: =VLOOKUP($J66,'mapping-Y26'!$H:$L,2,0) -> D269450舒洁湿厕纸家庭装40抽 | N66: =VLOOKUP($J66,'mapping-Y26'!M:N,3,0) -> #N/A | O66: =VLOOKUP($J66,'mapping-Y26'!$M:$N,5,0) -> #N/A | P66: =VLOOKUP($J66,'mapping-Y26'!$M:$N,6,0) -> #N/A | Q66: =VLOOKUP($J66,'mapping-Y26'!$M:$Q,7,0) -> #N/A | R66: =Q66/O66 -> #N/A | U66: 6.9 | V66: 5.9 | X66: 0.6 | Y66: 0.4 | Z66: =T66*W66+U66*X66+V66*Y66 -> 6.5 | AA66: 0.15 | AB66: 0.05 | AC66: =Z66*(1-AA66-AB66)/1.13 -> 4.6017699 | AE66: 0.093 | AF66: =AD66*(1-AE66) -> 0 | AG66: =(R66-AF66)/R66 -> #N/A | AH66: 0 | AI66: 0.04 | AJ66: =(AH66+AI66)*AF66/R66+AG66 -> #N/A | AK66: =R66*(1-AJ66) -> #N/A | AL66: =VLOOKUP($J66,#REF!,12,0) -> #REF! | AM66: 0.027 | AN66: =AK66-R66*(AL66+AM66) -> #N/A | AO66: =AN66/AK66 -> #N/A | AP66: 300 | AQ66: =O66*AK66*AP66 -> #N/A | AR66: =AP66*AN66*O66 -> #N/A | AS66: =AP66*Q66 -> #N/A
A67: =F67&J67 -> 朝批others2701-90 | B67: =E67&J67 -> 北京朝批2701-90 | C67: =E67&F67 -> 北京朝批朝批others | D67: RLKA | E67: 北京朝批 | F67: 朝批others | G67: =VLOOKUP($J67,'mapping-Y26'!#REF!,2,0) -> #REF! | I67: =VLOOKUP($J67,'mapping-Y26'!$F:$L,5,0) -> 14016871 | J67: 2701-90 | K67: =VLOOKUP($J67,'mapping-Y26'!$F:$L,4,0) -> 270190舒洁小熊印花手帕纸3层10包FSC mix70% | L67: =VLOOKUP($J67,'mapping-Y26'!#REF!,4,0) -> #REF! | M67: =VLOOKUP($J67,'mapping-Y26'!$H:$L,2,0) -> 270190舒洁小熊印花手帕纸3层10包FSC mix70% | N67: =VLOOKUP($J67,'mapping-Y26'!M:N,3,0) -> #N/A | O67: =VLOOKUP($J67,'mapping-Y26'!$M:$N,5,0) -> #N/A | P67: =VLOOKUP($J67,'mapping-Y26'!$M:$N,6,0) -> #N/A | Q67: =VLOOKUP($J67,'mapping-Y26'!$M:$Q,7,0) -> #N/A | R67: =Q67/O67 -> #N/A | U67: 6.9 | V67: 5.9 | X67: 0.7 | Y67: 0.3 | Z67: =T67*W67+U67*X67+V67*Y67 -> 6.6 | AA67: 0.15 | AB67: 0.05 | AC67: =Z67*(1-AA67-AB67)/1.13 -> 4.6725664 | AE67: 0.093 | AF67: =AD67*(1-AE67) -> 0 | AG67: =(R67-AF67)/R67 -> #N/A | AH67: 0 | AI67: 0.04 | AJ67: =(AH67+AI67)*AF67/R67+AG67 -> #N/A | AK67: =R67*(1-AJ67) -> #N/A | AL67: =VLOOKUP($J67,#REF!,12,0) -> #REF! | AM67: 0.027 | AN67: =AK67-R67*(AL67+AM67) -> #N/A | AO67: =AN67/AK67 -> #N/A | AP67: 180 | AQ67: =O67*AK67*AP67 -> #N/A | AR67: =AP67*AN67*O67 -> #N/A | AS67: =AP67*Q67 -> #N/A
A68: =F68&J68 -> 朝批others2660-10 | B68: =E68&J68 -> 北京朝批2660-10 | C68: =E68&F68 -> 北京朝批朝批others | D68: RLKA | E68: 北京朝批 | F68: 朝批others | G68: =VLOOKUP($J68,'mapping-Y26'!#REF!,2,0) -> #REF! | H68: =VLOOKUP($J68,'mapping-Y26'!$F:$L,6,0) -> 80P | I68: =VLOOKUP($J68,'mapping-Y26'!$F:$L,5,0) -> 14017865 | J68: 2660-10 | K68: =VLOOKUP($J68,'mapping-Y26'!$F:$L,4,0) -> 266010舒洁湿厕纸80片 | L68: =VLOOKUP($J68,'mapping-Y26'!#REF!,4,0) -> #REF! | M68: =VLOOKUP($J68,'mapping-Y26'!$H:$L,2,0) -> 266010舒洁湿厕纸80片 | N68: =VLOOKUP($J68,'mapping-Y26'!M:N,3,0) -> #N/A | O68: =VLOOKUP($J68,'mapping-Y26'!$M:$N,5,0) -> #N/A | P68: =VLOOKUP($J68,'mapping-Y26'!$M:$N,6,0) -> #N/A | Q68: =VLOOKUP($J68,'mapping-Y26'!$M:$Q,7,0) -> #N/A | R68: =Q68/O68 -> #N/A | T68: 12.9 | U68: 9.9 | V68: 8.9 | W68: 0.1 | X68: 0.6 | Y68: 0.3 | Z68: =T68*W68+U68*X68+V68*Y68 -> 9.9 | AA68: 0.15 | AB68: 0.05 | AC68: =Z68*(1-AA68-AB68)/1.13 -> 7.0088496 | AE68: 0.093 | AF68: =AD68*(1-AE68) -> 0 | AG68: =(R68-AF68)/R68 -> #N/A | AH68: 0 | AI68: 0.04 | AJ68: =(AH68+AI68)*AF68/R68+AG68 -> #N/A | AK68: =R68*(1-AJ68) -> #N/A | AL68: =VLOOKUP($J68,#REF!,12,0) -> #REF! | AM68: 0.027 | AN68: =AK68-R68*(AL68+AM68) -> #N/A | AO68: =AN68/AK68 -> #N/A | AP68: 120 | AQ68: =O68*AK68*AP68 -> #N/A | AR68: =AP68*AN68*O68 -> #N/A | AS68: =AP68*Q68 -> #N/A
A69: =F69&J69 -> 朝批others2107-61 | B69: =E69&J69 -> 北京朝批2107-61 | C69: =E69&F69 -> 北京朝批朝批others | D69: RLKA | E69: 北京朝批 | F69: 朝批others | G69: =VLOOKUP($J69,'mapping-Y26'!#REF!,2,0) -> #REF! | I69: =VLOOKUP($J69,'mapping-Y26'!$F:$L,5,0) -> 14014470 | J69: 2107-61 | K69: =VLOOKUP($J69,'mapping-Y26'!$F:$L,4,0) -> 210761舒洁卡通系列抽纸200抽3包 FSC mix70% | L69: =VLOOKUP($J69,'mapping-Y26'!#REF!,4,0) -> #REF! | M69: =VLOOKUP($J69,'mapping-Y26'!$H:$L,2,0) -> 210761舒洁卡通系列抽纸200抽3包 FSC mix70% | N69: =VLOOKUP($J69,'mapping-Y26'!M:N,3,0) -> #N/A | O69: =VLOOKUP($J69,'mapping-Y26'!$M:$N,5,0) -> #N/A | P69: =VLOOKUP($J69,'mapping-Y26'!$M:$N,6,0) -> #N/A | Q69: =VLOOKUP($J69,'mapping-Y26'!$M:$Q,7,0) -> #N/A | R69: =Q69/O69 -> #N/A | T69: 21.9 | U69: 19.9 | V69: 17.9 | W69: 0.1 | X69: 0.5 | Y69: 0.4 | Z69: =T69*W69+U69*X69+V69*Y69 -> 19.3 | AA69: 0.15 | AB69: 0.05 | AC69: =Z69*(1-AA69-AB69)/1.13 -> 13.663717 | AE69: 0.093 | AF69: =AD69*(1-AE69) -> 0 | AG69: =(R69-AF69)/R69 -> #N/A | AH69: 0 | AI69: 0.04 | AJ69: =(AH69+AI69)*AF69/R69+AG69 -> #N/A | AK69: =R69*(1-AJ69) -> #N/A | AL69: =VLOOKUP($J69,#REF!,12,0) -> #REF! | AM69: 0.027 | AN69: =AK69-R69*(AL69+AM69) -> #N/A | AO69: =AN69/AK69 -> #N/A | AP69: 80 | AQ69: =O69*AK69*AP69 -> #N/A | AR69: =AP69*AN69*O69 -> #N/A | AS69: =AP69*Q69 -> #N/A
A70: =F70&J70 -> 7112694-50 | B70: =E70&J70 -> 北京宝诚恒信2694-50 | C70: =E70&F70 -> 北京宝诚恒信711 | D70: RLKA | E70: 北京宝诚恒信 | F70: 711 | G70: =VLOOKUP($J70,'mapping-Y26'!#REF!,2,0) -> #REF! | H70: =VLOOKUP($J70,'mapping-Y26'!$F:$L,6,0) -> 40P-55gsm | I70: =VLOOKUP($J70,'mapping-Y26'!$F:$L,5,0) -> 14017864 | J70: 2694-50 | K70: =VLOOKUP($J70,'mapping-Y26'!$F:$L,4,0) -> D269450舒洁湿厕纸家庭装40抽 | L70: =VLOOKUP($J70,'mapping-Y26'!#REF!,4,0) -> #REF! | M70: =VLOOKUP($J70,'mapping-Y26'!$H:$L,2,0) -> D269450舒洁湿厕纸家庭装40抽 | N70: =VLOOKUP($J70,'mapping-Y26'!M:N,3,0) -> #N/A | O70: =VLOOKUP($J70,'mapping-Y26'!$M:$N,5,0) -> #N/A | P70: =VLOOKUP($J70,'mapping-Y26'!$M:$N,6,0) -> #N/A | Q70: =VLOOKUP($J70,'mapping-Y26'!$M:$Q,7,0) -> #N/A | R70: =Q70/O70 -> #N/A | T70: 9.45 | U70: 7.25 | V70: 7.25 | W70: 0.8 | X70: 0.2 | Z70: =T70*W70+U70*X70+V70*Y70 -> 9.01 | AA70: 0.4 | AB70: 0.0452 | AC70: =Z70*(1-AA70-AB70)/1.13 -> 4.4236708 | AE70: 0.232 | AF70: =AD70*(1-AE70) -> 0 | AG70: =(R70-AF70)/R70 -> #N/A | AH70: 0 | AI70: 0.04 | AJ70: =(AH70+AI70)*AF70/R70+AG70 -> #N/A | AK70: =R70*(1-AJ70) -> #N/A | AL70: =VLOOKUP($J70,#REF!,12,0) -> #REF! | AM70: 0.027 | AN70: =AK70-R70*(AL70+AM70) -> #N/A | AO70: =AN70/AK70 -> #N/A | AP70: 1100 | AQ70: =O70*AK70*AP70 -> #N/A | AR70: =AP70*AN70*O70 -> #N/A | AS70: =AP70*Q70 -> #N/A
A71: =F71&J71 -> 罗森2694-50 | B71: =E71&J71 -> 北京宝诚恒信2694-50 | C71: =E71&F71 -> 北京宝诚恒信罗森 | D71: RLKA | E71: 北京宝诚恒信 | F71: 罗森 | G71: =VLOOKUP($J71,'mapping-Y26'!#REF!,2,0) -> #REF! | H71: =VLOOKUP($J71,'mapping-Y26'!$F:$L,6,0) -> 40P-55gsm | I71: =VLOOKUP($J71,'mapping-Y26'!$F:$L,5,0) -> 14017864 | J71: 2694-50 | K71: =VLOOKUP($J71,'mapping-Y26'!$F:$L,4,0) -> D269450舒洁湿厕纸家庭装40抽 | L71: =VLOOKUP($J71,'mapping-Y26'!#REF!,4,0) -> #REF! | M71: =VLOOKUP($J71,'mapping-Y26'!$H:$L,2,0) -> D269450舒洁湿厕纸家庭装40抽 | N71: =VLOOKUP($J71,'mapping-Y26'!M:N,3,0) -> #N/A | O71: =VLOOKUP($J71,'mapping-Y26'!$M:$N,5,0) -> #N/A | P71: =VLOOKUP($J71,'mapping-Y26'!$M:$N,6,0) -> #N/A | Q71: =VLOOKUP($J71,'mapping-Y26'!$M:$Q,7,0) -> #N/A | R71: =Q71/O71 -> #N/A | T71: 11.92 | U71: 8.45 | V71: 8.45 | W71: 0.5 | X71: 0.5 | Y71: 0 | Z71: =T71*W71+U71*X71+V71*Y71 -> 10.185 | AA71: 0.342 | AB71: 0.075 | AC71: =Z71*(1-AA71-AB71)/1.13 -> 5.2547389 | AE71: 0.185 | AF71: =AD71*(1-AE71) -> 0 | AG71: =(R71-AF71)/R71 -> #N/A | AH71: 0 | AI71: 0.04 | AJ71: =(AH71+AI71)*AF71/R71+AG71 -> #N/A | AK71: =R71*(1-AJ71) -> #N/A | AL71: =VLOOKUP($J71,#REF!,12,0) -> #REF! | AM71: 0.027 | AN71: =AK71-R71*(AL71+AM71) -> #N/A | AO71: =AN71/AK71 -> #N/A | AP71: 1100 | AQ71: =O71*AK71*AP71 -> #N/A | AR71: =AP71*AN71*O71 -> #N/A | AS71: =AP71*Q71 -> #N/A
A72: =F72&J72 -> 罗森2103-90 | B72: =E72&J72 -> 北京宝诚恒信2103-90 | C72: =E72&F72 -> 北京宝诚恒信罗森 | D72: RLKA | E72: 北京宝诚恒信 | F72: 罗森 | G72: =VLOOKUP($J72,'mapping-Y26'!#REF!,2,0) -> #REF! | I72: =VLOOKUP($J72,'mapping-Y26'!$F:$L,5,0) -> 14016868 | J72: 2103-90 | K72: =VLOOKUP($J72,'mapping-Y26'!$F:$L,4,0) -> 210390舒洁小熊印花抽纸3层80抽4包FSC mix70% | L72: =VLOOKUP($J72,'mapping-Y26'!#REF!,4,0) -> #REF! | M72: =VLOOKUP($J72,'mapping-Y26'!$H:$L,2,0) -> 210390舒洁小熊印花抽纸3层80抽4包FSC mix70% | N72: =VLOOKUP($J72,'mapping-Y26'!M:N,3,0) -> #N/A | O72: =VLOOKUP($J72,'mapping-Y26'!$M:$N,5,0) -> #N/A | P72: =VLOOKUP($J72,'mapping-Y26'!$M:$N,6,0) -> #N/A | Q72: =VLOOKUP($J72,'mapping-Y26'!$M:$Q,7,0) -> #N/A | R72: =Q72/O72 -> #N/A | T72: 20 | U72: 15 | V72: 12 | W72: 0.6 | X72: 0.3 | Y72: 0.1 | Z72: =T72*W72+U72*X72+V72*Y72 -> 17.7 | AA72: 0.318 | AB72: 0.075 | AC72: =Z72*(1-AA72-AB72)/1.13 -> 9.5078761 | AE72: 0.185 | AF72: =AD72*(1-AE72) -> 0 | AG72: =(R72-AF72)/R72 -> #N/A | AH72: 0 | AI72: 0.04 | AJ72: =(AH72+AI72)*AF72/R72+AG72 -> #N/A | AK72: =R72*(1-AJ72) -> #N/A | AL72: =VLOOKUP($J72,#REF!,12,0) -> #REF! | AM72: 0.027 | AN72: =AK72-R72*(AL72+AM72) -> #N/A | AO72: =AN72/AK72 -> #N/A | AP72: 250 | AQ72: =O72*AK72*AP72 -> #N/A | AR72: =AP72*AN72*O72 -> #N/A | AS72: =AP72*Q72 -> #N/A
A73: =F73&J73 -> 罗森2613-00 | B73: =E73&J73 -> 北京宝诚恒信2613-00 | C73: =E73&F73 -> 北京宝诚恒信罗森 | D73: RLKA | E73: 北京宝诚恒信 | F73: 罗森 | G73: =VLOOKUP($J73,'mapping-Y26'!#REF!,2,0) -> #REF! | I73: =VLOOKUP($J73,'mapping-Y26'!$F:$L,5,0) -> 14004626 | J73: 2613-00 | K73: =VLOOKUP($J73,'mapping-Y26'!$F:$L,4,0) -> 261300舒洁无香湿巾单包装 | L73: =VLOOKUP($J73,'mapping-Y26'!#REF!,4,0) -> #REF! | M73: =VLOOKUP($J73,'mapping-Y26'!$H:$L,2,0) -> 261300舒洁无香湿巾单包装 | N73: =VLOOKUP($J73,'mapping-Y26'!M:N,3,0) -> #N/A | O73: =VLOOKUP($J73,'mapping-Y26'!$M:$N,5,0) -> #N/A | P73: =VLOOKUP($J73,'mapping-Y26'!$M:$N,6,0) -> #N/A | Q73: =VLOOKUP($J73,'mapping-Y26'!$M:$Q,7,0) -> #N/A | R73: =Q73/O73 -> #N/A | T73: 5.5 | U73: 5.5 | V73: 5.5 | W73: 1 | Z73: =T73*W73+U73*X73+V73*Y73 -> 5.5 | AA73: 0.356 | AB73: 0.075 | AC73: =Z73*(1-AA73-AB73)/1.13 -> 2.769469 | AE73: 0.185 | AF73: =AD73*(1-AE73) -> 0 | AG73: =(R73-AF73)/R73 -> #N/A | AH73: 0 | AI73: 0.04 | AJ73: =(AH73+AI73)*AF73/R73+AG73 -> #N/A | AK73: =R73*(1-AJ73) -> #N/A | AL73: =VLOOKUP($J73,#REF!,12,0) -> #REF! | AM73: 0.027 | AN73: =AK73-R73*(AL73+AM73) -> #N/A | AO73: =AN73/AK73 -> #N/A | AP73: 600 | AQ73: =O73*AK73*AP73 -> #N/A | AR73: =AP73*AN73*O73 -> #N/A | AS73: =AP73*Q73 -> #N/A
A74: =F74&J74 -> 罗森2701-90 | B74: =E74&J74 -> 北京宝诚恒信2701-90 | C74: =E74&F74 -> 北京宝诚恒信罗森 | D74: RLKA | E74: 北京宝诚恒信 | F74: 罗森 | G74: =VLOOKUP($J74,'mapping-Y26'!#REF!,2,0) -> #REF! | I74: =VLOOKUP($J74,'mapping-Y26'!$F:$L,5,0) -> 14016871 | J74: 2701-90 | K74: =VLOOKUP($J74,'mapping-Y26'!$F:$L,4,0) -> 270190舒洁小熊印花手帕纸3层10包FSC mix70% | L74: =VLOOKUP($J74,'mapping-Y26'!#REF!,4,0) -> #REF! | M74: =VLOOKUP($J74,'mapping-Y26'!$H:$L,2,0) -> 270190舒洁小熊印花手帕纸3层10包FSC mix70% | N74: =VLOOKUP($J74,'mapping-Y26'!M:N,3,0) -> #N/A | O74: =VLOOKUP($J74,'mapping-Y26'!$M:$N,5,0) -> #N/A | P74: =VLOOKUP($J74,'mapping-Y26'!$M:$N,6,0) -> #N/A | Q74: =VLOOKUP($J74,'mapping-Y26'!$M:$Q,7,0) -> #N/A | R74: =Q74/O74 -> #N/A | T74: 15 | U74: 15 | V74: 15 | W74: 1 | X74: 0 | Y74: 0 | Z74: =T74*W74+U74*X74+V74*Y74 -> 15 | AA74: 0.45 | AB74: 0.075 | AC74: =Z74*(1-AA74-AB74)/1.13 -> 6.3053097 | AE74: 0.185 | AF74: =AD74*(1-AE74) -> 0 | AG74: =(R74-AF74)/R74 -> #N/A | AH74: 0 | AI74: 0.04 | AJ74: =(AH74+AI74)*AF74/R74+AG74 -> #N/A | AK74: =R74*(1-AJ74) -> #N/A | AL74: =VLOOKUP($J74,#REF!,12,0) -> #REF! | AM74: 0.027 | AN74: =AK74-R74*(AL74+AM74) -> #N/A | AO74: =AN74/AK74 -> #N/A | AP74: 100 | AQ74: =O74*AK74*AP74 -> #N/A | AR74: =AP74*AN74*O74 -> #N/A | AS74: =AP74*Q74 -> #N/A
A75: =F75&J75 -> 宝诚others2694-50 | B75: =E75&J75 -> 北京宝诚恒信2694-50 | C75: =E75&F75 -> 北京宝诚恒信宝诚others | D75: RLKA | E75: 北京宝诚恒信 | F75: 宝诚others | G75: =VLOOKUP($J75,'mapping-Y26'!#REF!,2,0) -> #REF! | H75: =VLOOKUP($J75,'mapping-Y26'!$F:$L,6,0) -> 40P-55gsm | I75: =VLOOKUP($J75,'mapping-Y26'!$F:$L,5,0) -> 14017864 | J75: 2694-50 | K75: =VLOOKUP($J75,'mapping-Y26'!$F:$L,4,0) -> D269450舒洁湿厕纸家庭装40抽 | L75: =VLOOKUP($J75,'mapping-Y26'!#REF!,4,0) -> #REF! | M75: =VLOOKUP($J75,'mapping-Y26'!$H:$L,2,0) -> D269450舒洁湿厕纸家庭装40抽 | N75: =VLOOKUP($J75,'mapping-Y26'!M:N,3,0) -> #N/A | O75: =VLOOKUP($J75,'mapping-Y26'!$M:$N,5,0) -> #N/A | P75: =VLOOKUP($J75,'mapping-Y26'!$M:$N,6,0) -> #N/A | Q75: =VLOOKUP($J75,'mapping-Y26'!$M:$Q,7,0) -> #N/A | R75: =Q75/O75 -> #N/A | T75: 7.9 | U75: 6.9 | V75: 5.9 | W75: 0.1 | X75: 0.6 | Y75: 0.3 | Z75: =T75*W75+U75*X75+V75*Y75 -> 6.7 | AA75: 0.15 | AB75: 0 | AC75: =Z75*(1-AA75-AB75)/1.13 -> 5.039823 | AE75: 0.15 | AF75: =AD75*(1-AE75) -> 0 | AG75: =(R75-AF75)/R75 -> #N/A | AH75: 0 | AI75: 0.04 | AJ75: =(AH75+AI75)*AF75/R75+AG75 -> #N/A | AK75: =R75*(1-AJ75) -> #N/A | AL75: =VLOOKUP($J75,#REF!,12,0) -> #REF! | AM75: 0.027 | AN75: =AK75-R75*(AL75+AM75) -> #N/A | AO75: =AN75/AK75 -> #N/A | AP75: 150 | AQ75: =O75*AK75*AP75 -> #N/A | AR75: =AP75*AN75*O75 -> #N/A | AS75: =AP75*Q75 -> #N/A
A76: =F76&J76 -> 宝诚others2613-00 | B76: =E76&J76 -> 北京宝诚恒信2613-00 | C76: =E76&F76 -> 北京宝诚恒信宝诚others | D76: RLKA | E76: 北京宝诚恒信 | F76: 宝诚others | G76: =VLOOKUP($J76,'mapping-Y26'!#REF!,2,0) -> #REF! | I76: =VLOOKUP($J76,'mapping-Y26'!$F:$L,5,0) -> 14004626 | J76: 2613-00 | K76: =VLOOKUP($J76,'mapping-Y26'!$F:$L,4,0) -> 261300舒洁无香湿巾单包装 | L76: =VLOOKUP($J76,'mapping-Y26'!#REF!,4,0) -> #REF! | M76: =VLOOKUP($J76,'mapping-Y26'!$H:$L,2,0) -> 261300舒洁无香湿巾单包装 | N76: =VLOOKUP($J76,'mapping-Y26'!M:N,3,0) -> #N/A | O76: =VLOOKUP($J76,'mapping-Y26'!$M:$N,5,0) -> #N/A | P76: =VLOOKUP($J76,'mapping-Y26'!$M:$N,6,0) -> #N/A | Q76: =VLOOKUP($J76,'mapping-Y26'!$M:$Q,7,0) -> #N/A | R76: =Q76/O76 -> #N/A | T76: 4.9 | U76: 3.9 | V76: 2.9 | W76: 0.05 | X76: 0.6 | Y76: 0.35 | Z76: =T76*W76+U76*X76+V76*Y76 -> 3.6 | AA76: 0.15 | AB76: 0 | AC76: =Z76*(1-AA76-AB76)/1.13 -> 2.7079646 | AE76: 0.15 | AF76: =AD76*(1-AE76) -> 0 | AG76: =(R76-AF76)/R76 -> #N/A | AH76: 0 | AI76: 0.04 | AJ76: =(AH76+AI76)*AF76/R76+AG76 -> #N/A | AK76: =R76*(1-AJ76) -> #N/A | AL76: =VLOOKUP($J76,#REF!,12,0) -> #REF! | AM76: 0.027 | AN76: =AK76-R76*(AL76+AM76) -> #N/A | AO76: =AN76/AK76 -> #N/A | AP76: 50 | AQ76: =O76*AK76*AP76 -> #N/A | AR76: =AP76*AN76*O76 -> #N/A | AS76: =AP76*Q76 -> #N/A
A77: =F77&J77 -> 宝诚others2103-90 | B77: =E77&J77 -> 北京宝诚恒信2103-90 | C77: =E77&F77 -> 北京宝诚恒信宝诚others | D77: RLKA | E77: 北京宝诚恒信 | F77: 宝诚others | G77: =VLOOKUP($J77,'mapping-Y26'!#REF!,2,0) -> #REF! | I77: =VLOOKUP($J77,'mapping-Y26'!$F:$L,5,0) -> 14016868 | J77: 2103-90 | K77: =VLOOKUP($J77,'mapping-Y26'!$F:$L,4,0) -> 210390舒洁小熊印花抽纸3层80抽4包FSC mix70% | L77: =VLOOKUP($J77,'mapping-Y26'!#REF!,4,0) -> #REF! | M77: =VLOOKUP($J77,'mapping-Y26'!$H:$L,2,0) -> 210390舒洁小熊印花抽纸3层80抽4包FSC mix70% | N77: =VLOOKUP($J77,'mapping-Y26'!M:N,3,0) -> #N/A | O77: =VLOOKUP($J77,'mapping-Y26'!$M:$N,5,0) -> #N/A | P77: =VLOOKUP($J77,'mapping-Y26'!$M:$N,6,0) -> #N/A | Q77: =VLOOKUP($J77,'mapping-Y26'!$M:$Q,7,0) -> #N/A | R77: =Q77/O77 -> #N/A | T77: 15.9 | U77: 13.9 | V77: 11.9 | W77: 0.05 | X77: 0.7 | Y77: 0.25 | Z77: =T77*W77+U77*X77+V77*Y77 -> 13.5 | AA77: 0.15 | AB77: 0 | AC77: =Z77*(1-AA77-AB77)/1.13 -> 10.154867 | AE77: 0.15 | AF77: =AD77*(1-AE77) -> 0 | AG77: =(R77-AF77)/R77 -> #N/A | AH77: 0 | AI77: 0.04 | AJ77: =(AH77+AI77)*AF77/R77+AG77 -> #N/A | AK77: =R77*(1-AJ77) -> #N/A | AL77: =VLOOKUP($J77,#REF!,12,0) -> #REF! | AM77: 0.027 | AN77: =AK77-R77*(AL77+AM77) -> #N/A | AO77: =AN77/AK77 -> #N/A | AP77: 70 | AQ77: =O77*AK77*AP77 -> #N/A | AR77: =AP77*AN77*O77 -> #N/A | AS77: =AP77*Q77 -> #N/A
A78: =F78&J78 -> 罗森2694-50 | B78: =E78&J78 -> 大连达博2694-50 | C78: =E78&F78 -> 大连达博罗森 | D78: RLKA | E78: 大连达博 | F78: 罗森 | G78: =VLOOKUP($J78,'mapping-Y26'!#REF!,2,0) -> #REF! | H78: =VLOOKUP($J78,'mapping-Y26'!$F:$L,6,0) -> 40P-55gsm | I78: =VLOOKUP($J78,'mapping-Y26'!$F:$L,5,0) -> 14017864 | J78: 2694-50 | K78: =VLOOKUP($J78,'mapping-Y26'!$F:$L,4,0) -> D269450舒洁湿厕纸家庭装40抽 | L78: =VLOOKUP($J78,'mapping-Y26'!#REF!,4,0) -> #REF! | M78: =VLOOKUP($J78,'mapping-Y26'!$H:$L,2,0) -> D269450舒洁湿厕纸家庭装40抽 | N78: =VLOOKUP($J78,'mapping-Y26'!M:N,3,0) -> #N/A | O78: =VLOOKUP($J78,'mapping-Y26'!$M:$N,5,0) -> #N/A | P78: =VLOOKUP($J78,'mapping-Y26'!$M:$N,6,0) -> #N/A | Q78: =VLOOKUP($J78,'mapping-Y26'!$M:$Q,7,0) -> #N/A | R78: =Q78/O78 -> #N/A | T78: 11.925 | U78: 8.45 | V78: 8.45 | W78: 0.6 | X78: 0.4 | Y78: 0 | Z78: =T78*W78+U78*X78+V78*Y78 -> 10.535 | AA78: 0.37 | AB78: 0 | AC78: =Z78*(1-AA78-AB78)/1.13 -> 5.8734956 | AE78: 0.3 | AF78: =AD78*(1-AE78) -> 0 | AG78: =(R78-AF78)/R78 -> #N/A | AH78: 0 | AI78: 0.04 | AJ78: =(AH78+AI78)*AF78/R78+AG78 -> #N/A | AK78: =R78*(1-AJ78) -> #N/A | AL78: =VLOOKUP($J78,#REF!,12,0) -> #REF! | AM78: 0.027 | AN78: =AK78-R78*(AL78+AM78) -> #N/A | AO78: =AN78/AK78 -> #N/A | AP78: 600 | AQ78: =O78*AK78*AP78 -> #N/A | AR78: =AP78*AN78*O78 -> #N/A | AS78: =AP78*Q78 -> #N/A
A79: =F79&J79 -> 罗森2103-90 | B79: =E79&J79 -> 大连达博2103-90 | C79: =E79&F79 -> 大连达博罗森 | D79: RLKA | E79: 大连达博 | F79: 罗森 | G79: =VLOOKUP($J79,'mapping-Y26'!#REF!,2,0) -> #REF! | I79: =VLOOKUP($J79,'mapping-Y26'!$F:$L,5,0) -> 14016868 | J79: 2103-90 | K79: =VLOOKUP($J79,'mapping-Y26'!$F:$L,4,0) -> 210390舒洁小熊印花抽纸3层80抽4包FSC mix70% | L79: =VLOOKUP($J79,'mapping-Y26'!#REF!,4,0) -> #REF! | M79: =VLOOKUP($J79,'mapping-Y26'!$H:$L,2,0) -> 210390舒洁小熊印花抽纸3层80抽4包FSC mix70% | N79: =VLOOKUP($J79,'mapping-Y26'!M:N,3,0) -> #N/A | O79: =VLOOKUP($J79,'mapping-Y26'!$M:$N,5,0) -> #N/A | P79: =VLOOKUP($J79,'mapping-Y26'!$M:$N,6,0) -> #N/A | Q79: =VLOOKUP($J79,'mapping-Y26'!$M:$Q,7,0) -> #N/A | R79: =Q79/O79 -> #N/A | T79: 24 | U79: 18 | V79: 14 | W79: 0.8 | X79: 0.1 | Y79: 0.1 | Z79: =T79*W79+U79*X79+V79*Y79 -> 22.4 | AA79: 0.432 | AB79: 0 | AC79: =Z79*(1-AA79-AB79)/1.13 -> 11.259469 | AE79: 0.3 | AF79: =AD79*(1-AE79) -> 0 | AG79: =(R79-AF79)/R79 -> #N/A | AH79: 0 | AI79: 0.04 | AJ79: =(AH79+AI79)*AF79/R79+AG79 -> #N/A | AK79: =R79*(1-AJ79) -> #N/A | AL79: =VLOOKUP($J79,#REF!,12,0) -> #REF! | AM79: 0.027 | AN79: =AK79-R79*(AL79+AM79) -> #N/A | AO79: =AN79/AK79 -> #N/A | AP79: 100 | AQ79: =O79*AK79*AP79 -> #N/A | AR79: =AP79*AN79*O79 -> #N/A | AS79: =AP79*Q79 -> #N/A
A80: =F80&J80 -> 罗森2694-50 | B80: =E80&J80 -> 沈阳和盛祥2694-50 | C80: =E80&F80 -> 沈阳和盛祥罗森 | D80: RLKA | E80: 沈阳和盛祥 | F80: 罗森 | G80: =VLOOKUP($J80,'mapping-Y26'!#REF!,2,0) -> #REF! | H80: =VLOOKUP($J80,'mapping-Y26'!$F:$L,6,0) -> 40P-55gsm | I80: =VLOOKUP($J80,'mapping-Y26'!$F:$L,5,0) -> 14017864 | J80: 2694-50 | K80: =VLOOKUP($J80,'mapping-Y26'!$F:$L,4,0) -> D269450舒洁湿厕纸家庭装40抽 | L80: =VLOOKUP($J80,'mapping-Y26'!#REF!,4,0) -> #REF! | M80: =VLOOKUP($J80,'mapping-Y26'!$H:$L,2,0) -> D269450舒洁湿厕纸家庭装40抽 | N80: =VLOOKUP($J80,'mapping-Y26'!M:N,3,0) -> #N/A | O80: =VLOOKUP($J80,'mapping-Y26'!$M:$N,5,0) -> #N/A | P80: =VLOOKUP($J80,'mapping-Y26'!$M:$N,6,0) -> #N/A | Q80: =VLOOKUP($J80,'mapping-Y26'!$M:$Q,7,0) -> #N/A | R80: =Q80/O80 -> #N/A | U80: 10.425 | V80: 7.45 | W80: 0 | X80: 0.6 | Y80: 0.4 | Z80: =T80*W80+U80*X80+V80*Y80 -> 9.235 | AA80: 0.31 | AB80: 0 | AC80: =Z80*(1-AA80-AB80)/1.13 -> 5.6390708 | AE80: 0.3 | AF80: =AD80*(1-AE80) -> 0 | AG80: =(R80-AF80)/R80 -> #N/A | AH80: 0 | AI80: 0.04 | AJ80: =(AH80+AI80)*AF80/R80+AG80 -> #N/A | AK80: =R80*(1-AJ80) -> #N/A | AL80: =VLOOKUP($J80,#REF!,12,0) -> #REF! | AM80: 0.027 | AN80: =AK80-R80*(AL80+AM80) -> #N/A | AO80: =AN80/AK80 -> #N/A | AP80: 300 | AQ80: =O80*AK80*AP80 -> #N/A | AR80: =AP80*AN80*O80 -> #N/A | AS80: =AP80*Q80 -> #N/A
A81: =F81&J81 -> 物美2103-90 | B81: =E81&J81 -> XXX2103-90 | C81: =E81&F81 -> XXX物美 | D81: RLKA | E81: XXX | F81: 物美 | G81: =VLOOKUP($J81,'mapping-Y26'!#REF!,2,0) -> #REF! | I81: =VLOOKUP($J81,'mapping-Y26'!$F:$L,5,0) -> 14016868 | J81: 2103-90 | K81: =VLOOKUP($J81,'mapping-Y26'!$F:$L,4,0) -> 210390舒洁小熊印花抽纸3层80抽4包FSC mix70% | L81: =VLOOKUP($J81,'mapping-Y26'!#REF!,4,0) -> #REF! | M81: =VLOOKUP($J81,'mapping-Y26'!$H:$L,2,0) -> 210390舒洁小熊印花抽纸3层80抽4包FSC mix70% | N81: =VLOOKUP($J81,'mapping-Y26'!M:N,3,0) -> #N/A | O81: =VLOOKUP($J81,'mapping-Y26'!$M:$N,5,0) -> #N/A | P81: =VLOOKUP($J81,'mapping-Y26'!$M:$N,6,0) -> #N/A | Q81: =VLOOKUP($J81,'mapping-Y26'!$M:$Q,7,0) -> #N/A | R81: =Q81/O81 -> #N/A | U81: 12.9 | V81: 12.9 | X81: 1 | Z81: =T81*W81+U81*X81+V81*Y81 -> 12.9 | AA81: 0.2248062 | AB81: 0.112 | AC81: =Z81*(1-AA81-AB81)/1.13 -> 7.5709735 | AE81: 0.1 | AF81: =AD81*(1-AE81) -> 0 | AG81: =(R81-AF81)/R81 -> #N/A | AH81: 0 | AI81: 0.04 | AJ81: =(AH81+AI81)*AF81/R81+AG81 -> #N/A | AK81: =R81*(1-AJ81) -> #N/A | AL81: =VLOOKUP($J81,#REF!,12,0) -> #REF! | AM81: 0.027 | AN81: =AK81-R81*(AL81+AM81) -> #N/A | AO81: =AN81/AK81 -> #N/A | AP81: 0 | AQ81: =O81*AK81*AP81 -> #N/A | AR81: =AP81*AN81*O81 -> #N/A | AS81: =AP81*Q81 -> #N/A
A82: =F82&J82 -> 物美2694-50 | B82: =E82&J82 -> XXX2694-50 | C82: =E82&F82 -> XXX物美 | D82: RLKA | E82: XXX | F82: 物美 | G82: =VLOOKUP($J82,'mapping-Y26'!#REF!,2,0) -> #REF! | H82: =VLOOKUP($J82,'mapping-Y26'!$F:$L,6,0) -> 40P-55gsm | I82: =VLOOKUP($J82,'mapping-Y26'!$F:$L,5,0) -> 14017864 | J82: 2694-50 | K82: =VLOOKUP($J82,'mapping-Y26'!$F:$L,4,0) -> D269450舒洁湿厕纸家庭装40抽 | L82: =VLOOKUP($J82,'mapping-Y26'!#REF!,4,0) -> #REF! | M82: =VLOOKUP($J82,'mapping-Y26'!$H:$L,2,0) -> D269450舒洁湿厕纸家庭装40抽 | N82: =VLOOKUP($J82,'mapping-Y26'!M:N,3,0) -> #N/A | O82: =VLOOKUP($J82,'mapping-Y26'!$M:$N,5,0) -> #N/A | P82: =VLOOKUP($J82,'mapping-Y26'!$M:$N,6,0) -> #N/A | Q82: =VLOOKUP($J82,'mapping-Y26'!$M:$Q,7,0) -> #N/A | R82: =Q82/O82 -> #N/A | U82: 6.9 | V82: 6.9 | X82: 1 | Z82: =T82*W82+U82*X82+V82*Y82 -> 6.9 | AA82: 0.20289855 | AB82: 0.112 | AC82: =Z82*(1-AA82-AB82)/1.13 -> 4.1833628 | AE82: 0.1 | AF82: =AD82*(1-AE82) -> 0 | AG82: =(R82-AF82)/R82 -> #N/A | AH82: 0 | AI82: 0.04 | AJ82: =(AH82+AI82)*AF82/R82+AG82 -> #N/A | AK82: =R82*(1-AJ82) -> #N/A | AL82: =VLOOKUP($J82,#REF!,12,0) -> #REF! | AM82: 0.027 | AN82: =AK82-R82*(AL82+AM82) -> #N/A | AO82: =AN82/AK82 -> #N/A | AP82: 1560 | AQ82: =O82*AK82*AP82 -> #N/A | AR82: =AP82*AN82*O82 -> #N/A | AS82: =AP82*Q82 -> #N/A
A83: =F83&J83 -> 物美2162-08 | B83: =E83&J83 -> XXX2162-08 | C83: =E83&F83 -> XXX物美 | D83: RLKA | E83: XXX | F83: 物美 | G83: =VLOOKUP($J83,'mapping-Y26'!#REF!,2,0) -> #REF! | I83: =VLOOKUP($J83,'mapping-Y26'!$F:$L,5,0) -> 14015110 | J83: 2162-08 | K83: =VLOOKUP($J83,'mapping-Y26'!$F:$L,4,0) -> 216208舒洁®北海道牛乳系列乳霜纸面巾20抽8包装 | L83: =VLOOKUP($J83,'mapping-Y26'!#REF!,4,0) -> #REF! | M83: =VLOOKUP($J83,'mapping-Y26'!$H:$L,2,0) -> 216208舒洁®北海道牛乳系列乳霜纸面巾20抽8包装 | N83: =VLOOKUP($J83,'mapping-Y26'!M:N,3,0) -> #N/A | O83: =VLOOKUP($J83,'mapping-Y26'!$M:$N,5,0) -> #N/A | P83: =VLOOKUP($J83,'mapping-Y26'!$M:$N,6,0) -> #N/A | Q83: =VLOOKUP($J83,'mapping-Y26'!$M:$Q,7,0) -> #N/A | R83: =Q83/O83 -> #N/A | U83: 19.9 | V83: 19.9 | X83: 1 | Z83: =T83*W83+U83*X83+V83*Y83 -> 19.9 | AA83: 0.24623116 | AB83: 0.112 | AC83: =Z83*(1-AA83-AB83)/1.13 -> 11.301947 | AE83: 0.1 | AF83: =AD83*(1-AE83) -> 0 | AG83: =(R83-AF83)/R83 -> #N/A | AH83: 0 | AI83: 0.04 | AJ83: =(AH83+AI83)*AF83/R83+AG83 -> #N/A | AK83: =R83*(1-AJ83) -> #N/A | AL83: =VLOOKUP($J83,#REF!,12,0) -> #REF! | AM83: 0.027 | AN83: =AK83-R83*(AL83+AM83) -> #N/A | AO83: =AN83/AK83 -> #N/A | AP83: 1642.5 | AQ83: =O83*AK83*AP83 -> #N/A | AR83: =AP83*AN83*O83 -> #N/A | AS83: =AP83*Q83 -> #N/A
A84: =F84&J84 -> 银座2155-03 | B84: =E84&J84 -> XXX2155-03 | C84: =E84&F84 -> XXX银座 | D84: RLKA | E84: XXX | F84: 银座 | G84: =VLOOKUP($J84,'mapping-Y26'!#REF!,2,0) -> #REF! | I84: =VLOOKUP($J84,'mapping-Y26'!$F:$L,5,0) -> 14016306 | J84: 2155-03 | K84: =VLOOKUP($J84,'mapping-Y26'!$F:$L,4,0) -> 215503舒洁®北海道轻牛乳系列乳霜纸面巾40抽3包装 | L84: =VLOOKUP($J84,'mapping-Y26'!#REF!,4,0) -> #REF! | M84: =VLOOKUP($J84,'mapping-Y26'!$H:$L,2,0) -> 215503舒洁®北海道轻牛乳系列乳霜纸面巾40抽3包装 | N84: =VLOOKUP($J84,'mapping-Y26'!M:N,3,0) -> #N/A | O84: =VLOOKUP($J84,'mapping-Y26'!$M:$N,5,0) -> #N/A | P84: =VLOOKUP($J84,'mapping-Y26'!$M:$N,6,0) -> #N/A | Q84: =VLOOKUP($J84,'mapping-Y26'!$M:$Q,7,0) -> #N/A | R84: =Q84/O84 -> #N/A | T84: 15.9 | U84: 9.9 | V84: 8.9 | W84: 0.05 | X84: 0.7 | Y84: 0.25 | Z84: =T84*W84+U84*X84+V84*Y84 -> 9.95 | AA84: 0.2 | AB84: 0 | AC84: =Z84*(1-AA84-AB84)/1.13 -> 7.0442478 | AE84: 0.1 | AF84: =AD84*(1-AE84) -> 0 | AG84: =(R84-AF84)/R84 -> #N/A | AH84: 0.054 | AI84: 0.04 | AJ84: =(AH84+AI84)*AF84/R84+AG84 -> #N/A | AK84: =R84*(1-AJ84) -> #N/A | AL84: =VLOOKUP($J84,#REF!,12,0) -> #REF! | AM84: 0.027 | AN84: =AK84-R84*(AL84+AM84) -> #N/A | AO84: =AN84/AK84 -> #N/A | AP84: 889.6875 | AQ84: =O84*AK84*AP84 -> #N/A | AR84: =AP84*AN84*O84 -> #N/A | AS84: =AP84*Q84 -> #N/A
A85: =F85&J85 -> 银座2162-08 | B85: =E85&J85 -> XXX2162-08 | C85: =E85&F85 -> XXX银座 | D85: RLKA | E85: XXX | F85: 银座 | G85: =VLOOKUP($J85,'mapping-Y26'!#REF!,2,0) -> #REF! | I85: =VLOOKUP($J85,'mapping-Y26'!$F:$L,5,0) -> 14015110 | J85: 2162-08 | K85: =VLOOKUP($J85,'mapping-Y26'!$F:$L,4,0) -> 216208舒洁®北海道牛乳系列乳霜纸面巾20抽8包装 | L85: =VLOOKUP($J85,'mapping-Y26'!#REF!,4,0) -> #REF! | M85: =VLOOKUP($J85,'mapping-Y26'!$H:$L,2,0) -> 216208舒洁®北海道牛乳系列乳霜纸面巾20抽8包装 | N85: =VLOOKUP($J85,'mapping-Y26'!M:N,3,0) -> #N/A | O85: =VLOOKUP($J85,'mapping-Y26'!$M:$N,5,0) -> #N/A | P85: =VLOOKUP($J85,'mapping-Y26'!$M:$N,6,0) -> #N/A | Q85: =VLOOKUP($J85,'mapping-Y26'!$M:$Q,7,0) -> #N/A | R85: =Q85/O85 -> #N/A | T85: 23.9 | U85: 21.9 | V85: 19.9 | W85: 0.1 | X85: 0.6 | Y85: 0.3 | Z85: =T85*W85+U85*X85+V85*Y85 -> 21.5 | AA85: 0.2 | AB85: 0 | AC85: =Z85*(1-AA85-AB85)/1.13 -> 15.221239 | AE85: 0.1 | AF85: =AD85*(1-AE85) -> 0 | AG85: =(R85-AF85)/R85 -> #N/A | AH85: 0.054 | AI85: 0.04 | AJ85: =(AH85+AI85)*AF85/R85+AG85 -> #N/A | AK85: =R85*(1-AJ85) -> #N/A | AL85: =VLOOKUP($J85,#REF!,12,0) -> #REF! | AM85: 0.027 | AN85: =AK85-R85*(AL85+AM85) -> #N/A | AO85: =AN85/AK85 -> #N/A | AP85: 1314 | AQ85: =O85*AK85*AP85 -> #N/A | AR85: =AP85*AN85*O85 -> #N/A | AS85: =AP85*Q85 -> #N/A
A86: =F86&J86 -> 银座2660-10 | B86: =E86&J86 -> XXX2660-10 | C86: =E86&F86 -> XXX银座 | D86: RLKA | E86: XXX | F86: 银座 | G86: =VLOOKUP($J86,'mapping-Y26'!#REF!,2,0) -> #REF! | H86: =VLOOKUP($J86,'mapping-Y26'!$F:$L,6,0) -> 80P | I86: =VLOOKUP($J86,'mapping-Y26'!$F:$L,5,0) -> 14017865 | J86: 2660-10 | K86: =VLOOKUP($J86,'mapping-Y26'!$F:$L,4,0) -> 266010舒洁湿厕纸80片 | L86: =VLOOKUP($J86,'mapping-Y26'!#REF!,4,0) -> #REF! | M86: =VLOOKUP($J86,'mapping-Y26'!$H:$L,2,0) -> 266010舒洁湿厕纸80片 | N86: =VLOOKUP($J86,'mapping-Y26'!M:N,3,0) -> #N/A | O86: =VLOOKUP($J86,'mapping-Y26'!$M:$N,5,0) -> #N/A | P86: =VLOOKUP($J86,'mapping-Y26'!$M:$N,6,0) -> #N/A | Q86: =VLOOKUP($J86,'mapping-Y26'!$M:$Q,7,0) -> #N/A | R86: =Q86/O86 -> #N/A | T86: 17.9 | U86: 9.9 | V86: 8.9 | W86: 0.05 | X86: 0.7 | Y86: 0.25 | Z86: =T86*W86+U86*X86+V86*Y86 -> 10.05 | AA86: 0.2 | AB86: 0 | AC86: =Z86*(1-AA86-AB86)/1.13 -> 7.1150442 | AE86: 0.1 | AF86: =AD86*(1-AE86) -> 0 | AG86: =(R86-AF86)/R86 -> #N/A | AH86: 0.054 | AI86: 0.04 | AJ86: =(AH86+AI86)*AF86/R86+AG86 -> #N/A | AK86: =R86*(1-AJ86) -> #N/A | AL86: =VLOOKUP($J86,#REF!,12,0) -> #REF! | AM86: 0.027 | AN86: =AK86-R86*(AL86+AM86) -> #N/A | AO86: =AN86/AK86 -> #N/A | AP86: 403.02083 | AQ86: =O86*AK86*AP86 -> #N/A | AR86: =AP86*AN86*O86 -> #N/A | AS86: =AP86*Q86 -> #N/A
A87: =F87&J87 -> 银座2701-90 | B87: =E87&J87 -> XXX2701-90 | C87: =E87&F87 -> XXX银座 | D87: RLKA | E87: XXX | F87: 银座 | G87: =VLOOKUP($J87,'mapping-Y26'!#REF!,2,0) -> #REF! | I87: =VLOOKUP($J87,'mapping-Y26'!$F:$L,5,0) -> 14016871 | J87: 2701-90 | K87: =VLOOKUP($J87,'mapping-Y26'!$F:$L,4,0) -> 270190舒洁小熊印花手帕纸3层10包FSC mix70% | L87: =VLOOKUP($J87,'mapping-Y26'!#REF!,4,0) -> #REF! | M87: =VLOOKUP($J87,'mapping-Y26'!$H:$L,2,0) -> 270190舒洁小熊印花手帕纸3层10包FSC mix70% | N87: =VLOOKUP($J87,'mapping-Y26'!M:N,3,0) -> #N/A | O87: =VLOOKUP($J87,'mapping-Y26'!$M:$N,5,0) -> #N/A | P87: =VLOOKUP($J87,'mapping-Y26'!$M:$N,6,0) -> #N/A | Q87: =VLOOKUP($J87,'mapping-Y26'!$M:$Q,7,0) -> #N/A | R87: =Q87/O87 -> #N/A | T87: 7.8 | U87: 7.5 | V87: 6.9 | W87: 0.05 | X87: 0.7 | Y87: 0.25 | Z87: =T87*W87+U87*X87+V87*Y87 -> 7.365 | AA87: 0.2 | AB87: 0 | AC87: =Z87*(1-AA87-AB87)/1.13 -> 5.2141593 | AE87: 0.1 | AF87: =AD87*(1-AE87) -> 0 | AG87: =(R87-AF87)/R87 -> #N/A | AH87: 0.054 | AI87: 0.04 | AJ87: =(AH87+AI87)*AF87/R87+AG87 -> #N/A | AK87: =R87*(1-AJ87) -> #N/A | AL87: =VLOOKUP($J87,#REF!,12,0) -> #REF! | AM87: 0.027 | AN87: =AK87-R87*(AL87+AM87) -> #N/A | AO87: =AN87/AK87 -> #N/A | AP87: 334.58333 | AQ87: =O87*AK87*AP87 -> #N/A | AR87: =AP87*AN87*O87 -> #N/A | AS87: =AP87*Q87 -> #N/A
A88: =F88&J88 -> 银座2103-90 | B88: =E88&J88 -> XXX2103-90 | C88: =E88&F88 -> XXX银座 | D88: RLKA | E88: XXX | F88: 银座 | G88: =VLOOKUP($J88,'mapping-Y26'!#REF!,2,0) -> #REF! | I88: =VLOOKUP($J88,'mapping-Y26'!$F:$L,5,0) -> 14016868 | J88: 2103-90 | K88: =VLOOKUP($J88,'mapping-Y26'!$F:$L,4,0) -> 210390舒洁小熊印花抽纸3层80抽4包FSC mix70% | L88: =VLOOKUP($J88,'mapping-Y26'!#REF!,4,0) -> #REF! | M88: =VLOOKUP($J88,'mapping-Y26'!$H:$L,2,0) -> 210390舒洁小熊印花抽纸3层80抽4包FSC mix70% | N88: =VLOOKUP($J88,'mapping-Y26'!M:N,3,0) -> #N/A | O88: =VLOOKUP($J88,'mapping-Y26'!$M:$N,5,0) -> #N/A | P88: =VLOOKUP($J88,'mapping-Y26'!$M:$N,6,0) -> #N/A | Q88: =VLOOKUP($J88,'mapping-Y26'!$M:$Q,7,0) -> #N/A | R88: =Q88/O88 -> #N/A | T88: 15.9 | U88: 13.9 | V88: 12.9 | W88: 0.05 | X88: 0.7 | Y88: 0.25 | Z88: =T88*W88+U88*X88+V88*Y88 -> 13.75 | AA88: 0.2 | AB88: 0 | AC88: =Z88*(1-AA88-AB88)/1.13 -> 9.7345133 | AE88: 0.1 | AF88: =AD88*(1-AE88) -> 0 | AG88: =(R88-AF88)/R88 -> #N/A | AH88: 0.054 | AI88: 0.04 | AJ88: =(AH88+AI88)*AF88/R88+AG88 -> #N/A | AK88: =R88*(1-AJ88) -> #N/A | AL88: =VLOOKUP($J88,#REF!,12,0) -> #REF! | AM88: 0.027 | AN88: =AK88-R88*(AL88+AM88) -> #N/A | AO88: =AN88/AK88 -> #N/A | AP88: 261.58333 | AQ88: =O88*AK88*AP88 -> #N/A | AR88: =AP88*AN88*O88 -> #N/A | AS88: =AP88*Q88 -> #N/A
A89: =F89&J89 -> 银座2291-60 | B89: =E89&J89 -> XXX2291-60 | C89: =E89&F89 -> XXX银座 | D89: RLKA | E89: XXX | F89: 银座 | G89: =VLOOKUP($J89,'mapping-Y26'!#REF!,2,0) -> #REF! | I89: =VLOOKUP($J89,'mapping-Y26'!$F:$L,5,0) -> 14014479 | J89: 2291-60 | K89: =VLOOKUP($J89,'mapping-Y26'!$F:$L,4,0) -> 229160舒洁绿茶洋甘菊印花清香卷纸10粒 | L89: =VLOOKUP($J89,'mapping-Y26'!#REF!,4,0) -> #REF! | M89: =VLOOKUP($J89,'mapping-Y26'!$H:$L,2,0) -> 229160舒洁绿茶洋甘菊印花清香卷纸10粒 | N89: =VLOOKUP($J89,'mapping-Y26'!M:N,3,0) -> #N/A | O89: =VLOOKUP($J89,'mapping-Y26'!$M:$N,5,0) -> #N/A | P89: =VLOOKUP($J89,'mapping-Y26'!$M:$N,6,0) -> #N/A | Q89: =VLOOKUP($J89,'mapping-Y26'!$M:$Q,7,0) -> #N/A | R89: =Q89/O89 -> #N/A | T89: 35.9 | U89: 32.9 | V89: 29.9 | W89: 0.05 | X89: 0.85 | Y89: 0.1 | Z89: =T89*W89+U89*X89+V89*Y89 -> 32.75 | AA89: 0.2 | AB89: 0 | AC89: =Z89*(1-AA89-AB89)/1.13 -> 23.185841 | AE89: 0.1 | AF89: =AD89*(1-AE89) -> 0 | AG89: =(R89-AF89)/R89 -> #N/A | AH89: 0.054 | AI89: 0.04 | AJ89: =(AH89+AI89)*AF89/R89+AG89 -> #N/A | AK89: =R89*(1-AJ89) -> #N/A | AL89: =VLOOKUP($J89,#REF!,12,0) -> #REF! | AM89: 0.027 | AN89: =AK89-R89*(AL89+AM89) -> #N/A | AO89: =AN89/AK89 -> #N/A | AP89: 2500 | AQ89: =O89*AK89*AP89 -> #N/A | AR89: =AP89*AN89*O89 -> #N/A | AS89: =AP89*Q89 -> #N/A
A90: =F90&J90 -> 利群2291-60 | B90: =E90&J90 -> 福兴祥2291-60 | C90: =E90&F90 -> 福兴祥利群 | D90: RLKA | E90: 福兴祥 | F90: 利群 | G90: =VLOOKUP($J90,'mapping-Y26'!#REF!,2,0) -> #REF! | I90: =VLOOKUP($J90,'mapping-Y26'!$F:$L,5,0) -> 14014479 | J90: 2291-60 | K90: =VLOOKUP($J90,'mapping-Y26'!$F:$L,4,0) -> 229160舒洁绿茶洋甘菊印花清香卷纸10粒 | L90: =VLOOKUP($J90,'mapping-Y26'!#REF!,4,0) -> #REF! | M90: =VLOOKUP($J90,'mapping-Y26'!$H:$L,2,0) -> 229160舒洁绿茶洋甘菊印花清香卷纸10粒 | N90: =VLOOKUP($J90,'mapping-Y26'!M:N,3,0) -> #N/A | O90: =VLOOKUP($J90,'mapping-Y26'!$M:$N,5,0) -> #N/A | P90: =VLOOKUP($J90,'mapping-Y26'!$M:$N,6,0) -> #N/A | Q90: =VLOOKUP($J90,'mapping-Y26'!$M:$Q,7,0) -> #N/A | R90: =Q90/O90 -> #N/A | T90: 39.9 | U90: 35.9 | V90: 29.9 | W90: 0.05 | X90: 0.85 | Y90: 0.1 | Z90: =T90*W90+U90*X90+V90*Y90 -> 35.5 | AA90: 0.18 | AB90: 0 | AC90: =Z90*(1-AA90-AB90)/1.13 -> 25.761062 | AE90: 0.06 | AF90: =AD90*(1-AE90) -> 0 | AG90: =(R90-AF90)/R90 -> #N/A | AH90: 0.074 | AI90: 0.04 | AJ90: =(AH90+AI90)*AF90/R90+AG90 -> #N/A | AK90: =R90*(1-AJ90) -> #N/A | AL90: =VLOOKUP($J90,#REF!,12,0) -> #REF! | AM90: 0.027 | AN90: =AK90-R90*(AL90+AM90) -> #N/A | AO90: =AN90/AK90 -> #N/A | AP90: 420.918 | AQ90: =O90*AK90*AP90 -> #N/A | AR90: =AP90*AN90*O90 -> #N/A | AS90: =AP90*Q90 -> #N/A
A91: =F91&J91 -> 利群2216-35 | B91: =E91&J91 -> 福兴祥2216-35 | C91: =E91&F91 -> 福兴祥利群 | D91: RLKA | E91: 福兴祥 | F91: 利群 | G91: =VLOOKUP($J91,'mapping-Y26'!#REF!,2,0) -> #REF! | I91: =VLOOKUP($J91,'mapping-Y26'!$F:$L,5,0) -> 14015861 | J91: 2216-35 | K91: =VLOOKUP($J91,'mapping-Y26'!$F:$L,4,0) -> 221635舒洁卷纸3层纯白10粒（蓝色） | L91: =VLOOKUP($J91,'mapping-Y26'!#REF!,4,0) -> #REF! | M91: =VLOOKUP($J91,'mapping-Y26'!$H:$L,2,0) -> 221635舒洁卷纸3层纯白10粒（蓝色） | N91: =VLOOKUP($J91,'mapping-Y26'!M:N,3,0) -> #N/A | O91: =VLOOKUP($J91,'mapping-Y26'!$M:$N,5,0) -> #N/A | P91: =VLOOKUP($J91,'mapping-Y26'!$M:$N,6,0) -> #N/A | Q91: =VLOOKUP($J91,'mapping-Y26'!$M:$Q,7,0) -> #N/A | R91: =Q91/O91 -> #N/A | T91: 32.9 | U91: 27.9 | V91: 19.9 | W91: 0.05 | X91: 0.7 | Y91: 0.25 | Z91: =T91*W91+U91*X91+V91*Y91 -> 26.15 | AA91: 0.18 | AB91: 0 | AC91: =Z91*(1-AA91-AB91)/1.13 -> 18.976106 | AE91: 0.06 | AF91: =AD91*(1-AE91) -> 0 | AG91: =(R91-AF91)/R91 -> #N/A | AH91: 0.074 | AI91: 0.04 | AJ91: =(AH91+AI91)*AF91/R91+AG91 -> #N/A | AK91: =R91*(1-AJ91) -> #N/A | AL91: =VLOOKUP($J91,#REF!,12,0) -> #REF! | AM91: 0.027 | AN91: =AK91-R91*(AL91+AM91) -> #N/A | AO91: =AN91/AK91 -> #N/A | AP91: 210.459 | AQ91: =O91*AK91*AP91 -> #N/A | AR91: =AP91*AN91*O91 -> #N/A | AS91: =AP91*Q91 -> #N/A
A92: =F92&J92 -> 利群2660-10 | B92: =E92&J92 -> 福兴祥2660-10 | C92: =E92&F92 -> 福兴祥利群 | D92: RLKA | E92: 福兴祥 | F92: 利群 | G92: =VLOOKUP($J92,'mapping-Y26'!#REF!,2,0) -> #REF! | H92: =VLOOKUP($J92,'mapping-Y26'!$F:$L,6,0) -> 80P | I92: =VLOOKUP($J92,'mapping-Y26'!$F:$L,5,0) -> 14017865 | J92: 2660-10 | K92: =VLOOKUP($J92,'mapping-Y26'!$F:$L,4,0) -> 266010舒洁湿厕纸80片 | L92: =VLOOKUP($J92,'mapping-Y26'!#REF!,4,0) -> #REF! | M92: =VLOOKUP($J92,'mapping-Y26'!$H:$L,2,0) -> 266010舒洁湿厕纸80片 | N92: =VLOOKUP($J92,'mapping-Y26'!M:N,3,0) -> #N/A | O92: =VLOOKUP($J92,'mapping-Y26'!$M:$N,5,0) -> #N/A | P92: =VLOOKUP($J92,'mapping-Y26'!$M:$N,6,0) -> #N/A | Q92: =VLOOKUP($J92,'mapping-Y26'!$M:$Q,7,0) -> #N/A | R92: =Q92/O92 -> #N/A | T92: 19.9 | U92: 9.9 | V92: 8.9 | W92: 0.05 | X92: 0.7 | Y92: 0.25 | Z92: =T92*W92+U92*X92+V92*Y92 -> 10.15 | AA92: 0.18 | AB92: 0 | AC92: =Z92*(1-AA92-AB92)/1.13 -> 7.3654867 | AE92: 0.06 | AF92: =AD92*(1-AE92) -> 0 | AG92: =(R92-AF92)/R92 -> #N/A | AH92: 0.074 | AI92: 0.04 | AJ92: =(AH92+AI92)*AF92/R92+AG92 -> #N/A | AK92: =R92*(1-AJ92) -> #N/A | AL92: =VLOOKUP($J92,#REF!,12,0) -> #REF! | AM92: 0.027 | AN92: =AK92-R92*(AL92+AM92) -> #N/A | AO92: =AN92/AK92 -> #N/A | AP92: 648.72667 | AQ92: =O92*AK92*AP92 -> #N/A | AR92: =AP92*AN92*O92 -> #N/A | AS92: =AP92*Q92 -> #N/A
A93: =F93&J93 -> 利群2701-90 | B93: =E93&J93 -> 福兴祥2701-90 | C93: =E93&F93 -> 福兴祥利群 | D93: RLKA | E93: 福兴祥 | F93: 利群 | G93: =VLOOKUP($J93,'mapping-Y26'!#REF!,2,0) -> #REF! | I93: =VLOOKUP($J93,'mapping-Y26'!$F:$L,5,0) -> 14016871 | J93: 2701-90 | K93: =VLOOKUP($J93,'mapping-Y26'!$F:$L,4,0) -> 270190舒洁小熊印花手帕纸3层10包FSC mix70% | L93: =VLOOKUP($J93,'mapping-Y26'!#REF!,4,0) -> #REF! | M93: =VLOOKUP($J93,'mapping-Y26'!$H:$L,2,0) -> 270190舒洁小熊印花手帕纸3层10包FSC mix70% | N93: =VLOOKUP($J93,'mapping-Y26'!M:N,3,0) -> #N/A | O93: =VLOOKUP($J93,'mapping-Y26'!$M:$N,5,0) -> #N/A | P93: =VLOOKUP($J93,'mapping-Y26'!$M:$N,6,0) -> #N/A | Q93: =VLOOKUP($J93,'mapping-Y26'!$M:$Q,7,0) -> #N/A | R93: =Q93/O93 -> #N/A | T93: 7.5 | U93: 7.9 | V93: 6.9 | W93: 0.05 | X93: 0.6 | Y93: 0.35 | Z93: =T93*W93+U93*X93+V93*Y93 -> 7.53 | AA93: 0.18 | AB93: 0 | AC93: =Z93*(1-AA93-AB93)/1.13 -> 5.4642478 | AE93: 0.06 | AF93: =AD93*(1-AE93) -> 0 | AG93: =(R93-AF93)/R93 -> #N/A | AH93: 0.074 | AI93: 0.04 | AJ93: =(AH93+AI93)*AF93/R93+AG93 -> #N/A | AK93: =R93*(1-AJ93) -> #N/A | AL93: =VLOOKUP($J93,#REF!,12,0) -> #REF! | AM93: 0.027 | AN93: =AK93-R93*(AL93+AM93) -> #N/A | AO93: =AN93/AK93 -> #N/A | AP93: 131.26258 | AQ93: =O93*AK93*AP93 -> #N/A | AR93: =AP93*AN93*O93 -> #N/A | AS93: =AP93*Q93 -> #N/A
A94: =F94&J94 -> 利群2103-90 | B94: =E94&J94 -> 福兴祥2103-90 | C94: =E94&F94 -> 福兴祥利群 | D94: RLKA | E94: 福兴祥 | F94: 利群 | G94: =VLOOKUP($J94,'mapping-Y26'!#REF!,2,0) -> #REF! | I94: =VLOOKUP($J94,'mapping-Y26'!$F:$L,5,0) -> 14016868 | J94: 2103-90 | K94: =VLOOKUP($J94,'mapping-Y26'!$F:$L,4,0) -> 210390舒洁小熊印花抽纸3层80抽4包FSC mix70% | L94: =VLOOKUP($J94,'mapping-Y26'!#REF!,4,0) -> #REF! | M94: =VLOOKUP($J94,'mapping-Y26'!$H:$L,2,0) -> 210390舒洁小熊印花抽纸3层80抽4包FSC mix70% | N94: =VLOOKUP($J94,'mapping-Y26'!M:N,3,0) -> #N/A | O94: =VLOOKUP($J94,'mapping-Y26'!$M:$N,5,0) -> #N/A | P94: =VLOOKUP($J94,'mapping-Y26'!$M:$N,6,0) -> #N/A | Q94: =VLOOKUP($J94,'mapping-Y26'!$M:$Q,7,0) -> #N/A | R94: =Q94/O94 -> #N/A | T94: 17.9 | U94: 13.9 | V94: 12.9 | W94: 0.05 | X94: 0.5 | Y94: 0.45 | Z94: =T94*W94+U94*X94+V94*Y94 -> 13.65 | AA94: 0.18 | AB94: 0 | AC94: =Z94*(1-AA94-AB94)/1.13 -> 9.9053097 | AE94: 0.06 | AF94: =AD94*(1-AE94) -> 0 | AG94: =(R94-AF94)/R94 -> #N/A | AH94: 0.074 | AI94: 0.04 | AJ94: =(AH94+AI94)*AF94/R94+AG94 -> #N/A | AK94: =R94*(1-AJ94) -> #N/A | AL94: =VLOOKUP($J94,#REF!,12,0) -> #REF! | AM94: 0.027 | AN94: =AK94-R94*(AL94+AM94) -> #N/A | AO94: =AN94/AK94 -> #N/A | AP94: 157.26325 | AQ94: =O94*AK94*AP94 -> #N/A | AR94: =AP94*AN94*O94 -> #N/A | AS94: =AP94*Q94 -> #N/A
A95: =F95&J95 -> 利群2155-03 | B95: =E95&J95 -> 福兴祥2155-03 | C95: =E95&F95 -> 福兴祥利群 | D95: RLKA | E95: 福兴祥 | F95: 利群 | G95: =VLOOKUP($J95,'mapping-Y26'!#REF!,2,0) -> #REF! | I95: =VLOOKUP($J95,'mapping-Y26'!$F:$L,5,0) -> 14016306 | J95: 2155-03 | K95: =VLOOKUP($J95,'mapping-Y26'!$F:$L,4,0) -> 215503舒洁®北海道轻牛乳系列乳霜纸面巾40抽3包装 | L95: =VLOOKUP($J95,'mapping-Y26'!#REF!,4,0) -> #REF! | M95: =VLOOKUP($J95,'mapping-Y26'!$H:$L,2,0) -> 215503舒洁®北海道轻牛乳系列乳霜纸面巾40抽3包装 | N95: =VLOOKUP($J95,'mapping-Y26'!M:N,3,0) -> #N/A | O95: =VLOOKUP($J95,'mapping-Y26'!$M:$N,5,0) -> #N/A | P95: =VLOOKUP($J95,'mapping-Y26'!$M:$N,6,0) -> #N/A | Q95: =VLOOKUP($J95,'mapping-Y26'!$M:$Q,7,0) -> #N/A | R95: =Q95/O95 -> #N/A | T95: 17.9 | U95: 9.9 | V95: 8.9 | W95: 0.05 | X95: 0.7 | Y95: 0.25 | Z95: =T95*W95+U95*X95+V95*Y95 -> 10.05 | AA95: 0.18 | AB95: 0 | AC95: =Z95*(1-AA95-AB95)/1.13 -> 7.2929204 | AE95: 0.06 | AF95: =AD95*(1-AE95) -> 0 | AG95: =(R95-AF95)/R95 -> #N/A | AH95: 0.074 | AI95: 0.04 | AJ95: =(AH95+AI95)*AF95/R95+AG95 -> #N/A | AK95: =R95*(1-AJ95) -> #N/A | AL95: =VLOOKUP($J95,#REF!,12,0) -> #REF! | AM95: 0.027 | AN95: =AK95-R95*(AL95+AM95) -> #N/A | AO95: =AN95/AK95 -> #N/A | AP95: 325.30625 | AQ95: =O95*AK95*AP95 -> #N/A | AR95: =AP95*AN95*O95 -> #N/A | AS95: =AP95*Q95 -> #N/A
A96: =F96&J96 -> 比优特2103-90 | B96: =E96&J96 -> 真市美2103-90 | C96: =E96&F96 -> 真市美比优特 | D96: RLKA | E96: 真市美 | F96: 比优特 | G96: =VLOOKUP($J96,'mapping-Y26'!#REF!,2,0) -> #REF! | I96: =VLOOKUP($J96,'mapping-Y26'!$F:$L,5,0) -> 14016868 | J96: 2103-90 | K96: =VLOOKUP($J96,'mapping-Y26'!$F:$L,4,0) -> 210390舒洁小熊印花抽纸3层80抽4包FSC mix70% | L96: =VLOOKUP($J96,'mapping-Y26'!#REF!,4,0) -> #REF! | M96: =VLOOKUP($J96,'mapping-Y26'!$H:$L,2,0) -> 210390舒洁小熊印花抽纸3层80抽4包FSC mix70% | N96: =VLOOKUP($J96,'mapping-Y26'!M:N,3,0) -> #N/A | O96: =VLOOKUP($J96,'mapping-Y26'!$M:$N,5,0) -> #N/A | P96: =VLOOKUP($J96,'mapping-Y26'!$M:$N,6,0) -> #N/A | Q96: =VLOOKUP($J96,'mapping-Y26'!$M:$Q,7,0) -> #N/A | R96: =Q96/O96 -> #N/A | T96: 14.9 | U96: 12.9 | V96: 9.9 | W96: 0.2 | X96: 0.6 | Y96: 0.2 | Z96: =T96*W96+U96*X96+V96*Y96 -> 12.7 | AA96: 0.15 | AB96: 0 | AC96: =Z96*(1-AA96-AB96)/1.13 -> 9.5530973 | AE96: 0.08 | AF96: =AD96*(1-AE96) -> 0 | AG96: =(R96-AF96)/R96 -> #N/A | AH96: 0.02 | AI96: 0.04 | AJ96: =(AH96+AI96)*AF96/R96+AG96 -> #N/A | AK96: =R96*(1-AJ96) -> #N/A | AL96: =VLOOKUP($J96,#REF!,12,0) -> #REF! | AM96: 0.027 | AN96: =AK96-R96*(AL96+AM96) -> #N/A | AO96: =AN96/AK96 -> #N/A | AP96: 400 | AQ96: =O96*AK96*AP96 -> #N/A | AR96: =AP96*AN96*O96 -> #N/A | AS96: =AP96*Q96 -> #N/A
A97: =F97&J97 -> 比优特2107-61 | B97: =E97&J97 -> 真市美2107-61 | C97: =E97&F97 -> 真市美比优特 | D97: RLKA | E97: 真市美 | F97: 比优特 | G97: =VLOOKUP($J97,'mapping-Y26'!#REF!,2,0) -> #REF! | I97: =VLOOKUP($J97,'mapping-Y26'!$F:$L,5,0) -> 14014470 | J97: 2107-61 | K97: =VLOOKUP($J97,'mapping-Y26'!$F:$L,4,0) -> 210761舒洁卡通系列抽纸200抽3包 FSC mix70% | L97: =VLOOKUP($J97,'mapping-Y26'!#REF!,4,0) -> #REF! | M97: =VLOOKUP($J97,'mapping-Y26'!$H:$L,2,0) -> 210761舒洁卡通系列抽纸200抽3包 FSC mix70% | N97: =VLOOKUP($J97,'mapping-Y26'!M:N,3,0) -> #N/A | O97: =VLOOKUP($J97,'mapping-Y26'!$M:$N,5,0) -> #N/A | P97: =VLOOKUP($J97,'mapping-Y26'!$M:$N,6,0) -> #N/A | Q97: =VLOOKUP($J97,'mapping-Y26'!$M:$Q,7,0) -> #N/A | R97: =Q97/O97 -> #N/A | T97: 21.9 | U97: 19.9 | V97: 17.9 | W97: 0.1 | X97: 0.5 | Y97: 0.4 | Z97: =T97*W97+U97*X97+V97*Y97 -> 19.3 | AA97: 0.15 | AB97: 0 | AC97: =Z97*(1-AA97-AB97)/1.13 -> 14.517699 | AE97: 0.08 | AF97: =AD97*(1-AE97) -> 0 | AG97: =(R97-AF97)/R97 -> #N/A | AH97: 0.02 | AI97: 0.04 | AJ97: =(AH97+AI97)*AF97/R97+AG97 -> #N/A | AK97: =R97*(1-AJ97) -> #N/A | AL97: =VLOOKUP($J97,#REF!,12,0) -> #REF! | AM97: 0.027 | AN97: =AK97-R97*(AL97+AM97) -> #N/A | AO97: =AN97/AK97 -> #N/A | AP97: 220 | AQ97: =O97*AK97*AP97 -> #N/A | AR97: =AP97*AN97*O97 -> #N/A | AS97: =AP97*Q97 -> #N/A
A98: =F98&J98 -> 比优特2694-50 | B98: =E98&J98 -> 真市美2694-50 | C98: =E98&F98 -> 真市美比优特 | D98: RLKA | E98: 真市美 | F98: 比优特 | G98: =VLOOKUP($J98,'mapping-Y26'!#REF!,2,0) -> #REF! | H98: =VLOOKUP($J98,'mapping-Y26'!$F:$L,6,0) -> 40P-55gsm | I98: =VLOOKUP($J98,'mapping-Y26'!$F:$L,5,0) -> 14017864 | J98: 2694-50 | K98: =VLOOKUP($J98,'mapping-Y26'!$F:$L,4,0) -> D269450舒洁湿厕纸家庭装40抽 | L98: =VLOOKUP($J98,'mapping-Y26'!#REF!,4,0) -> #REF! | M98: =VLOOKUP($J98,'mapping-Y26'!$H:$L,2,0) -> D269450舒洁湿厕纸家庭装40抽 | N98: =VLOOKUP($J98,'mapping-Y26'!M:N,3,0) -> #N/A | O98: =VLOOKUP($J98,'mapping-Y26'!$M:$N,5,0) -> #N/A | P98: =VLOOKUP($J98,'mapping-Y26'!$M:$N,6,0) -> #N/A | Q98: =VLOOKUP($J98,'mapping-Y26'!$M:$Q,7,0) -> #N/A | R98: =Q98/O98 -> #N/A | T98: 6.9 | U98: 5.9 | V98: 5 | W98: 0.5 | X98: 0.35 | Y98: 0.15 | Z98: =T98*W98+U98*X98+V98*Y98 -> 6.265 | AA98: 0.15 | AB98: 0 | AC98: =Z98*(1-AA98-AB98)/1.13 -> 4.7126106 | AE98: 0.08 | AF98: =AD98*(1-AE98) -> 0 | AG98: =(R98-AF98)/R98 -> #N/A | AH98: 0.02 | AI98: 0.04 | AJ98: =(AH98+AI98)*AF98/R98+AG98 -> #N/A | AK98: =R98*(1-AJ98) -> #N/A | AL98: =VLOOKUP($J98,#REF!,12,0) -> #REF! | AM98: 0.027 | AN98: =AK98-R98*(AL98+AM98) -> #N/A | AO98: =AN98/AK98 -> #N/A | AP98: 600 | AQ98: =O98*AK98*AP98 -> #N/A | AR98: =AP98*AN98*O98 -> #N/A | AS98: =AP98*Q98 -> #N/A
A99: =F99&J99 -> 比优特2701-90 | B99: =E99&J99 -> 真市美2701-90 | C99: =E99&F99 -> 真市美比优特 | D99: RLKA | E99: 真市美 | F99: 比优特 | G99: =VLOOKUP($J99,'mapping-Y26'!#REF!,2,0) -> #REF! | I99: =VLOOKUP($J99,'mapping-Y26'!$F:$L,5,0) -> 14016871 | J99: 2701-90 | K99: =VLOOKUP($J99,'mapping-Y26'!$F:$L,4,0) -> 270190舒洁小熊印花手帕纸3层10包FSC mix70% | L99: =VLOOKUP($J99,'mapping-Y26'!#REF!,4,0) -> #REF! | M99: =VLOOKUP($J99,'mapping-Y26'!$H:$L,2,0) -> 270190舒洁小熊印花手帕纸3层10包FSC mix70% | N99: =VLOOKUP($J99,'mapping-Y26'!M:N,3,0) -> #N/A | O99: =VLOOKUP($J99,'mapping-Y26'!$M:$N,5,0) -> #N/A | P99: =VLOOKUP($J99,'mapping-Y26'!$M:$N,6,0) -> #N/A | Q99: =VLOOKUP($J99,'mapping-Y26'!$M:$Q,7,0) -> #N/A | R99: =Q99/O99 -> #N/A | T99: 7.9 | U99: 7.5 | V99: 6.9 | W99: 0.3 | X99: 0.5 | Y99: 0.2 | Z99: =T99*W99+U99*X99+V99*Y99 -> 7.5 | AA99: 0.15 | AB99: 0 | AC99: =Z99*(1-AA99-AB99)/1.13 -> 5.6415929 | AE99: 0.08 | AF99: =AD99*(1-AE99) -> 0 | AG99: =(R99-AF99)/R99 -> #N/A | AH99: 0.02 | AI99: 0.04 | AJ99: =(AH99+AI99)*AF99/R99+AG99 -> #N/A | AK99: =R99*(1-AJ99) -> #N/A | AL99: =VLOOKUP($J99,#REF!,12,0) -> #REF! | AM99: 0.027 | AN99: =AK99-R99*(AL99+AM99) -> #N/A | AO99: =AN99/AK99 -> #N/A | AP99: 300 | AQ99: =O99*AK99*AP99 -> #N/A | AR99: =AP99*AN99*O99 -> #N/A | AS99: =AP99*Q99 -> #N/A
A100: =F100&J100 -> 比优特2291-60 | B100: =E100&J100 -> 真市美2291-60 | C100: =E100&F100 -> 真市美比优特 | D100: RLKA | E100: 真市美 | F100: 比优特 | G100: =VLOOKUP($J100,'mapping-Y26'!#REF!,2,0) -> #REF! | I100: =VLOOKUP($J100,'mapping-Y26'!$F:$L,5,0) -> 14014479 | J100: 2291-60 | K100: =VLOOKUP($J100,'mapping-Y26'!$F:$L,4,0) -> 229160舒洁绿茶洋甘菊印花清香卷纸10粒 | L100: =VLOOKUP($J100,'mapping-Y26'!#REF!,4,0) -> #REF! | M100: =VLOOKUP($J100,'mapping-Y26'!$H:$L,2,0) -> 229160舒洁绿茶洋甘菊印花清香卷纸10粒 | N100: =VLOOKUP($J100,'mapping-Y26'!M:N,3,0) -> #N/A | O100: =VLOOKUP($J100,'mapping-Y26'!$M:$N,5,0) -> #N/A | P100: =VLOOKUP($J100,'mapping-Y26'!$M:$N,6,0) -> #N/A | Q100: =VLOOKUP($J100,'mapping-Y26'!$M:$Q,7,0) -> #N/A | R100: =Q100/O100 -> #N/A | T100: 39.9 | U100: 35.9 | V100: 29.9 | W100: 0.05 | X100: 0.5 | Y100: 0.45 | Z100: =T100*W100+U100*X100+V100*Y100 -> 33.4 | AA100: 0.15 | AB100: 0 | AC100: =Z100*(1-AA100-AB100)/1.13 -> 25.123894 | AE100: 0.08 | AF100: =AD100*(1-AE100) -> 0 | AG100: =(R100-AF100)/R100 -> #N/A | AH100: 0.02 | AI100: 0.04 | AJ100: =(AH100+AI100)*AF100/R100+AG100 -> #N/A | AK100: =R100*(1-AJ100) -> #N/A | AL100: =VLOOKUP($J100,#REF!,12,0) -> #REF! | AM100: 0.027 | AN100: =AK100-R100*(AL100+AM100) -> #N/A | AO100: =AN100/AK100 -> #N/A | AP100: 500 | AQ100: =O100*AK100*AP100 -> #N/A | AR100: =AP100*AN100*O100 -> #N/A | AS100: =AP100*Q100 -> #N/A
...

Sheet mapping-Y26
B1: category | C1: 产品系列 | D1: fcst line | E1: 4 PRO | F1: Merge_code | G1: Barcode（EA） | H1: pro code | I1: Description | J1: sap code | K1: Size | L1: PR00 Price | M1: EA/Case | N1: Pack/EA | O1: PR00 Price
B2: FMC | C2: =VLOOKUP(F2,[1]Assortment!$F:$AS,27,0) -> 抽纸 | D2: Box Facial | E2: 2312 | F2: 2312-16 | G2: 6923589423128 | H2: 2312-16 | I2: =VLOOKUP(H2,[2]FMC!$A:$D,4,0) -> 231216 舒洁马蹄莲盒面纸200抽3盒 FSC mix70% | J2: 14014482 | K2: # | L2: 243.21307 | M2: 10 | N2: 3 | O2: 243.21307
B3: FMC | C3: =VLOOKUP(F3,[1]Assortment!$F:$AS,27,0) -> 手帕纸 | D3: Hanky | E3: 2701 | F3: 2701-90 | G3: 6923589427010 | H3: 2701-90 | I3: =VLOOKUP(H3,[2]FMC!$A:$D,4,0) -> 270190舒洁小熊印花手帕纸3层10包FSC mix70% | J3: 14016871 | K3: # | L3: 208.46834 | M3: 36 | N3: 10 | O3: 208.46834
B4: FMC | C4: =VLOOKUP(F4,[1]Assortment!$F:$AS,27,0) -> 抽纸 | D4: Poly Facial | E4: 2103 | F4: 2103-90 | G4: 6923589421032 | H4: 2103-90 | I4: =VLOOKUP(H4,[2]FMC!$A:$D,4,0) -> 210390舒洁小熊印花抽纸3层80抽4包FSC mix70% | J4: 14016868 | K4: # | L4: 287.22305 | M4: 24 | N4: 4 | O4: 287.22305
B5: FMC | C5: =VLOOKUP(F5,[1]Assortment!$F:$AS,27,0) -> 抽纸 | D5: Poly Facial | E5: 2107 | F5: 2107-61 | G5: 6923589421070 | H5: 2107-61 | I5: =VLOOKUP(H5,[2]FMC!$A:$D,4,0) -> 210761舒洁卡通系列抽纸200抽3包 FSC mix70% | J5: 14014470 | K5: # | L5: 338.18199 | M5: 20 | N5: 3 | O5: 338.18199
B6: FMC | C6: =VLOOKUP(F6,[1]Assortment!$F:$AS,27,0) -> 抽纸 | D6: Poly Facial | E6: 2148 | F6: 2148-90 | G6: 6923589421483 | H6: 2148-90 | I6: =VLOOKUP(H6,[2]FMC!$A:$D,4,0) -> 214890舒洁小熊印花抽纸3层80抽16包FSC mix70% | J6: 14016869 | K6: # | L6: 283.80123 | M6: 6 | N6: 16 | O6: 283.80123
B7: FMC | C7: =VLOOKUP(F7,[1]Assortment!$F:$AS,27,0) -> 乳霜纸 | D7: Poly Facial | E7: 2152 | F7: 2152-04 | G7: 6923589421520 | H7: 2152-04 | I7: =VLOOKUP(H7,[2]FMC!$A:$D,4,0) -> 215204舒洁鎏金系列乳霜纸巾40抽8包 | J7: 14014940 | K7: Lotion 3Ply | L7: 105.788 | M7: 4 | N7: 8 | O7: 105.788
B8: FMC | C8: =VLOOKUP(F8,[1]Assortment!$F:$AS,27,0) -> 乳霜纸 | D8: Poly Facial | E8: 2155 | F8: 2155-03 | G8: 6923589421551 | H8: 2155-03 | I8: =VLOOKUP(H8,[2]FMC!$A:$D,4,0) -> 215503舒洁®北海道轻牛乳系列乳霜纸面巾40抽3包装 | J8: 14016306 | K8: Lotion 4Ply | L8: 222.4 | M8: 16 | N8: 3 | O8: 222.4
B9: FMC | C9: =VLOOKUP(F9,[1]Assortment!$F:$AS,27,0) -> 乳霜纸 | D9: Poly Facial | E9: 2156 | F9: 2156-10 | G9: 6923589421568 | H9: 2156-10 | I9: =VLOOKUP(H9,[2]FMC!$A:$D,4,0) -> 215610舒洁®北海道轻牛乳系列乳霜纸面巾100抽3包装 | J9: 14016307 | K9: Lotion 4Ply | L9: 215.4 | M9: 6 | N9: 3 | O9: 215.4
B10: FMC | C10: =VLOOKUP(F10,[1]Assortment!$F:$AS,27,0) -> 乳霜纸 | D10: Poly Facial | E10: 2162 | F10: 2162-08 | G10: 6923589421629 | H10: 2162-08 | I10: =VLOOKUP(H10,[2]FMC!$A:$D,4,0) -> 216208舒洁®北海道牛乳系列乳霜纸面巾20抽8包装 | J10: 14015110 | K10: Lotion 6Ply | L10: 100.4986 | M10: 4 | N10: 8 | O10: 100.4986
B11: FMC | C11: =VLOOKUP(F11,[1]Assortment!$F:$AS,27,0) -> 乳霜纸 | D11: Poly Facial | E11: 2167 | F11: 2167-10 | G11: 6923589421605 | H11: 2167-10 | I11: =VLOOKUP(H11,[2]FMC!$A:$D,4,0) -> 216710舒洁®牛乳系列乳霜纸面巾口袋包7抽10包装 | J11: 14016042 | K11: Lotion 6Ply | L11: 202.8 | M11: 12 | N11: 10 | O11: 202.8
B12: FMC | C12: =VLOOKUP(F12,[1]Assortment!$F:$AS,27,0) -> 乳霜纸 | D12: Poly Facial | E12: 2168 | F12: 2168-05 | G12: 6923589421681 | H12: 2168-05 | I12: =VLOOKUP(H12,[2]FMC!$A:$D,4,0) -> 216805舒洁®北海道牛乳系列乳霜纸面巾80抽5包装 | J12: 14015111 | K12: Lotion 6Ply | L12: 215.568 | M12: 3 | N12: 5 | O12: 215.568
B13: FMC | C13: =VLOOKUP(F13,[1]Assortment!$F:$AS,27,0) -> 乳霜纸 | D13: Poly Facial | E13: 2168-00 | F13: 2168-00 | G13: 6923589421681 | H13: 2168-00 | I13: 216800舒洁®北海道牛乳系列乳霜纸面巾80抽5包装（山姆） | J13: 14018015 | K13: Lotion 6Ply | L13: 431.136 | M13: 6 | N13: 5 | O13: 431.136
A14: 山姆专供 | B14: FMC | C14: =VLOOKUP(F14,[1]Assortment!$F:$AS,27,0) -> 乳霜纸 | D14: Poly Facial | E14: 2169 | F14: 2169-00 | G14: 6923589421704 | H14: 2169-00 | I14: =VLOOKUP(H14,[2]FMC!$A:$D,4,0) -> 216900舒洁®北海道牛乳系列乳霜纸面巾80抽6包装 | J14: 14018125 | K14: Lotion 6Ply-山姆 | L14: 431.136 | M14: 6 | N14: 6 | O14: 431.136
B15: FMC | C15: =VLOOKUP(F15,[1]Assortment!$F:$AS,27,0) -> 湿厕纸 | D15: Wet Wipes | E15: 2613 | F15: 2613-00 | G15: 6923589426136 | H15: 2613-00 | I15: =VLOOKUP(H15,[2]FMC!$A:$D,4,0) -> 261300舒洁无香湿巾单包装 | J15: 14004626 | K15: # | L15: 91.36283 | M15: 30 | N15: 1 | O15: 91.36283
B16: FMC | C16: =VLOOKUP(F16,[1]Assortment!$F:$AS,27,0) -> 洗脸巾 | D16: Dry Wipes | E16: 2530 | F16: 2530-00 | G16: 6923589425306 | H16: 2530-00 | I16: =VLOOKUP(H16,[2]FMC!$A:$D,4,0) -> 253000舒洁蚕丝洗脸巾80抽3包装 | J16: 14015043 | K16: # | L16: 358.2 | M16: 6 | N16: 3 | O16: 358.2
B17: FMC | C17: =VLOOKUP(F17,[1]Assortment!$F:$AS,27,0) -> 湿厕纸 | D17: MBT | E17: 2655 | F17: 2655-10 | G17: 6923589426556 | H17: 2655-10 | I17: =VLOOKUP(H17,[2]FMC!$A:$D,4,0) -> 265510舒洁湿厕纸7抽6包装 | J17: 14017863 | K17: 7P-55gsm | L17: 179.2 | M17: 16 | N17: 6 | O17: 179.2
B18: FMC | C18: =VLOOKUP(F18,[1]Assortment!$F:$AS,27,0) -> 湿厕纸 | D18: MBT | E18: 2608 | F18: 2608-00 | G18: 6923589426082 | H18: 2608-00 | I18: =VLOOKUP(H18,[2]FMC!$A:$D,4,0) -> 260800舒洁湿厕纸(65gsm)7抽6包装 | J18: 14018368 | K18: 7P-65gsm | L18: 179.2 | M18: 16 | N18: 6 | O18: 179.2
A19: 山姆专供 | B19: FMC | C19: =VLOOKUP(F19,[1]Assortment!$F:$AS,27,0) -> 湿厕纸 | D19: MBT | E19: 2609 | F19: 2609-00 | G19: 6923589426099 | H19: 2609-00 | I19: =VLOOKUP(H19,[2]FMC!$A:$D,4,0) -> 260900舒洁湿厕纸(65gsm)8片x48包 | J19: 14018377 | K19: 8P-65gsm-山姆 | L19: 102.4 | M19: 1 | N19: 48 | O19: 102.4
B20: FMC | C20: =VLOOKUP(F20,[1]Assortment!$F:$AS,27,0) -> 湿厕纸 | D20: MBT | E20: 2670 | F20: 2670-40 | G20: 6923589426709 | H20: 2670-40 | I20: =VLOOKUP(H20,[2]FMC!$A:$D,4,0) -> D267040舒洁湿厕纸旅行装10包装 | J20: 14017871 | K20: 10P-55gsm | L20: 151.33 | M20: 4 | N20: 10 | O20: 151.33
B21: FMC | C21: =VLOOKUP(F21,[1]Assortment!$F:$AS,27,0) -> 湿厕纸 | D21: MBT | E21: 2610 | F21: 2610-00 | G21: 6923589426105 | H21: 2610-00 | I21: =VLOOKUP(H21,[2]FMC!$A:$D,4,0) -> 261000舒洁湿厕纸(65gsm)旅行装10片x10包装 | J21: 14018369 | K21: 10P-65gsm | L21: 151.33 | M21: 4 | N21: 10 | O21: 151.33
B22: FMC | C22: =VLOOKUP(F22,[1]Assortment!$F:$AS,27,0) -> 湿厕纸 | D22: MBT | E22: 2682 | F22: 2682-20 | G22: 6923589426822 | H22: 2682-20 | I22: =VLOOKUP(H22,[2]FMC!$A:$D,4,0) -> 268220舒洁女性湿厕纸10包装 | J22: 14014250 | K22: 24P | L22: 255.40531 | M22: 4 | N22: 10 | O22: 255.40531
B23: FMC | C23: =VLOOKUP(F23,[1]Assortment!$F:$AS,27,0) -> 湿厕纸 | D23: MBT | E23: 2694 | F23: 2694-30 | G23: 6923589426945 | H23: 2694-30 | I23: =VLOOKUP(H23,[2]FMC!$A:$D,4,0) -> D269430舒洁湿厕纸家庭装40抽 | J23: 14014247 | K23: 40P-55gsm | L23: 367.52 | M23: 40 | N23: 1 | O23: 367.52197
B24: FMC | C24: =VLOOKUP(F24,[1]Assortment!$F:$AS,27,0) -> 湿厕纸 | D24: MBT | E24: 2694 | F24: 2694-50 | G24: 6923589426945 | H24: 2694-50 | I24: =VLOOKUP(H24,[2]FMC!$A:$D,4,0) -> D269450舒洁湿厕纸家庭装40抽 | J24: 14017864 | K24: 40P-55gsm | L24: 367.52 | M24: 40 | N24: 1 | O24: 367.52
B25: FMC | C25: =VLOOKUP(F25,[1]Assortment!$F:$AS,27,0) -> 湿厕纸 | D25: MBT | E25: 2620 | F25: 2620-00 | G25: 6923589426204 | H25: 2620-00 | I25: =VLOOKUP(H25,[2]FMC!$A:$D,4,0) -> 262000舒洁湿厕纸(65gsm)家庭装40抽 | J25: 14018370 | K25: 40P-65gsm | L25: 367.52 | M25: 40 | N25: 1 | O25: 367.52
B26: FMC | C26: =VLOOKUP(F26,[1]Assortment!$F:$AS,27,0) -> 湿厕纸 | D26: MBT | E26: 2694 | F26: 2694-60 | G26: 6923589420011 | H26: 2694-60 | I26: =VLOOKUP(H26,[2]FMC!$A:$D,4,0) -> D269460舒洁湿厕纸家庭装40抽10包装 | J26: 14017872 | K26: 40P-55gsm | L26: 330.25 | M26: 4 | N26: 10 | O26: 330.25
B27: FMC | C27: =VLOOKUP(F27,[1]Assortment!$F:$AS,27,0) -> 湿厕纸 | D27: MBT | E27: 2624 | F27: 2624-00 | G27: 6923589426242 | H27: 2624-00 | I27: =VLOOKUP(H27,[2]FMC!$A:$D,4,0) -> 262400舒洁湿厕纸(65gsm)家庭装40抽10包装 | J27: 14018371 | K27: 40P-65gsm | L27: 330.25 | M27: 4 | N27: 10 | O27: 330.25
B28: FMC | C28: =VLOOKUP(F28,[1]Assortment!$F:$AS,27,0) -> 湿厕纸 | D28: MBT | E28: 2673 | F28: 2673-00 | G28: 6923589426730 | H28: 2673-00 | I28: =VLOOKUP(H28,[2]FMC!$A:$D,4,0) -> 267300舒洁®山茶花系列湿巾（湿厕纸）60片 | J28: 14016683 | K28: 60P | L28: 244.8 | M28: 24 | N28: 1 | O28: 244.8
B29: FMC | C29: =VLOOKUP(F29,[1]Assortment!$F:$AS,27,0) -> 湿厕纸 | D29: MBT | E29: 2674 | F29: 2674-00 | G29: 6923589426730 | H29: 2674-00 | I29: =VLOOKUP(H29,[2]FMC!$A:$D,4,0) -> 267400舒洁®山茶花系列湿巾（湿厕纸）60片x4包 | J29: 14016684 | K29: 60P | L29: 41.9 | M29: 1 | N29: 4 | O29: 41.9
B30: FMC | C30: =VLOOKUP(F30,[1]Assortment!$F:$AS,27,0) -> 湿厕纸 | D30: MBT | E30: 2660 | F30: 2660-10 | G30: 6923589426600 | H30: 2660-10 | I30: =VLOOKUP(H30,[2]FMC!$A:$D,4,0) -> 266010舒洁湿厕纸80片 | J30: 14017865 | K30: 80P | L30: 326.88 | M30: 24 | N30: 1 | O30: 326.88
B31: FMC | C31: =VLOOKUP(F31,[1]Assortment!$F:$AS,27,0) -> 湿厕纸 | D31: MBT | E31: 2634 | F31: 2634-00 | G31: 6923589426341 | H31: 2634-00 | I31: =VLOOKUP(H31,[2]FMC!$A:$D,4,0) -> 263400舒洁湿厕纸(65gsm)80片 | J31: 14018372 | K31: 80P-55gsm | L31: 326.88 | M31: 24 | N31: 1 | O31: 326.88
... B33: FMC | C33: =VLOOKUP(F33,[1]Assortment!$F:$AS,27,0) -> 湿厕纸 | D33: MBT | E33: 2661 | F33: 2661-10 | G33: 6923589426617 | H33: 2661-10 | I33: =VLOOKUP(H33,[2]FMC!$A:$D,4,0) -> 266110舒洁湿厕纸80片x3包 | J33: 14017866 | K33: 80P-55gsm | L33: 310.48 | M33: 8 | N33: 3 | O33: 310.48
B34: FMC | C34: 湿厕纸 | D34: MBT | E34: 2635 | F34: 2635-00 | G34: 6923589426358 | H34: 2635-00 | I34: =VLOOKUP(H34,[2]FMC!$A:$D,4,0) -> 263500舒洁湿厕纸(65gsm)80片x3包 | J34: 14018373 | K34: 80P-65gsm | L34: 310.48 | M34: 8 | N34: 3 | O34: 310.48
B35: FMC | C35: =VLOOKUP(F35,[1]Assortment!$F:$AS,27,0) -> 湿厕纸 | D35: MBT | E35: 2662 | F35: 2662-10 | G35: 6923589426624 | H35: 2662-10 | I35: =VLOOKUP(H35,[2]FMC!$A:$D,4,0) -> 266210舒洁湿厕纸80片x6包 | J35: 14017868 | K35: 80P | L35: 69.44 | M35: 1 | N35: 6 | O35: 69.44
B36: FMC | C36: =VLOOKUP(F36,[1]Assortment!$F:$AS,27,0) -> 湿厕纸 | D36: MBT | E36: 2636 | F36: 2636-00 | G36: 6923589426365 | H36: 2636-00 | I36: =VLOOKUP(H36,[2]FMC!$A:$D,4,0) -> 263600舒洁湿厕纸(65gsm)80片x6包 | J36: 14018374 | K36: 80P-65gsm | L36: 69.44 | M36: 1 | N36: 6 | O36: 69.44
B37: FMC | C37: =VLOOKUP(F37,[1]Assortment!$F:$AS,27,0) -> 湿厕纸 | D37: MBT | E37: 2664 | F37: 2664-10 | G37: 6923589426600 | H37: 2664-10 | I37: =VLOOKUP(H37,[2]FMC!$A:$D,4,0) -> 266410舒洁湿厕纸80片x8包(黄箱) | J37: 14017869 | K37: 80P-55gsm | L37: 92.6 | M37: 1 | N37: 8 | O37: 92.6
B38: FMC | C38: 湿厕纸 | D38: MBT | E38: 2637 | F38: 2637-00 | G38: 6923589426372 | H38: 2637-00 | I38: =VLOOKUP(H38,[2]FMC!$A:$D,4,0) -> 263700舒洁湿厕纸(65gsm)80片x8包 | J38: 14018375 | K38: 80P-65gsm | L38: 92.6 | M38: 1 | N38: 8 | O38: 92.6
B39: FMC | C39: 湿厕纸 | D39: MBT | E39: 2665 | F39: 2665-10 | G39: 6923589426600 | H39: 2665-10 | I39: =VLOOKUP(H39,[2]FMC!$A:$D,4,0) -> D266510舒洁湿厕纸80片x10包-京东 | J39: 14017870 | K39: 80P-55gsm | L39: 115.7 | M39: 1 | N39: 10 | O39: 115.7
B40: FMC | C40: 湿厕纸 | D40: MBT | E40: 2638 | F40: 2638-00 | G40: 6923589426389 | H40: 2638-00 | I40: =VLOOKUP(H40,[2]FMC!$A:$D,4,0) -> 263800舒洁湿厕纸(65gsm)80片x10包 | J40: 14018376 | K40: 80P-65gsm | L40: 115.7 | M40: 1 | N40: 10 | O40: 115.7
B41: FMC | C41: =VLOOKUP(F41,[1]Assortment!$F:$AS,27,0) -> 湿厕纸 | D41: MBT | E41: 2666 | F41: 2666-00 | G41: 6923589426662 | H41: 2666-00 | I41: =VLOOKUP(H41,[2]FMC!$A:$D,4,0) -> 266600舒洁湿厕纸100片x6包 | J41: 14016486 | K41: 100P | L41: 86.8 | M41: 1 | N41: 1 | O41: 86.8
A42: 官方PR00未出 | B42: FMC | C42: =VLOOKUP(F42,[1]Assortment!$F:$AS,27,0) -> 湿厕纸 | D42: MBT | E42: 2653 | F42: 2653-00 | G42: 6923589426532 | H42: 2653-00 | I42: 2653-00舒洁小熊湿厕纸40片 | J42: 14018677 | K42: 40P-小熊 | L42: 367.52 | M42: 40 | N42: 1 | O42: 367.52197
A43: 官方PR00未出 | B43: FMC | C43: =VLOOKUP(F43,[1]Assortment!$F:$AS,27,0) -> 湿厕纸 | D43: MBT | E43: 2657 | F43: 2657-00 | G43: 6923589426570 | H43: 2657-00 | I43: 2657-00舒洁小熊湿厕纸80片 | J43: 14018689 | K43: 80P-小熊 | L43: 326.88 | M43: 24 | N43: 1 | O43: 326.4
A44: 官方PR00未出 | B44: FMC | C44: =VLOOKUP(F44,[1]Assortment!$F:$AS,27,0) -> 湿厕纸 | D44: MBT | E44: 2658 | F44: 2658-00 | G44: 6923589426587 | H44: 2658-00 | I44: 2658-00舒洁小熊湿厕纸80片x8包 | J44: 14018693 | K44: 80P-小熊 | L44: 92.533333 | M44: 1 | N44: 8 | O44: 92.533333
A45: 官方PR00未出 | B45: FMC | C45: =VLOOKUP(F45,[1]Assortment!$F:$AS,27,0) -> 湿厕纸 | D45: MBT | E45: 2659 | F45: 2659-00 | G45: 6923589426594 | H45: 2659-00 | I45: 2659-00舒洁小熊湿厕纸80片×10包 | J45: 14018675 | K45: 80P-小熊 | L45: 115.66667 | M45: 1 | N45: 10 | O45: 115.66667
B46: FMC | C46: =VLOOKUP(F46,[1]Assortment!$F:$AS,27,0) -> 卷纸 | D46: RBT | E46: 2291 | F46: 2291-60 | G46: 6923589422916 | H46: 2291-60 | I46: =VLOOKUP(H46,[2]FMC!$A:$D,4,0) -> 229160舒洁绿茶洋甘菊印花清香卷纸10粒 | J46: 14014479 | K46: # | L46: 153.64889 | M46: 5 | N46: 10 | O46: 153.64889
B47: FMC | C47: =VLOOKUP(F47,[1]Assortment!$F:$AS,27,0) -> 卷纸 | D47: RBT | E47: 2216 | F47: 2216-35 | G47: 6923589422169 | H47: 2216-35 | I47: =VLOOKUP(H47,[2]FMC!$A:$D,4,0) -> 221635舒洁卷纸3层纯白10粒（蓝色） | J47: 14015861 | K47: # | L47: 240.89676 | M47: 10 | N47: 10 | O47: 240.89676

Sheet Sheet2
A2: CVS | B2: 全家
A3: CVS | B3: 罗森
A4: CVS | B4: 711
A5: CVS-Others | B5: 便利蜂
A6: CVS-Others | B6: 美宜佳
A7: CVS-Others | B7: 十足
A8: CVS-Others | B8: 唐久便利店
A9: CVS-Others | B9: 金虎便利店
A10: CVS-Others | B10: 芙蓉兴盛
A11: CVS-Others | B11: 左邻右舍
A12: NKA | B12: 大润发
A13: NKA | B13: 盒马
A14: NKA | B14: 麦德龙
A15: NKA | B15: 永辉
A16: NKA | B16: 山姆
... A54: RLKA | B54: 易初莲花

Sheet 26年价格体系T1
B1: 销售填写 | C1: 销售填写 | D1: 公式 | E1: 公式 | F1: 公式 | G1: 公式 | H1: 公式 | I1: KA填写 | J1: =SUM(J3:J26) -> 78.541439 | K1: =SUM(K3:K26) -> 88.751826 | N1: =SUM(N3:N26) -> 87.885939 | O1: =SUM(O3:O26) -> 90.522518 | P1: =SUM(P3:P26) -> 77.775168 | R1: =SUM(R3:R26) -> 90.517718 | S1: 不填 | T1: 不填 | U1: 不填 | V1: 公式 | W1: 公式 | X1: 公式 | Y1: 公式 | Z1: 参照O列 | AA1: 参照O列 | AC1: 参照P列 | AD1: 参照O列 | AE1: 参照O列 | AI1: EDLP | AJ1: EDLP
B2: 客户 | C2: Product Code | D2: 产品名称 | E2: 箱规 | F2: 包/箱 | G2: PR00 (箱价)-未税 | H2: PR00/EA | I2: 进货箱数 | J2: 中提供台参考nsv价格 | K2: 1.13含税 | L2: 经销商实际到手价格@ Shengtao | M2: 经销商打款价格（3返利%） | N2: 客户实际含税到手价格 | O2: 剔除3%返利（客户打款含税价格） | P2: nsv实际需要价格 | Q2: 实际需求与指引差 | R2: 打款价格/包-含税 | S2: 后补/包-含税 | T2: 后补金额-含税-TTL | U2: 后补金额未税-TTL | V2: GSV | W2: NSV | X2: DQF COGS % VS GSV | Y2: DQF DE % VS GSV | Z2: GP | AA2: GP% | AC2: NSV | AD2: GP | AE2: GP%（我们Propose） | AF2: Biz.Weight-2025 | AG2: Biz.Weight-2026-Proposal-@ Shengtao | AI2: 含票扣3.4%箱价 /不含税 | AJ2: 维护折扣金额-1000箱 | AK2: Sales Quantity CS | AL2: GSV
B3: T1级 | C3: 2701-90 | D3: =VLOOKUP($C3,[1]Assortment!$F:$BA,5,0) -> 270190舒洁小熊印花手帕纸3层10包FSC mix70% | E3: =VLOOKUP($C3,[1]Assortment!$F:$AM,7,0) -> 36 | F3: =VLOOKUP($C3,[1]Assortment!$F:$AM,31,0) -> 360 | G3: =VLOOKUP($C3,[1]Assortment!$F:$AM,14,0) -> 208.46834 | H3: =G3/E3 -> 5.7907872 | I3: 1 | J3: 0.38649421 | K3: =J3*1.13 -> 0.43673846 | L3: 0.39 | M3: =L3*1.03 -> 0.4017 | N3: 0.39 | O3: =N3*1.03 -> 0.4017 | P3: =N3/1.13 -> 0.34513274 | Q3: =P3-J3 -> -0.041361471 | R3: =O3 -> 0.4017 | V3: =G3*I3 -> 208.46834 | W3: =R3*F3*I3/1.13 -> 127.97522 | X3: ='25年版cogs'!F4 -> 0.42397103 | Y3: ='25年版cogs'!G4 -> 0.025426167 | Z3: =W3-V3*(X3+Y3) -> 34.290133 | AA3: =Z3/W3 -> 0.26794354 | AC3: =P3*F3*I3 -> 124.24779 | AD3: =AC3-V3*(X3+Y3) -> 30.5627 | AE3: =AD3/AC3 -> 0.24598184 | AF3: 0.027504779 | AG3: 0.018 | AH3: =SUM(AG3:AG26) -> 0.99974101 | AI3: =R3*F3/0.966/1.13 -> 132.47953 | AJ3: =(G3-AI3)*1000 -> 75988.815 | AK3: 1.341 | AL3: =AK3*G3 -> 279.55604
B4: T1级 | C4: 2694-40 | D4: =VLOOKUP($C4,[1]Assortment!$F:$BA,5,0) -> 269440舒洁湿厕纸家庭装40抽10包装 | E4: =VLOOKUP($C4,[1]Assortment!$F:$AM,7,0) -> 4 | F4: =VLOOKUP($C4,[1]Assortment!$F:$AM,31,0) -> 40 | G4: =VLOOKUP($C4,[1]Assortment!$F:$AM,14,0) -> 330.25 | H4: =G4/E4 -> 82.5625 | I4: 1 | J4: 2.7785183 | K4: =J4*1.13 -> 3.1397256 | L4: 3.65 | M4: =L4*1.03 -> 3.7595 | N4: 3.65 | O4: =N4*1.03 -> 3.7595 | P4: =N4/1.13 -> 3.2300885 | Q4: =P4-J4 -> 0.45157023 | R4: =O4 -> 3.7595 | V4: =G4*I4 -> 330.25 | W4: =R4*F4*I4/1.13 -> 133.07965 | X4: ='25年版cogs'!F5 -> 0.26981474 | Y4: ='25年版cogs'!G5 -> 0.025386209 | Z4: =W4-V4*(X4+Y4) -> 35.589534 | AA4: =Z4/W4 -> 0.26743033 | AC4: =P4*F4*I4 -> 129.20354 | AD4: =AC4-V4*(X4+Y4) -> 31.713428 | AE4: =AD4/AC4 -> 0.24545324 | AF4: 0.052241538 | AG4: 0.04 | AK4: 2.617 | AL4: =AK4*G4 -> 864.26425
B5: T1级 | C5: 2694-30 | D5: =VLOOKUP($C5,[1]Assortment!$F:$BA,5,0) -> 269430舒洁湿厕纸家庭装40抽 | E5: =VLOOKUP($C5,[1]Assortment!$F:$AM,7,0) -> 40 | F5: =VLOOKUP($C5,[1]Assortment!$F:$AM,31,0) -> 40 | G5: =VLOOKUP($C5,[1]Assortment!$F:$AM,14,0) -> 367.52 | H5: =G5/E5 -> 9.188 | I5: 1 | J5: 3.5557967 | K5: =J5*1.13 -> 4.0180503 | L5: 3.6 | M5: =L5*1.03 -> 3.708 | N5: 3.6 | O5: =N5*1.03 -> 3.708 | P5: =N5/1.13 -> 3.1858407 | Q5: =P5-J5 -> -0.36995598 | R5: =O5 -> 3.708 | V5: =G5*I5 -> 367.52 | W5: =R5*F5*I5/1.13 -> 131.25664 | X5: ='25年版cogs'!F6 -> 0.26981474 | Y5: ='25年版cogs'!G6 -> 0.025386209 | Z5: =W5-V5*(X5+Y5) -> 22.764386 | AA5: =Z5/W5 -> 0.17343417 | AC5: =P5*F5*I5 -> 127.43363 | AD5: =AC5-V5*(X5+Y5) -> 18.941377 | AE5: =AD5/AC5 -> 0.1486372 | AF5: 0.14847537 | AG5: 0.17 | AK5: 8.141 | AL5: =AK5*G5 -> 2991.9803
B6: T1级 | C6: 2682-20 | D6: =VLOOKUP($C6,[1]Assortment!$F:$BA,5,0) -> 268220舒洁女性湿厕纸10包装 | E6: =VLOOKUP($C6,[1]Assortment!$F:$AM,7,0) -> 4 | F6: =VLOOKUP($C6,[1]Assortment!$F:$AM,31,0) -> 40 | G6: =VLOOKUP($C6,[1]Assortment!$F:$AM,14,0) -> 255.40531 | H6: =G6/E6 -> 63.851327 | I6: 1 | J6: 2.2651221 | K6: =J6*1.13 -> 2.559588 | L6: 2.559588 | M6: =L6*1.03 -> 2.6363756 | N6: =J6*1.13 -> 2.559588 | O6: =N6*1.03 -> 2.6363756 | P6: =N6/1.13 -> 2.2651221 | Q6: =P6-J6 -> 0 | R6: =O6 -> 2.6363756 | V6: =G6*I6 -> 255.40531 | W6: =R6*F6*I6/1.13 -> 93.323031 | X6: ='25年版cogs'!F7 -> 0.22151094 | Y6: ='25年版cogs'!G7 -> 0.025347831 | Z6: =W6-V6*(X6+Y6) -> 30.273991 | AA6: =Z6/W6 -> 0.32439999 | AC6: =P6*F6*I6 -> 90.604885 | AD6: =AC6-V6*(X6+Y6) -> 27.555844 | AE6: =AD6/AC6 -> 0.30413199 | AF6: 0.0019531766 | AG6: 0.0019531766 | AK6: 0.102 | AL6: =AK6*G6 -> 26.051342
B7: T1级 | C7: 2674-00 | D7: =VLOOKUP($C7,[1]Assortment!$F:$BA,5,0) -> 267400舒洁山茶花系列湿厕纸60片x4包 | E7: =VLOOKUP($C7,[1]Assortment!$F:$AM,7,0) -> 1 | F7: =VLOOKUP($C7,[1]Assortment!$F:$AM,31,0) -> 4 | G7: =VLOOKUP($C7,[1]Assortment!$F:$AM,14,0) -> 41.9 | H7: =G7/E7 -> 41.9 | I7: 1 | J7: 5.0396416 | K7: =J7*1.13 -> 5.694795 | L7: 5.694795 | M7: =L7*1.03 -> 5.8656389 | N7: =J7*1.13 -> 5.694795 | O7: =N7*1.03 -> 5.8656389 | P7: =N7/1.13 -> 5.0396416 | Q7: =P7-J7 -> 0 | R7: =O7 -> 5.8656389 | V7: =G7*I7 -> 41.9 | W7: =R7*F7*I7/1.13 -> 20.763323 | X7: ='25年版cogs'!F8 -> 0.35939124 | Y7: ='25年版cogs'!G8 -> 0.02533352 | Z7: =W7-V7*(X7+Y7) -> 4.6433559 | AA7: =Z7/W7 -> 0.2236326 | AC7: =P7*F7*I7 -> 20.158566 | AD7: =AC7-V7*(X7+Y7) -> 4.0385989 | AE7: =AD7/AC7 -> 0.20034157 | AF7: 0.00051970605 | AG7: 0.00051970605 | AK7: 0.031 | AL7: =AK7*G7 -> 1.2989
B8: T1级 | C8: 2673-00 | D8: =VLOOKUP($C8,[1]Assortment!$F:$BA,5,0) -> 267300舒洁山茶花系列湿厕纸60片 | E8: =VLOOKUP($C8,[1]Assortment!$F:$AM,7,0) -> 24 | F8: =VLOOKUP($C8,[1]Assortment!$F:$AM,31,0) -> 24 | G8: =VLOOKUP($C8,[1]Assortment!$F:$AM,14,0) -> 244.8 | H8: =G8/E8 -> 10.2 | I8: 1 | J8: 5.3658761 | K8: =J8*1.13 -> 6.06344 | L8: 6.06344 | M8: =L8*1.03 -> 6.2453432 | N8: =J8*1.13 -> 6.06344 | O8: =N8*1.03 -> 6.2453432 | P8: =N8/1.13 -> 5.3658761 | Q8: =P8-J8 -> 0 | R8: =O8 -> 6.2453432 | V8: =G8*I8 -> 244.8 | W8: =R8*F8*I8/1.13 -> 132.64446 | X8: ='25年版cogs'!F9 -> 0.35822651 | Y8: ='25年版cogs'!G9 -> 0.025367759 | Z8: =W8-V8*(X8+Y8) -> 38.740579 | AA8: =Z8/W8 -> 0.29206331 | AC8: =P8*F8*I8 -> 128.78103 | AD8: =AC8-V8*(X8+Y8) -> 34.877148 | AE8: =AD8/AC8 -> 0.27082521 | AF8: 0.0035206815 | AG8: 0.0035206815 | AK8: 0.167 | AL8: =AK8*G8 -> 40.8816
B9: T1级 | C9: 2670-30 | D9: =VLOOKUP($C9,[1]Assortment!$F:$BA,5,0) -> 267030舒洁湿厕纸旅行装10包装 | E9: =VLOOKUP($C9,[1]Assortment!$F:$AM,7,0) -> 4 | F9: =VLOOKUP($C9,[1]Assortment!$F:$AM,31,0) -> 40 | G9: =VLOOKUP($C9,[1]Assortment!$F:$AM,14,0) -> 151.33 | H9: =G9/E9 -> 37.8325 | I9: 1 | J9: 0.94070026 | K9: =J9*1.13 -> 1.0629913 | L9: 1.0629913 | M9: =L9*1.03 -> 1.094881 | N9: =J9*1.13 -> 1.0629913 | O9: =N9*1.03 -> 1.094881 | P9: =N9/1.13 -> 0.94070026 | Q9: =P9-J9 -> 0 | R9: =O9 -> 1.094881 | V9: =G9*I9 -> 151.33 | W9: =R9*F9*I9/1.13 -> 38.756851 | X9: ='25年版cogs'!F10 -> 0.18260265 | Y9: ='25年版cogs'!G10 -> 0.025370117 | Z9: =W9-V9*(X9+Y9) -> 7.2843316 | AA9: =Z9/W9 -> 0.18794952 | AC9: =P9*F9*I9 -> 37.62801 | AD9: =AC9-V9*(X9+Y9) -> 6.1554913 | AE9: =AD9/AC9 -> 0.16358801 | AF9: 0.00056438213 | AG9: 0.00056438213 | AK9: 0.011 | AL9: =AK9*G9 -> 1.66463
B10: T1级 | C10: 2666-00 | D10: =VLOOKUP($C10,[1]Assortment!$F:$BA,5,0) -> 266600舒洁湿厕纸100片x6包-植物双萃 | E10: =VLOOKUP($C10,[1]Assortment!$F:$AM,7,0) -> 1 | F10: =VLOOKUP($C10,[1]Assortment!$F:$AM,31,0) -> 6 | G10: =VLOOKUP($C10,[1]Assortment!$F:$AM,14,0) -> 86.8 | H10: =G10/E10 -> 86.8 | I10: 1 | J10: 6.8392271 | K10: =J10*1.13 -> 7.7283267 | L10: 7.7283267 | M10: =L10*1.03 -> 7.9601765 | N10: =J10*1.13 -> 7.7283267 | O10: =N10*1.03 -> 7.9601765 | P10: =N10/1.13 -> 6.8392271 | Q10: =P10-J10 -> 0 | R10: =O10 -> 7.9601765 | V10: =G10*I10 -> 86.8 | W10: =R10*F10*I10/1.13 -> 42.266424 | X10: ='25年版cogs'!F11 -> 0.32309188 | Y10: ='25年版cogs'!G11 -> 0.02533601 | Z10: =W10-V10*(X10+Y10) -> 12.022883 | AA10: =Z10/W10 -> 0.2844547 | AC10: =P10*F10*I10 -> 41.035363 | AD10: =AC10-V10*(X10+Y10) -> 10.791822 | AE10: =AD10/AC10 -> 0.26298834 | AF10: 0.00091353072 | AG10: 0.00091353072 | AK10: 0.064 | AL10: =AK10*G10 -> 5.5552
B11: T1级 | C11: 2662-00 | D11: =VLOOKUP($C11,[1]Assortment!$F:$BA,5,0) -> 266200舒洁湿厕纸80片x6包 | E11: =VLOOKUP($C11,[1]Assortment!$F:$AM,7,0) -> 1 | F11: =VLOOKUP($C11,[1]Assortment!$F:$AM,31,0) -> 6 | G11: =VLOOKUP($C11,[1]Assortment!$F:$AM,14,0) -> 69.44 | H11: =G11/E11 -> 69.44 | I11: 1 | J11: 4.9479304 | K11: =J11*1.13 -> 5.5911613 | L11: 5.9 | M11: =L11*1.03 -> 6.077 | N11: =K11 -> 5.5911613 | O11: =N11*1.03 -> 5.7588962 | P11: =N11/1.13 -> 4.9479304 | Q11: =P11-J11 -> 0 | R11: =O11 -> 5.7588962 | V11: =G11*I11 -> 69.44 | W11: =R11*F11*I11/1.13 -> 30.57821 | X11: ='25年版cogs'!F12 -> 0.34017628 | Y11: ='25年版cogs'!G12 -> 0.025238484 | Z11: =W11-V11*(X11+Y11) -> 5.2038089 | AA11: =Z11/W11 -> 0.1701803 | AC11: =P11*F11*I11 -> 29.687582 | AD11: =AC11-V11*(X11+Y11) -> 4.3131814 | AE11: =AD11/AC11 -> 0.14528571 | AF11: 0.127216 | AG11: 0.17 | AK11: 25.258 | AL11: =AK11*G11 -> 1753.9155
B12: T1级 | C12: 2661-00 | D12: =VLOOKUP($C12,[1]Assortment!$F:$BA,5,0) -> 266100舒洁湿厕纸80片x3包 | E12: =VLOOKUP($C12,[1]Assortment!$F:$AM,7,0) -> 8 | F12: =VLOOKUP($C12,[1]Assortment!$F:$AM,31,0) -> 24 | G12: =VLOOKUP($C12,[1]Assortment!$F:$AM,14,0) -> 310.48 | H12: =G12/E12 -> 38.81 | I12: 1 | J12: 6.0069858 | K12: =J12*1.13 -> 6.787894 | L12: 6.787894 | M12: =L12*1.03 -> 6.9915308 | N12: =J12*1.13 -> 6.787894 | O12: =N12*1.03 -> 6.9915308 | P12: =N12/1.13 -> 6.0069858 | Q12: =P12-J12 -> 0 | R12: =O12 -> 6.9915308 | V12: =G12*I12 -> 310.48 | W12: =R12*F12*I12/1.13 -> 148.49269 | X12: ='25年版cogs'!F13 -> 0.30486433 | Y12: ='25年版cogs'!G13 -> 0.025424502 | Z12: =W12-V12*(X12+Y12) -> 45.944613 | AA12: =Z12/W12 -> 0.30940657 | AC12: =P12*F12*I12 -> 144.16766 | AD12: =AC12-V12*(X12+Y12) -> 41.619583 | AE12: =AD12/AC12 -> 0.28868876 | AF12: 0.0045366619 | AG12: 0.0045366619 | AK12: 0.232 | AL12: =AK12*G12 -> 72.03136
B13: T1级 | C13: 2655-00 | D13: =VLOOKUP($C13,[1]Assortment!$F:$BA,5,0) -> 265500舒洁湿厕纸7抽6包装 | E13: =VLOOKUP($C13,[1]Assortment!$F:$AM,7,0) -> 16 | F13: =VLOOKUP($C13,[1]Assortment!$F:$AM,31,0) -> 96 | G13: =VLOOKUP($C13,[1]Assortment!$F:$AM,14,0) -> 179.2 | H13: =G13/E13 -> 11.2 | I13: 1 | J13: 0.99271976 | K13: =J13*1.13 -> 1.1217733 | L13: 0.95 | M13: =L13*1.03 -> 0.9785 | N13: =L13*1.13 -> 1.0735 | O13: =N13*1.03 -> 1.105705 | P13: =N13/1.13 -> 0.95 | Q13: =P13-J13 -> -0.042719764 | R13: =O13 -> 1.105705 | V13: =G13*I13 -> 179.2 | W13: =R13*F13*I13/1.13 -> 93.936 | X13: ='25年版cogs'!F14 -> 0.27365302 | Y13: ='25年版cogs'!G14 -> 0.025424502 | Z13: =W13-V13*(X13+Y13) -> 40.341308 | AA13: =Z13/W13 -> 0.42945524 | AC13: =P13*F13*I13 -> 91.2 | AD13: =AC13-V13*(X13+Y13) -> 37.605308 | AE13: =AD13/AC13 -> 0.4123389 | AF13: 0.0046618358 | AG13: 0.004 | AK13: 0.306 | AL13: =AK13*G13 -> 54.8352
B14: T1级 | C14: 2613-00 | D14: =VLOOKUP($C14,[1]Assortment!$F:$BA,5,0) -> 261300舒洁无香湿巾单包装 | E14: =VLOOKUP($C14,[1]Assortment!$F:$AM,7,0) -> 30 | F14: =VLOOKUP($C14,[1]Assortment!$F:$AM,31,0) -> 30 | G14: =VLOOKUP($C14,[1]Assortment!$F:$AM,14,0) -> 91.36283 | H14: =G14/E14 -> 3.0454277 | I14: 1 | J14: 1.5982478 | K14: =J14*1.13 -> 1.80602 | L14: 1.53 | M14: =L14*1.03 -> 1.5759 | N14: 1.53 | O14: =N14*1.03 -> 1.5759 | P14: =N14/1.13 -> 1.3539823 | Q14: =P14-J14 -> -0.24426549 | R14: =O14 -> 1.5759 | V14: =G14*I14 -> 91.36283 | W14: =R14*F14*I14/1.13 -> 41.838053 | X14: ='25年版cogs'!F15 -> 0.33593911 | Y14: ='25年版cogs'!G15 -> 0.025420065 | Z14: =W14-V14*(X14+Y14) -> 8.8232565 | AA14: =Z14/W14 -> 0.2108907 | AC14: =P14*F14*I14 -> 40.619469 | AD14: =AC14-V14*(X14+Y14) -> 7.6046724 | AE14: =AD14/AC14 -> 0.18721743 | AF14: 0.090805241 | AG14: 0.090805241 | AK14: 15.2 | AL14: =AK14*G14 -> 1388.715
B15: T1级 | C15: 2530-00 | D15: =VLOOKUP($C15,[1]Assortment!$F:$BA,5,0) -> 253000舒洁蚕丝洗脸巾80抽3包装 | E15: =VLOOKUP($C15,[1]Assortment!$F:$AM,7,0) -> 6 | F15: =VLOOKUP($C15,[1]Assortment!$F:$AM,31,0) -> 18 | G15: =VLOOKUP($C15,[1]Assortment!$F:$AM,14,0) -> 358.2 | H15: =G15/E15 -> 59.7 | I15: 1 | J15: 6.745528 | K15: =J15*1.13 -> 7.6224467 | L15: 7.6224467 | M15: =L15*1.03 -> 7.8511201 | N15: =J15*1.13 -> 7.6224467 | O15: =N15*1.03 -> 7.8511201 | P15: =N15/1.13 -> 6.745528 | Q15: =P15-J15 -> 0 | R15: =O15 -> 7.8511201 | V15: =G15*I15 -> 358.2 | W15: =R15*F15*I15/1.13 -> 125.06209 | X15: ='25年版cogs'!F16 -> 0.24149261 | Y15: ='25年版cogs'!G16 -> 0.025313854 | Z15: =W15-V15*(X15+Y15) -> 29.492013 | AA15: =Z15/W15 -> 0.23581897 | AC15: =P15*F15*I15 -> 121.4195 | AD15: =AC15-V15*(X15+Y15) -> 25.849428 | AE15: =AD15/AC15 -> 0.21289354 | AF15: 0.0034525429 | AG15: 0.0034525429 | AK15: 0.006 | AL15: =AK15*G15 -> 2.1492
B16: T1级 | C16: 2312-16 | D16: =VLOOKUP($C16,[1]Assortment!$F:$BA,5,0) -> 231216 舒洁马蹄莲盒面纸200抽3盒 FSC mix70% | E16: =VLOOKUP($C16,[1]Assortment!$F:$AM,7,0) -> 10 | F16: =VLOOKUP($C16,[1]Assortment!$F:$AM,31,0) -> 30 | G16: =VLOOKUP($C16,[1]Assortment!$F:$AM,14,0) -> 243.21307 | H16: =G16/E16 -> 24.321307 | I16: 1 | J16: 5.1610665 | K16: =J16*1.13 -> 5.8320051 | L16: 6 | M16: =L16*1.03 -> 6.18 | N16: =K16 -> 5.8320051 | O16: =N16*1.03 -> 6.0069653 | P16: =N16/1.13 -> 5.1610665 | Q16: =P16-J16 -> 0 | R16: =O16 -> 6.0069653 | V16: =G16*I16 -> 243.21307 | W16: =R16*F16*I16/1.13 -> 159.47695 | X16: ='25年版cogs'!F17 -> 0.38128924 | Y16: ='25年版cogs'!G17 -> 0.025408135 | Z16: =W16-V16*(X16+Y16) -> 60.562837 | AA16: =Z16/W16 -> 0.37975918 | AC16: =P16*F16*I16 -> 154.83199 | AD16: =AC16-V16*(X16+Y16) -> 55.917877 | AE16: =AD16/AC16 -> 0.36115195 | AF16: 0.11037747 | AG16: 0.07 | AK16: 5.0641 | AL16: =AK16*G16 -> 1231.6553
B17: T1级 | C17: 2291-60 | D17: =VLOOKUP($C17,[1]Assortment!$F:$BA,5,0) -> 229160舒洁绿茶洋甘菊印花清香卷纸10粒 | E17: =VLOOKUP($C17,[1]Assortment!$F:$AM,7,0) -> 5 | F17: =VLOOKUP($C17,[1]Assortment!$F:$AM,31,0) -> 50 | G17: =VLOOKUP($C17,[1]Assortment!$F:$AM,14,0) -> 153.64889 | H17: =G17/E17 -> 30.729778 | I17: 1 | J17: 2.172701 | K17: =J17*1.13 -> 2.4551521 | L17: 2.2 | M17: =L17*1.03 -> 2.266 | N17: 2.2 | O17: =N17*1.03 -> 2.266 | P17: =N17/1.13 -> 1.9469027 | Q17: =P17-J17 -> -0.22579832 | R17: =O17 -> 2.266 | V17: =G17*I17 -> 153.64889 | W17: =R17*F17*I17/1.13 -> 100.26549 | X17: ='25年版cogs'!F18 -> 0.49468307 | Y17: ='25年版cogs'!G18 -> 0.02536674 | Z17: =W17-V17*(X17+Y17) -> 20.360411 | AA17: =Z17/W17 -> 0.203065 | AC17: =P17*F17*I17 -> 97.345133 | AD17: =AC17-V17*(X17+Y17) -> 17.440057 | AE17: =AD17/AC17 -> 0.17915695 | AF17: 0.018186358 | AG17: 0.06 | AK17: 1.5 | AL17: =AK17*G17 -> 230.47333
B18: T1级 | C18: 2216-35 | D18: =VLOOKUP($C18,[1]Assortment!$F:$BA,5,0) -> 221635舒洁卷纸3层纯白10粒（蓝色） | E18: =VLOOKUP($C18,[1]Assortment!$F:$AM,7,0) -> 10 | F18: =VLOOKUP($C18,[1]Assortment!$F:$AM,31,0) -> 100 | G18: =VLOOKUP($C18,[1]Assortment!$F:$AM,14,0) -> 240.89676 | H18: =G18/E18 -> 24.089676 | I18: 1 | J18: 1.6797982 | K18: =J18*1.13 -> 1.898172 | L18: 1.73 | M18: =L18*1.03 -> 1.7819 | N18: 1.73 | O18: =N18*1.03 -> 1.7819 | P18: =N18/1.13 -> 1.5309735 | Q18: =P18-J18 -> -0.14882478 | R18: =O18 -> 1.7819 | V18: =G18*I18 -> 240.89676 | W18: =R18*F18*I18/1.13 -> 157.69027 | X18: ='25年版cogs'!F19 -> 0.47353964 | Y18: ='25年版cogs'!G19 -> 0.025423334 | Z18: =W18-V18*(X18+Y18) -> 37.491703 | AA18: =Z18/W18 -> 0.23775534 | AC18: =P18*F18*I18 -> 153.09735 | AD18: =AC18-V18*(X18+Y18) -> 32.898782 | AE18: =AD18/AC18 -> 0.214888 | AF18: 0.079866435 | AG18: 0.08 | AK18: 4.0652 | AL18: =AK18*G18 -> 979.29351
B19: T1级 | C19: 2168-05 | D19: =VLOOKUP($C19,[1]Assortment!$F:$BA,5,0) -> 216805舒洁®北海道牛乳系列乳霜纸面巾80抽5包装 | E19: =VLOOKUP($C19,[1]Assortment!$F:$AM,7,0) -> 3 | F19: =VLOOKUP($C19,[1]Assortment!$F:$AM,31,0) -> 15 | G19: =VLOOKUP($C19,[1]Assortment!$F:$AM,14,0) -> 215.568 | H19: =G19/E19 -> 71.856 | I19: 1 | J19: 6.5589669 | K19: =J19*1.13 -> 7.4116326 | L19: 7.4116326 | M19: =L19*1.03 -> 7.6339816 | N19: =J19*1.13 -> 7.4116326 | O19: =N19*1.03 -> 7.6339816 | P19: =N19/1.13 -> 6.5589669 | Q19: =P19-J19 -> 0 | R19: =O19 -> 7.6339816 | V19: =G19*I19 -> 215.568 | W19: =R19*F19*I19/1.13 -> 101.33604 | X19: ='25年版cogs'!F20 -> 0.26496938 | Y19: ='25年版cogs'!G20 -> 0.025333387 | Z19: =W19-V19*(X19+Y19) -> 38.756052 | AA19: =Z19/W19 -> 0.38245082 | AC19: =P19*F19*I19 -> 98.384504 | AD19: =AC19-V19*(X19+Y19) -> 35.804517 | AE19: =AD19/AC19 -> 0.36392435 | AF19: 0.023216316 | AG19: 0.023216316 | AK19: 1.6063 | AL19: =AK19*G19 -> 346.26688
B20: T1级 | C20: 2167-10 | D20: =VLOOKUP($C20,[1]Assortment!$F:$BA,5,0) -> 216710舒洁®牛乳系列乳霜纸面巾口袋包7抽10包装 | E20: =VLOOKUP($C20,[1]Assortment!$F:$AM,7,0) -> 12 | F20: =VLOOKUP($C20,[1]Assortment!$F:$AM,31,0) -> 120 | G20: =VLOOKUP($C20,[1]Assortment!$F:$AM,14,0) -> 202.8 | H20: =G20/E20 -> 16.9 | I20: 1 | J20: 0.85 | K20: =J20*1.13 -> 0.9605 | L20: 0.9605 | M20: =L20*1.03 -> 0.989315 | N20: =J20*1.13 -> 0.9605 | O20: =N20*1.03 -> 0.989315 | P20: =N20/1.13 -> 0.85 | Q20: =P20-J20 -> 0 | R20: =O20 -> 0.989315 | V20: =G20*I20 -> 202.8 | W20: =R20*F20*I20/1.13 -> 105.06 | X20: ='25年版cogs'!F21 -> 0.2909103 | Y20: ='25年版cogs'!G21 -> 0.025403037 | Z20: =W20-V20*(X20+Y20) -> 40.911655 | AA20: =Z20/W20 -> 0.38941229 | AC20: =P20*F20*I20 -> 102 | AD20: =AC20-V20*(X20+Y20) -> 37.851655 | AE20: =AD20/AC20 -> 0.37109465 | AF20: 0.0056779478 | AG20: 0.005 | AK20: 0.236 | AL20: =AK20*G20 -> 47.8608
B21: T1级 | C21: 2162-08 | D21: =VLOOKUP($C21,[1]Assortment!$F:$BA,5,0) -> 216208舒洁®北海道牛乳系列乳霜纸面巾20抽8包装 | E21: =VLOOKUP($C21,[1]Assortment!$F:$AM,7,0) -> 4 | F21: =VLOOKUP($C21,[1]Assortment!$F:$AM,31,0) -> 32 | G21: =VLOOKUP($C21,[1]Assortment!$F:$AM,14,0) -> 100.4986 | H21: =G21/E21 -> 25.12465 | I21: 1 | J21: 1.4996182 | K21: =J21*1.13 -> 1.6945686 | L21: 1.6945686 | M21: =L21*1.03 -> 1.7454056 | N21: =J21*1.13 -> 1.6945686 | O21: =N21*1.03 -> 1.7454056 | P21: =N21/1.13 -> 1.4996182 | Q21: =P21-J21 -> 0 | R21: =O21 -> 1.7454056 | V21: =G21*I21 -> 100.4986 | W21: =R21*F21*I21/1.13 -> 49.427417 | X21: ='25年版cogs'!F22 -> 0.29650668 | Y21: ='25年版cogs'!G22 -> 0.025358571 | Z21: =W21-V21*(X21+Y21) -> 17.080409 | AA21: =Z21/W21 -> 0.34556548 | AC21: =P21*F21*I21 -> 47.987783 | AD21: =AC21-V21*(X21+Y21) -> 15.640776 | AE21: =AD21/AC21 -> 0.32593245 | AF21: 0.0058378524 | AG21: 0.005 | AK21: 0.6445 | AL21: =AK21*G21 -> 64.771348
B22: T1级 | C22: 2156-10 | D22: =VLOOKUP($C22,[1]Assortment!$F:$BA,5,0) -> 215610舒洁®北海道轻牛乳系列乳霜纸面巾100抽3包装 | E22: =VLOOKUP($C22,[1]Assortment!$F:$AM,7,0) -> 6 | F22: =VLOOKUP($C22,[1]Assortment!$F:$AM,31,0) -> 18 | G22: =VLOOKUP($C22,[1]Assortment!$F:$AM,14,0) -> 215.4 | H22: =G22/E22 -> 35.9 | I22: 1 | J22: 4.1861298 | K22: =J22*1.13 -> 4.7303267 | L22: 5.2 | M22: =L22*1.03 -> 5.356 | N22: =K22 -> 4.7303267 | O22: =N22*1.03 -> 4.8722365 | P22: =N22/1.13 -> 4.1861298 | Q22: =P22-J22 -> 0 | R22: =O22 -> 4.8722365 | V22: =G22*I22 -> 215.4 | W22: =R22*F22*I22/1.13 -> 77.610846 | X22: ='25年版cogs'!F23 -> 0.22394373 | Y22: ='25年版cogs'!G23 -> 0.02536732 | Z22: =W22-V22*(X22+Y22) -> 23.909246 | AA22: =Z22/W22 -> 0.30806578 | AC22: =P22*F22*I22 -> 75.350336 | AD22: =AC22-V22*(X22+Y22) -> 21.648736 | AE22: =AD22/AC22 -> 0.28730776 | AF22: 0.0062721702 | AG22: 0.01 | AK22: 0.479 | AL22: =AK22*G22 -> 103.1766
B23: T1级 | C23: 2155-03 | D23: =VLOOKUP($C23,[1]Assortment!$F:$BA,5,0) -> 215503舒洁®北海道轻牛乳系列乳霜纸面巾40抽3包装 | E23: =VLOOKUP($C23,[1]Assortment!$F:$AM,7,0) -> 16 | F23: =VLOOKUP($C23,[1]Assortment!$F:$AM,31,0) -> 48 | G23: =VLOOKUP($C23,[1]Assortment!$F:$AM,14,0) -> 222.4 | H23: =G23/E23 -> 13.9 | I23: 1 | J23: 1.7765723 | K23: =J23*1.13 -> 2.0075267 | L23: 2.0075267 | M23: =L23*1.03 -> 2.0677525 | N23: =J23*1.13 -> 2.0075267 | O23: =N23*1.03 -> 2.0677525 | P23: =N23/1.13 -> 1.7765723 | Q23: =P23-J23 -> 0 | R23: =O23 -> 2.0677525 | V23: =G23*I23 -> 222.4 | W23: =R23*F23*I23/1.13 -> 87.833733 | X23: ='25年版cogs'!F24 -> 0.22149679 | Y23: ='25年版cogs'!G24 -> 0.025475023 | Z23: =W23-V23*(X23+Y23) -> 32.907201 | AA23: =Z23/W23 -> 0.37465333 | AC23: =P23*F23*I23 -> 85.275469 | AD23: =AC23-V23*(X23+Y23) -> 30.348937 | AE23: =AD23/AC23 -> 0.35589294 | AF23: 0.0017386837 | AG23: 0.006 | AK23: 0.071 | AL23: =AK23*G23 -> 15.7904
B24: T1级 | C24: 2152-04 | D24: =VLOOKUP($C24,[1]Assortment!$F:$BA,5,0) -> 215204舒洁鎏金系列乳霜纸巾40抽8包 | E24: =VLOOKUP($C24,[1]Assortment!$F:$AM,7,0) -> 4 | F24: =VLOOKUP($C24,[1]Assortment!$F:$AM,31,0) -> 32 | G24: =VLOOKUP($C24,[1]Assortment!$F:$AM,14,0) -> 105.788 | H24: =G24/E24 -> 26.447 | I24: 1 | J24: 1.3851652 | K24: =J24*1.13 -> 1.5652367 | L24: 1.5652367 | M24: =L24*1.03 -> 1.6121938 | N24: =J24*1.13 -> 1.5652367 | O24: =N24*1.03 -> 1.6121938 | P24: =N24/1.13 -> 1.3851652 | Q24: =P24-J24 -> 0 | R24: =O24 -> 1.6121938 | V24: =G24*I24 -> 105.788 | W24: =R24*F24*I24/1.13 -> 45.655045 | X24: ='25年版cogs'!F25 -> 0.25536403 | Y24: ='25年版cogs'!G25 -> 0.02536136 | Z24: =W24-V24*(X24+Y24) -> 15.957668 | AA24: =Z24/W24 -> 0.34952693 | AC24: =P24*F24*I24 -> 44.325286 | AD24: =AC24-V24*(X24+Y24) -> 14.627909 | AE24: =AD24/AC24 -> 0.33001274 | AF24: 0.0022587736 | AG24: 0.0022587736 | AK24: 0.225 | AL24: =AK24*G24 -> 23.8023
B25: T1级 | C25: 2107-61 | D25: =VLOOKUP($C25,[1]Assortment!$F:$BA,5,0) -> 210761舒洁卡通系列抽纸200抽3包 FSC mix70% | E25: =VLOOKUP($C25,[1]Assortment!$F:$AM,7,0) -> 20 | F25: =VLOOKUP($C25,[1]Assortment!$F:$AM,31,0) -> 60 | G25: =VLOOKUP($C25,[1]Assortment!$F:$AM,14,0) -> 338.18199 | H25: =G25/E25 -> 16.909099 | I25: 1 | J25: 3.7503136 | K25: =J25*1.13 -> 4.2378544 | L25: 4.24 | M25: =L25*1.03 -> 4.3672 | N25: 4.24 | O25: =N25*1.03 -> 4.3672 | P25: =N25/1.13 -> 3.7522124 | Q25: =P25-J25 -> 0.0018988042 | R25: =O25 -> 4.3672 | V25: =G25*I25 -> 338.18199 | W25: =R25*F25*I25/1.13 -> 231.88673 | X25: ='25年版cogs'!F26 -> 0.42805769 | Y25: ='25年版cogs'!G26 -> 0.025434118 | Z25: =W25-V25*(X25+Y25) -> 78.523964 | AA25: =Z25/W25 -> 0.3386307 | AC25: =P25*F25*I25 -> 225.13274 | AD25: =AC25-V25*(X25+Y25) -> 71.769981 | AE25: =AD25/AC25 -> 0.31878962 | AF25: 0.13403529 | AG25: 0.12 | AK25: 4.82 | AL25: =AK25*G25 -> 1630.0372
B26: T1级 | C26: 2103-90 | D26: =VLOOKUP($C26,[1]Assortment!$F:$BA,5,0) -> 210390舒洁小熊印花抽纸3层80抽4包FSC mix70% | E26: =VLOOKUP($C26,[1]Assortment!$F:$AM,7,0) -> 24 | F26: =VLOOKUP($C26,[1]Assortment!$F:$AM,31,0) -> 96 | G26: =VLOOKUP($C26,[1]Assortment!$F:$AM,14,0) -> 287.22305 | H26: =G26/E26 -> 11.967627 | I26: 1 | J26: 2.0583194 | K26: =J26*1.13 -> 2.3259009 | L26: 2.16 | M26: =L26*1.03 -> 2.2248 | N26: 2.16 | O26: =N26*1.03 -> 2.2248 | P26: =N26/1.13 -> 1.9115044 | Q26: =P26-J26 -> -0.14681493 | R26: 2.22 | V26: =G26*I26 -> 287.22305 | W26: =R26*F26*I26/1.13 -> 188.60177 | X26: ='25年版cogs'!F27 -> 0.4634207 | Y26: ='25年版cogs'!G27 -> 0.025450892 | Z26: =W26-V26*(X26+Y26) -> 48.186581 | AA26: =Z26/W26 -> 0.25549379 | AC26: =P26*F26*I26 -> 183.50442 | AD26: =AC26-V26*(X26+Y26) -> 43.089236 | AE26: =AD26/AC26 -> 0.23481306 | AF26: 0.1268699 | AG26: 0.11 | AK26: 5.275 | AL26: =AK26*G26 -> 1515.1016
B27: T1级 | C27: 2701-90 | D27: =VLOOKUP($C27,[1]Assortment!$F:$BA,5,0) -> 270190舒洁小熊印花手帕纸3层10包FSC mix70% | E27: =VLOOKUP($C27,[1]Assortment!$F:$AM,7,0) -> 36 | F27: =VLOOKUP($C27,[1]Assortment!$F:$AM,31,0) -> 360 | G27: =VLOOKUP($C27,[1]Assortment!$F:$AM,14,0) -> 208.46834 | H27: =G27/E27 -> 5.7907872 | I27: 1 | J27: 0.41625596 | K27: =J27*1.13 -> 0.47036923 | N27: =J27*1.13 -> 0.47036923 | P27: =O27/1.13 -> 0 | R27: 0.41625596 | V27: =G27*I27 -> 208.46834 | W27: =R27*F27*I27/1.13 -> 132.61252 | X27: =VLOOKUP(C27,'[3]Cost YTD'!$A:$L,12,0) -> 0.4324784 | Y27: 0.027 | Z27: =W27-V27*(X27+Y27) -> 36.825818 | AA27: =Z27/W27 -> 0.27769489 | AC27: =P27*F27*I27 -> 0 | AD27: =AC27-V27*(X27+Y27) -> -95.786699 | AE27: =AD27/AC27 -> #DIV/0! | AL27: =AK27*G27 -> 0
B28: T1级 | C28: 2694-40 | D28: =VLOOKUP($C28,[1]Assortment!$F:$BA,5,0) -> 269440舒洁湿厕纸家庭装40抽10包装 | E28: =VLOOKUP($C28,[1]Assortment!$F:$AM,7,0) -> 4 | F28: =VLOOKUP($C28,[1]Assortment!$F:$AM,31,0) -> 40 | G28: =VLOOKUP($C28,[1]Assortment!$F:$AM,14,0) -> 330.25 | H28: =G28/E28 -> 82.5625 | I28: 1 | J28: 3.0354981 | K28: =J28*1.13 -> 3.4301128 | N28: =J28*1.13 -> 3.4301128 | P28: =O28/1.13 -> 0 | R28: 3.8500222 | V28: =G28*I28 -> 330.25 | W28: =R28*F28*I28/1.13 -> 136.28397 | X28: =VLOOKUP(C28,'[3]Cost YTD'!$A:$L,12,0) -> 0.26998221 | Y28: 0.027 | Z28: =W28-V28*(X28+Y28) -> 38.205598 | AA28: =Z28/W28 -> 0.28033816 | AC28: =P28*F28*I28 -> 0 | AD28: =AC28-V28*(X28+Y28) -> -98.078375 | AE28: =AD28/AC28 -> #DIV/0! | AL28: =AK28*G28 -> 0
B29: T1级 | C29: 2694-30 | D29: =VLOOKUP($C29,[1]Assortment!$F:$BA,5,0) -> 269430舒洁湿厕纸家庭装40抽 | E29: =VLOOKUP($C29,[1]Assortment!$F:$AM,7,0) -> 40 | F29: =VLOOKUP($C29,[1]Assortment!$F:$AM,31,0) -> 40 | G29: =VLOOKUP($C29,[1]Assortment!$F:$AM,14,0) -> 367.52 | H29: =G29/E29 -> 9.188 | I29: 1 | J29: 3.8500222 | K29: =J29*1.13 -> 4.3505251 | N29: =J29*1.13 -> 4.3505251 | P29: =O29/1.13 -> 0 | R29: 3.8500222 | V29: =G29*I29 -> 367.52 | W29: =R29*F29*I29/1.13 -> 136.28397 | X29: =VLOOKUP(C29,'[3]Cost YTD'!$A:$L,12,0) -> 0.23244983 | Y29: 0.027 | Z29: =W29-V29*(X29+Y29) -> 40.930971 | AA29: =Z29/W29 -> 0.30033591 | AC29: =P29*F29*I29 -> 0 | AD29: =AC29-V29*(X29+Y29) -> -95.353002 | AE29: =AD29/AC29 -> #DIV/0! | AL29: =AK29*G29 -> 0
B30: T1级 | C30: 2682-20 | D30: =VLOOKUP($C30,[1]Assortment!$F:$BA,5,0) -> 268220舒洁女性湿厕纸10包装 | E30: =VLOOKUP($C30,[1]Assortment!$F:$AM,7,0) -> 4 | F30: =VLOOKUP($C30,[1]Assortment!$F:$AM,31,0) -> 40 | G30: =VLOOKUP($C30,[1]Assortment!$F:$AM,14,0) -> 255.40531 | H30: =G30/E30 -> 63.851327 | I30: 1 | J30: 2.4659681 | K30: =J30*1.13 -> 2.786544 | N30: =J30*1.13 -> 2.786544 | P30: =O30/1.13 -> 0 | R30: 2.4659681 | V30: =G30*I30 -> 255.40531 | W30: =R30*F30*I30/1.13 -> 87.290908 | X30: =VLOOKUP(C30,'[3]Cost YTD'!$A:$L,12,0) -> 0.23419798 | Y30: 0.027 | Z30: =W30-V30*(X30+Y30) -> 20.579558 | AA30: =Z30/W30 -> 0.23575832 | AC30: =P30*F30*I30 -> 0 | AD30: =AC30-V30*(X30+Y30) -> -66.71135 | AE30: =AD30/AC30 -> #DIV/0! | AL30: =AK30*G30 -> 0
B31: T1级 | C31: 2674-00 | D31: =VLOOKUP($C31,[1]Assortment!$F:$BA,5,0) -> 267400舒洁山茶花系列湿厕纸60片x4包 | E31: =VLOOKUP($C31,[1]Assortment!$F:$AM,7,0) -> 1 | F31: =VLOOKUP($C31,[1]Assortment!$F:$AM,31,0) -> 4 | G31: =VLOOKUP($C31,[1]Assortment!$F:$AM,14,0) -> 41.9 | H31: =G31/E31 -> 41.9 | I31: 1 | J31: 5.384865 | K31: =J31*1.13 -> 6.0848975 | N31: =J31*1.13 -> 6.0848975 | P31: =O31/1.13 -> 0 | R31: 5.384865 | V31: =G31*I31 -> 41.9 | W31: =R31*F31*I31/1.13 -> 19.061469 | X31: =VLOOKUP(C31,'[3]Cost YTD'!$A:$L,12,0) -> 0.36133013 | Y31: 0.027 | Z31: =W31-V31*(X31+Y31) -> 2.7904369 | AA31: =Z31/W31 -> 0.14639149 | AC31: =P31*F31*I31 -> 0 | AD31: =AC31-V31*(X31+Y31) -> -16.271032 | AE31: =AD31/AC31 -> #DIV/0! | AL31: =AK31*G31 -> 0
B32: T1级 | C32: 2673-00 | D32: =VLOOKUP($C32,[1]Assortment!$F:$BA,5,0) -> 267300舒洁山茶花系列湿厕纸60片 | E32: =VLOOKUP($C32,[1]Assortment!$F:$AM,7,0) -> 24 | F32: =VLOOKUP($C32,[1]Assortment!$F:$AM,31,0) -> 24 | G32: =VLOOKUP($C32,[1]Assortment!$F:$AM,14,0) -> 244.8 | H32: =G32/E32 -> 10.2 | I32: 1 | J32: 5.7647965 | K32: =J32*1.13 -> 6.51422 | N32: =J32*1.13 -> 6.51422 | P32: =O32/1.13 -> 0 | R32: 5.7647965 | V32: =G32*I32 -> 244.8 | W32: =R32*F32*I32/1.13 -> 122.43815 | X32: =VLOOKUP(C32,'[3]Cost YTD'!$A:$L,12,0) -> 0.36023809 | Y32: 0.027 | Z32: =W32-V32*(X32+Y32) -> 27.642269 | AA32: =Z32/W32 -> 0.22576516 | AC32: =P32*F32*I32 -> 0 | AD32: =AC32-V32*(X32+Y32) -> -94.795886 | AE32: =AD32/AC32 -> #DIV/0! | AL32: =AK32*G32 -> 0
B33: T1级 | C33: 2670-30 | D33: =VLOOKUP($C33,[1]Assortment!$F:$BA,5,0) -> 267030舒洁湿厕纸旅行装10包装 | E33: =VLOOKUP($C33,[1]Assortment!$F:$AM,7,0) -> 4 | F33: =VLOOKUP($C33,[1]Assortment!$F:$AM,31,0) -> 40 | G33: =VLOOKUP($C33,[1]Assortment!$F:$AM,14,0) -> 151.33 | H33: =G33/E33 -> 37.8325 | I33: 1 | J33: 1.0634917 | K33: =J33*1.13 -> 1.2017456 | N33: =J33*1.13 -> 1.2017456 | P33: =O33/1.13 -> 0 | R33: 1.0634917 | V33: =G33*I33 -> 151.33 | W33: =R33*F33*I33/1.13 -> 37.645725 | X33: =VLOOKUP(C33,'[3]Cost YTD'!$A:$L,12,0) -> 0.19361901 | Y33: 0.027 | Z33: =W33-V33*(X33+Y33) -> 4.2594497 | AA33: =Z33/W33 -> 0.11314564 | AC33: =P33*F33*I33 -> 0 | AD33: =AC33-V33*(X33+Y33) -> -33.386275 | AE33: =AD33/AC33 -> #DIV/0! | AL33: =AK33*G33 -> 0
B34: T1级 | C34: 2666-00 | D34: =VLOOKUP($C34,[1]Assortment!$F:$BA,5,0) -> 266600舒洁湿厕纸100片x6包-植物双萃 | E34: =VLOOKUP($C34,[1]Assortment!$F:$AM,7,0) -> 1 | F34: =VLOOKUP($C34,[1]Assortment!$F:$AM,31,0) -> 6 | G34: =VLOOKUP($C34,[1]Assortment!$F:$AM,14,0) -> 86.8 | H34: =G34/E34 -> 86.8 | I34: 1 | J34: 7.2990383 | K34: =J34*1.13 -> 8.2479133 | N34: =J34*1.13 -> 8.2479133 | P34: =O34/1.13 -> 0 | R34: 7.2990383 | V34: =G34*I34 -> 86.8 | W34: =R34*F34*I34/1.13 -> 38.755956 | X34: =VLOOKUP(C34,'[3]Cost YTD'!$A:$L,12,0) -> 0.32475113 | Y34: 0.027 | Z34: =W34-V34*(X34+Y34) -> 8.2239582 | AA34: =Z34/W34 -> 0.21219856 | AC34: =P34*F34*I34 -> 0 | AD34: =AC34-V34*(X34+Y34) -> -30.531998 | AE34: =AD34/AC34 -> #DIV/0! | AL34: =AK34*G34 -> 0
B35: T1级 | C35: 2662-00 | D35: =VLOOKUP($C35,[1]Assortment!$F:$BA,5,0) -> 266200舒洁湿厕纸80片x6包 | E35: =VLOOKUP($C35,[1]Assortment!$F:$AM,7,0) -> 1 | F35: =VLOOKUP($C35,[1]Assortment!$F:$AM,31,0) -> 6 | G35: =VLOOKUP($C35,[1]Assortment!$F:$AM,14,0) -> 69.44 | H35: =G35/E35 -> 69.44 | I35: 1 | J35: 5.3209416 | K35: =J35*1.13 -> 6.012664 | N35: =J35*1.13 -> 6.012664 | P35: =O35/1.13 -> 0 | R35: 6.4260593 | V35: =G35*I35 -> 69.44 | W35: =R35*F35*I35/1.13 -> 34.120669 | X35: =VLOOKUP(C35,'[3]Cost YTD'!$A:$L,12,0) -> 0.32389512 | Y35: 0.027 | Z35: =W35-V35*(X35+Y35) -> 9.7545114 | AA35: =Z35/W35 -> 0.28588277 | AC35: =P35*F35*I35 -> 0 | AD35: =AC35-V35*(X35+Y35) -> -24.366157 | AE35: =AD35/AC35 -> #DIV/0! | AL35: =AK35*G35 -> 0
B36: T1级 | C36: 2661-00 | D36: =VLOOKUP($C36,[1]Assortment!$F:$BA,5,0) -> 266100舒洁湿厕纸80片x3包 | E36: =VLOOKUP($C36,[1]Assortment!$F:$AM,7,0) -> 8 | F36: =VLOOKUP($C36,[1]Assortment!$F:$AM,31,0) -> 24 | G36: =VLOOKUP($C36,[1]Assortment!$F:$AM,14,0) -> 310.48 | H36: =G36/E36 -> 38.81 | I36: 1 | J36: 6.4260593 | K36: =J36*1.13 -> 7.261447 | N36: =J36*1.13 -> 7.261447 | P36: =O36/1.13 -> 0 | R36: 6.4260593 | V36: =G36*I36 -> 310.48 | W36: =R36*F36*I36/1.13 -> 136.48268 | X36: =VLOOKUP(C36,'[3]Cost YTD'!$A:$L,12,0) -> 0.29821889 | Y36: 0.027 | Z36: =W36-V36*(X36+Y36) -> 35.508714 | AA36: =Z36/W36 -> 0.26017012 | AC36: =P36*F36*I36 -> 0 | AD36: =AC36-V36*(X36+Y36) -> -100.97396 | AE36: =AD36/AC36 -> #DIV/0! | AL36: =AK36*G36 -> 0
B37: T1级 | C37: 2660-20 | D37: =VLOOKUP($C37,[1]Assortment!$F:$BA,5,0) -> #N/A | E37: =VLOOKUP($C37,[1]Assortment!$F:$AM,7,0) -> #N/A | F37: =VLOOKUP($C37,[1]Assortment!$F:$AM,31,0) -> #N/A | G37: =VLOOKUP($C37,[1]Assortment!$F:$AM,14,0) -> #N/A | H37: =G37/E37 -> #N/A | I37: 1 | J37: 5.7860903 | K37: =J37*1.13 -> 6.538282 | N37: =J37*1.13 -> 6.538282 | P37: =O37/1.13 -> 0 | R37: 5.7860903 | V37: =G37*I37 -> #N/A | W37: =R37*F37*I37/1.13 -> #N/A | X37: =VLOOKUP(C37,'[3]Cost YTD'!$A:$L,12,0) -> #N/A | Y37: 0.027 | Z37: =W37-V37*(X37+Y37) -> #N/A | AA37: =Z37/W37 -> #N/A | AC37: =P37*F37*I37 -> #N/A | AD37: =AC37-V37*(X37+Y37) -> #N/A | AE37: =AD37/AC37 -> #N/A | AL37: =AK37*G37 -> #N/A
B38: T1级 | C38: 2655-00 | D38: =VLOOKUP($C38,[1]Assortment!$F:$BA,5,0) -> 265500舒洁湿厕纸7抽6包装 | E38: =VLOOKUP($C38,[1]Assortment!$F:$AM,7,0) -> 16 | F38: =VLOOKUP($C38,[1]Assortment!$F:$AM,31,0) -> 96 | G38: =VLOOKUP($C38,[1]Assortment!$F:$AM,14,0) -> 179.2 | H38: =G38/E38 -> 11.2 | I38: 1 | J38: 1.0590442 | K38: =J38*1.13 -> 1.19672 | N38: =J38*1.13 -> 1.19672 | P38: =O38/1.13 -> 0 | R38: 1.0590442 | V38: =G38*I38 -> 179.2 | W38: =R38*F38*I38/1.13 -> 89.971901 | X38: =VLOOKUP(C38,'[3]Cost YTD'!$A:$L,12,0) -> 0.26631674 | Y38: 0.027 | Z38: =W38-V38*(X38+Y38) -> 37.409541 | AA38: =Z38/W38 -> 0.41579138 | AC38: =P38*F38*I38 -> 0 | AD38: =AC38-V38*(X38+Y38) -> -52.56236 | AE38: =AD38/AC38 -> #DIV/0! | AL38: =AK38*G38 -> 0
... B92: T1级 | C92: 2660-21 | D92: =VLOOKUP($C92,[1]Assortment!$F:$BA,5,0) -> #N/A | E92: =VLOOKUP($C92,[1]Assortment!$F:$AM,7,0) -> #N/A | F92: =VLOOKUP($C92,[1]Assortment!$F:$AM,31,0) -> #N/A | G92: =VLOOKUP($C92,[1]Assortment!$F:$AM,14,0) -> #N/A | H92: =G92/E92 -> #N/A | I92: 1 | J92: 5.719764 | K92: =J92*1.13 -> 6.4633333 | N92: =J92*1.13 -> 6.4633333 | P92: =O92/1.13 -> 0 | R92: 5.719764 | V92: =G92*I92 -> #N/A | W92: =R92*F92*I92/1.13 -> #N/A | X92: =VLOOKUP(C92,'[3]Cost YTD'!$A:$L,12,0) -> #N/A | Y92: 0.027 | Z92: =W92-V92*(X92+Y92) -> #N/A | AA92: =Z92/W92 -> #N/A | AC92: =P92*F92*I92 -> #N/A | AD92: =AC92-V92*(X92+Y92) -> #N/A | AE92: =AD92/AC92 -> #N/A | AL92: =AK92*G92 -> #N/A
B93: 关于26年年度FMC销售生意的计划以及价格沟通 一.背景: GT南边的客户以团购福利生意为主，团购生意占比大，今年通过团购的生意同比增长在50%以上，由于25年的价格体系没有参考团购价格的逻辑，每次订单产生之后都要case by case 进行价格审批，对中台和销售单元的工作都增加了一定的工作难度，因此为了做好26年的团购生意，在此申请一套26年的T1级别客户的价格体系，这套价格体系符合团购生意的价值链逻辑。 目前申请的价格是参考了中台部分给到的26年的价格指引，大部分产品按照中台部门提供的价格参考执行，其中标红部分的sku（该6支产品也是26年会重点在渠道中推品的）价格跟指引有差异并需要单独申请,申请T1价格经销商合计数量8个，客户清单如下： 1.上海文薪 2.天宁雕庄 3.云南普泉 4.上海芳薇 5.团氿南京 6.南京新语 7.宁波宝敏瑞 8.上海怡乐畅购 二.申请T1价格要求 1,年度团购生意需大于100w并签订全年销售指标 2.对团购生意项目信息需要与销售同步并建立项目档案 三.团购生意目标计划 目前沟通的团购客户部分客户已经完成初步26年生意目标沟通，以下罗列几个重点大客户目标 1.上海文薪年度目标：700w 2.天宁雕庄年度目标 ：200w 3.云南普泉年度目标：100w 其他客户由于时间关系暂时未沟通完毕，都是区域部分重点的潜力客户，所以同步申请该T1级别的客户，预计能合计贡献100w-200w的生意 全年预计T1级客户生意总1000-1200w 四.达成年度销售目标的举措 1.针对签约的经销商设立年度销售指标，按照季度销售目标达成激励2%的返利，年度目标达成给与1%返利（按照GT拟定的返利政策执行） 2.申请T1价格的经销商目标拆解到月，次月按照目标对上个月的目标进行回顾复盘 3.产品计划方面：重点推GP数字高的牛乳系列产品提升占比 4.重点平台：史泰博、得力、齐心等联合经销商做全年的生意计划，空白平台完成平台商城产品库上架工作 5.重点大客户项目：移动女工福利项目26年跟经销商做好老品的留存和新sku的推品上架工作 五.整体生意利润的测算 1.top5重点sku占比：2694湿厕纸40抽20%，2662湿厕纸80抽12.7%，2312马蹄莲抽纸12.1%，2103小熊80抽*4抽纸11%，2216纯白卷纸8% 2.团购生意GP情况：参考25年的sku销售占比情况，整体gp%数字在26% ps：若后续还有一些新开发的大客户有意向签约年度销售合作目标后续参考这个价格执行并邮寄报审到中台 | AG93: =SUMPRODUCT(AA3:AA26,AG3:AG26) -> 0.24436387
W116: 经销商考核指标、返利政策
W117: 1. 考核指标：舒洁系列产品整体进货指标达成
W118: 2. 考核周期：季度+年度
W119: 3. 考核门槛：舒洁系列季度完成目标大于25万、年度100万
W120: 4. 计算公式与折算比例：按照如下办法计算
W121: 季度返利以及年度返利形式
W123: 进货目标完成比例 | X123: 折算比例 | Y123: 季度返利比例 | Z123: 年度返利比例
W125: ＞=100% | X125: 1 | Y125: 0.02 | Z125: 0.01
W126: 85%-100% | X126: 按照实际完成比例核销 | Y126: 0.02 | Z126: 0.01
W127: 85%以下 | X127: 不核销 | Y127: 0.02 | Z127: 0.01

Sheet 26年价格体系 T2
B1: 销售填写 | C1: 销售填写 | D1: 公式 | E1: 公式 | F1: 公式 | G1: 公式 | H1: 公式 | J1: 不填 | S1: 不填 | T1: 不填 | U1: 不填 | V1: 公式 | W1: 公式 | X1: 公式 | Y1: 公式 | Z1: 公式 | AA1: 公式 | AF1: EDLP | AG1: EDLP
B2: 客户 | C2: Product Code | D2: 产品名称 | E2: 箱规 | F2: 包/箱 | G2: PR00 (箱价)-未税 | H2: PR00/EA | I2: 进货箱数 | J2: 进货价格/包-含税 | K2: nsv提税 | L2: 1.13含税价格 | N2: 经销商打款价格 | O2: 客户打款价 | P2: nsv实际需要价格 | Q2: 实际需求与指引差 | R2: 活动价格/包-含税 | S2: 后补/包-含税 | T2: 后补金额-含税-TTL | U2: 后补金额未税-TTL | V2: GSV | W2: NSV | X2: DQF COGS % VS GSV | Y2: DQF DE % VS GSV | Z2: GP | AA2: GP% | AB2: GP%（我们Propose） | AC2: Biz.Weight-2025 | AD2: Biz.Weight-2026-Proposal-@ Shengtao | AF2: 含票扣3.4%箱价 /不含税 | AG2: 维护折扣金额-1000箱
B3: T1级 | C3: 2701-90 | D3: =VLOOKUP($C3,[1]Assortment!$F:$BA,5,0) -> 270190舒洁小熊印花手帕纸3层10包FSC mix70% | E3: =VLOOKUP($C3,[1]Assortment!$F:$AM,7,0) -> 36 | F3: =VLOOKUP($C3,[1]Assortment!$F:$AM,31,0) -> 360 | G3: =VLOOKUP($C3,[1]Assortment!$F:$AM,14,0) -> 208.46834 | H3: =G3/E3 -> 5.7907872 | I3: 1 | K3: 0.41625596 | L3: =K3*1.13 -> 0.47036923 | P3: =#REF!/1.13 -> #REF! | R3: 0.41625596 | V3: =G3*I3 -> 208.46834 | W3: =R3*F3*I3/1.13 -> 132.61252 | X3: =VLOOKUP(C3,'[3]Cost YTD'!$A:$L,12,0) -> 0.4324784 | Y3: 0.027 | Z3: =W3-V3*(X3+Y3) -> 36.825818 | AA3: =Z3/W3 -> 0.27769489
B4: T1级 | C4: 2694-40 | D4: =VLOOKUP($C4,[1]Assortment!$F:$BA,5,0) -> 269440舒洁湿厕纸家庭装40抽10包装 | E4: =VLOOKUP($C4,[1]Assortment!$F:$AM,7,0) -> 4 | F4: =VLOOKUP($C4,[1]Assortment!$F:$AM,31,0) -> 40 | G4: =VLOOKUP($C4,[1]Assortment!$F:$AM,14,0) -> 330.25 | H4: =G4/E4 -> 82.5625 | I4: 1 | K4: 3.0354981 | L4: =K4*1.13 -> 3.4301128 | P4: =#REF!/1.13 -> #REF! | R4: 3.8500222 | V4: =G4*I4 -> 330.25 | W4: =R4*F4*I4/1.13 -> 136.28397 | X4: =VLOOKUP(C4,'[3]Cost YTD'!$A:$L,12,0) -> 0.26998221 | Y4: 0.027 | Z4: =W4-V4*(X4+Y4) -> 38.205598 | AA4: =Z4/W4 -> 0.28033816
B5: T1级 | C5: 2694-30 | D5: =VLOOKUP($C5,[1]Assortment!$F:$BA,5,0) -> 269430舒洁湿厕纸家庭装40抽 | E5: =VLOOKUP($C5,[1]Assortment!$F:$AM,7,0) -> 40 | F5: =VLOOKUP($C5,[1]Assortment!$F:$AM,31,0) -> 40 | G5: =VLOOKUP($C5,[1]Assortment!$F:$AM,14,0) -> 367.52 | H5: =G5/E5 -> 9.188 | I5: 1 | K5: 3.8500222 | L5: =K5*1.13 -> 4.3505251 | P5: =#REF!/1.13 -> #REF! | R5: 3.8500222 | V5: =G5*I5 -> 367.52 | W5: =R5*F5*I5/1.13 -> 136.28397 | X5: =VLOOKUP(C5,'[3]Cost YTD'!$A:$L,12,0) -> 0.23244983 | Y5: 0.027 | Z5: =W5-V5*(X5+Y5) -> 40.930971 | AA5: =Z5/W5 -> 0.30033591
B6: T1级 | C6: 2682-20 | D6: =VLOOKUP($C6,[1]Assortment!$F:$BA,5,0) -> 268220舒洁女性湿厕纸10包装 | E6: =VLOOKUP($C6,[1]Assortment!$F:$AM,7,0) -> 4 | F6: =VLOOKUP($C6,[1]Assortment!$F:$AM,31,0) -> 40 | G6: =VLOOKUP($C6,[1]Assortment!$F:$AM,14,0) -> 255.40531 | H6: =G6/E6 -> 63.851327 | I6: 1 | K6: 2.4659681 | L6: =K6*1.13 -> 2.786544 | P6: =#REF!/1.13 -> #REF! | R6: 2.4659681 | V6: =G6*I6 -> 255.40531 | W6: =R6*F6*I6/1.13 -> 87.290908 | X6: =VLOOKUP(C6,'[3]Cost YTD'!$A:$L,12,0) -> 0.23419798 | Y6: 0.027 | Z6: =W6-V6*(X6+Y6) -> 20.579558 | AA6: =Z6/W6 -> 0.23575832
B7: T1级 | C7: 2674-00 | D7: =VLOOKUP($C7,[1]Assortment!$F:$BA,5,0) -> 267400舒洁山茶花系列湿厕纸60片x4包 | E7: =VLOOKUP($C7,[1]Assortment!$F:$AM,7,0) -> 1 | F7: =VLOOKUP($C7,[1]Assortment!$F:$AM,31,0) -> 4 | G7: =VLOOKUP($C7,[1]Assortment!$F:$AM,14,0) -> 41.9 | H7: =G7/E7 -> 41.9 | I7: 1 | K7: 5.384865 | L7: =K7*1.13 -> 6.0848975 | P7: =#REF!/1.13 -> #REF! | R7: 5.384865 | V7: =G7*I7 -> 41.9 | W7: =R7*F7*I7/1.13 -> 19.061469 | X7: =VLOOKUP(C7,'[3]Cost YTD'!$A:$L,12,0) -> 0.36133013 | Y7: 0.027 | Z7: =W7-V7*(X7+Y7) -> 2.7904369 | AA7: =Z7/W7 -> 0.14639149
B8: T1级 | C8: 2673-00 | D8: =VLOOKUP($C8,[1]Assortment!$F:$BA,5,0) -> 267300舒洁山茶花系列湿厕纸60片 | E8: =VLOOKUP($C8,[1]Assortment!$F:$AM,7,0) -> 24 | F8: =VLOOKUP($C8,[1]Assortment!$F:$AM,31,0) -> 24 | G8: =VLOOKUP($C8,[1]Assortment!$F:$AM,14,0) -> 244.8 | H8: =G8/E8 -> 10.2 | I8: 1 | K8: 5.7647965 | L8: =K8*1.13 -> 6.51422 | P8: =#REF!/1.13 -> #REF! | R8: 5.7647965 | V8: =G8*I8 -> 244.8 | W8: =R8*F8*I8/1.13 -> 122.43815 | X8: =VLOOKUP(C8,'[3]Cost YTD'!$A:$L,12,0) -> 0.36023809 | Y8: 0.027 | Z8: =W8-V8*(X8+Y8) -> 27.642269 | AA8: =Z8/W8 -> 0.22576516
B9: T1级 | C9: 2670-30 | D9: =VLOOKUP($C9,[1]Assortment!$F:$BA,5,0) -> 267030舒洁湿厕纸旅行装10包装 | E9: =VLOOKUP($C9,[1]Assortment!$F:$AM,7,0) -> 4 | F9: =VLOOKUP($C9,[1]Assortment!$F:$AM,31,0) -> 40 | G9: =VLOOKUP($C9,[1]Assortment!$F:$AM,14,0) -> 151.33 | H9: =G9/E9 -> 37.8325 | I9: 1 | K9: 1.0634917 | L9: =K9*1.13 -> 1.2017456 | P9: =#REF!/1.13 -> #REF! | R9: 1.0634917 | V9: =G9*I9 -> 151.33 | W9: =R9*F9*I9/1.13 -> 37.645725 | X9: =VLOOKUP(C9,'[3]Cost YTD'!$A:$L,12,0) -> 0.19361901 | Y9: 0.027 | Z9: =W9-V9*(X9+Y9) -> 4.2594497 | AA9: =Z9/W9 -> 0.11314564
B10: T1级 | C10: 2666-00 | D10: =VLOOKUP($C10,[1]Assortment!$F:$BA,5,0) -> 266600舒洁湿厕纸100片x6包-植物双萃 | E10: =VLOOKUP($C10,[1]Assortment!$F:$AM,7,0) -> 1 | F10: =VLOOKUP($C10,[1]Assortment!$F:$AM,31,0) -> 6 | G10: =VLOOKUP($C10,[1]Assortment!$F:$AM,14,0) -> 86.8 | H10: =G10/E10 -> 86.8 | I10: 1 | K10: 7.2990383 | L10: =K10*1.13 -> 8.2479133 | P10: =#REF!/1.13 -> #REF! | R10: 7.2990383 | V10: =G10*I10 -> 86.8 | W10: =R10*F10*I10/1.13 -> 38.755956 | X10: =VLOOKUP(C10,'[3]Cost YTD'!$A:$L,12,0) -> 0.32475113 | Y10: 0.027 | Z10: =W10-V10*(X10+Y10) -> 8.2239582 | AA10: =Z10/W10 -> 0.21219856
B11: T1级 | C11: 2662-00 | D11: =VLOOKUP($C11,[1]Assortment!$F:$BA,5,0) -> 266200舒洁湿厕纸80片x6包 | E11: =VLOOKUP($C11,[1]Assortment!$F:$AM,7,0) -> 1 | F11: =VLOOKUP($C11,[1]Assortment!$F:$AM,31,0) -> 6 | G11: =VLOOKUP($C11,[1]Assortment!$F:$AM,14,0) -> 69.44 | H11: =G11/E11 -> 69.44 | I11: 1 | K11: 5.3209416 | L11: =K11*1.13 -> 6.012664 | P11: =#REF!/1.13 -> #REF! | R11: 6.4260593 | V11: =G11*I11 -> 69.44 | W11: =R11*F11*I11/1.13 -> 34.120669 | X11: =VLOOKUP(C11,'[3]Cost YTD'!$A:$L,12,0) -> 0.32389512 | Y11: 0.027 | Z11: =W11-V11*(X11+Y11) -> 9.7545114 | AA11: =Z11/W11 -> 0.28588277
B12: T1级 | C12: 2661-00 | D12: =VLOOKUP($C12,[1]Assortment!$F:$BA,5,0) -> 266100舒洁湿厕纸80片x3包 | E12: =VLOOKUP($C12,[1]Assortment!$F:$AM,7,0) -> 8 | F12: =VLOOKUP($C12,[1]Assortment!$F:$AM,31,0) -> 24 | G12: =VLOOKUP($C12,[1]Assortment!$F:$AM,14,0) -> 310.48 | H12: =G12/E12 -> 38.81 | I12: 1 | K12: 6.4260593 | L12: =K12*1.13 -> 7.261447 | P12: =#REF!/1.13 -> #REF! | R12: 6.4260593 | V12: =G12*I12 -> 310.48 | W12: =R12*F12*I12/1.13 -> 136.48268 | X12: =VLOOKUP(C12,'[3]Cost YTD'!$A:$L,12,0) -> 0.29821889 | Y12: 0.027 | Z12: =W12-V12*(X12+Y12) -> 35.508714 | AA12: =Z12/W12 -> 0.26017012
B13: T1级 | C13: 2660-20 | D13: =VLOOKUP($C13,[1]Assortment!$F:$BA,5,0) -> #N/A | E13: =VLOOKUP($C13,[1]Assortment!$F:$AM,7,0) -> #N/A | F13: =VLOOKUP($C13,[1]Assortment!$F:$AM,31,0) -> #N/A | G13: =VLOOKUP($C13,[1]Assortment!$F:$AM,14,0) -> #N/A | H13: =G13/E13 -> #N/A | I13: 1 | K13: 5.7860903 | L13: =K13*1.13 -> 6.538282 | P13: =#REF!/1.13 -> #REF! | R13: 5.7860903 | V13: =G13*I13 -> #N/A | W13: =R13*F13*I13/1.13 -> #N/A | X13: =VLOOKUP(C13,'[3]Cost YTD'!$A:$L,12,0) -> #N/A | Y13: 0.027 | Z13: =W13-V13*(X13+Y13) -> #N/A | AA13: =Z13/W13 -> #N/A
B14: T1级 | C14: 2655-00 | D14: =VLOOKUP($C14,[1]Assortment!$F:$BA,5,0) -> 265500舒洁湿厕纸7抽6包装 | E14: =VLOOKUP($C14,[1]Assortment!$F:$AM,7,0) -> 16 | F14: =VLOOKUP($C14,[1]Assortment!$F:$AM,31,0) -> 96 | G14: =VLOOKUP($C14,[1]Assortment!$F:$AM,14,0) -> 179.2 | H14: =G14/E14 -> 11.2 | I14: 1 | K14: 1.0590442 | L14: =K14*1.13 -> 1.19672 | P14: =#REF!/1.13 -> #REF! | R14: 1.0590442 | V14: =G14*I14 -> 179.2 | W14: =R14*F14*I14/1.13 -> 89.971901 | X14: =VLOOKUP(C14,'[3]Cost YTD'!$A:$L,12,0) -> 0.26631674 | Y14: 0.027 | Z14: =W14-V14*(X14+Y14) -> 37.409541 | AA14: =Z14/W14 -> 0.41579138
... B68: T1级 | C68: 2660-21 | D68: =VLOOKUP($C68,[1]Assortment!$F:$BA,5,0) -> #N/A | E68: =VLOOKUP($C68,[1]Assortment!$F:$AM,7,0) -> #N/A | F68: =VLOOKUP($C68,[1]Assortment!$F:$AM,31,0) -> #N/A | G68: =VLOOKUP($C68,[1]Assortment!$F:$AM,14,0) -> #N/A | H68: =G68/E68 -> #N/A | I68: 1 | K68: 5.719764 | L68: =K68*1.13 -> 6.4633333 | P68: =#REF!/1.13 -> #REF! | R68: 5.719764 | V68: =G68*I68 -> #N/A | W68: =R68*F68*I68/1.13 -> #N/A | X68: =VLOOKUP(C68,'[3]Cost YTD'!$A:$L,12,0) -> #N/A | Y68: 0.027 | Z68: =W68-V68*(X68+Y68) -> #N/A | AA68: =Z68/W68 -> #N/A
A69: 例+116:116994+110:110:118 | B69: T2级 | C69: 2701-90 | D69: =VLOOKUP($C69,[1]Assortment!$F:$BA,5,0) -> 270190舒洁小熊印花手帕纸3层10包FSC mix70% | E69: =VLOOKUP($C69,[1]Assortment!$F:$AM,7,0) -> 36 | F69: =VLOOKUP($C69,[1]Assortment!$F:$AM,31,0) -> 360 | G69: =VLOOKUP($C69,[1]Assortment!$F:$AM,14,0) -> 208.46834 | H69: =G69/E69 -> 5.7907872 | I69: 1 | K69: 0.41625596 | L69: =K69*1.13 -> 0.47036923 | M69: =L69*1.12 -> 0.52681354 | N69: 0.474 | P69: =N69/1.13 -> 0.41946903 | Q69: =P69-K69 -> 0.0032130696 | R69: =N69 -> 0.474 | V69: =G69*I69 -> 208.46834 | W69: =R69*F69*I69/1.13 -> 151.00885 | X69: ='25年版cogs'!F4 -> 0.42397103 | Y69: ='25年版cogs'!G4 -> 0.025426167 | Z69: =W69-V69*(X69+Y69) -> 57.323762 | AA69: =Z69/W69 -> 0.37960531 | AB69: =Z69/W69 -> 0.37960531 | AC69: 0.027504779 | AD69: 0.027504779 | AF69: =R69*F69/0.966/1.13 -> 156.32386 | AG69: =(G69-AF69)*1000 -> 52144.479
B70: T2级 | C70: 2694-40 | D70: =VLOOKUP($C70,[1]Assortment!$F:$BA,5,0) -> 269440舒洁湿厕纸家庭装40抽10包装 | E70: =VLOOKUP($C70,[1]Assortment!$F:$AM,7,0) -> 4 | F70: =VLOOKUP($C70,[1]Assortment!$F:$AM,31,0) -> 40 | G70: =VLOOKUP($C70,[1]Assortment!$F:$AM,14,0) -> 330.25 | H70: =G70/E70 -> 82.5625 | I70: 1 | K70: 3.0354981 | L70: =K70*1.13 -> 3.4301128 | M70: =L70*1.12 -> 3.8417264 | N70: 4.1 | P70: =N70/1.13 -> 3.6283186 | Q70: =P70-K70 -> 0.59282051 | R70: =N70 -> 4.1 | V70: =G70*I70 -> 330.25 | W70: =R70*F70*I70/1.13 -> 145.13274 | X70: ='25年版cogs'!F5 -> 0.26981474 | Y70: ='25年版cogs'!G5 -> 0.025386209 | Z70: =W70-V70*(X70+Y70) -> 47.642631 | AA70: =Z70/W70 -> 0.32826935 | AB70: =Z70/W70 -> 0.32826935 | AC70: 0.052241538 | AD70: 0.06
B71: T2级 | C71: 2694-30 | D71: =VLOOKUP($C71,[1]Assortment!$F:$BA,5,0) -> 269430舒洁湿厕纸家庭装40抽 | E71: =VLOOKUP($C71,[1]Assortment!$F:$AM,7,0) -> 40 | F71: =VLOOKUP($C71,[1]Assortment!$F:$AM,31,0) -> 40 | G71: =VLOOKUP($C71,[1]Assortment!$F:$AM,14,0) -> 367.52 | H71: =G71/E71 -> 9.188 | I71: 1 | K71: 3.8500222 | L71: =K71*1.13 -> 4.3505251 | M71: =L71*1.12 -> 4.8725881 | N71: 4.1 | P71: =N71/1.13 -> 3.6283186 | Q71: =P71-K71 -> -0.22170366 | R71: =N71 -> 4.1 | V71: =G71*I71 -> 367.52 | W71: =R71*F71*I71/1.13 -> 145.13274 | X71: ='25年版cogs'!F6 -> 0.26981474 | Y71: ='25年版cogs'!G6 -> 0.025386209 | Z71: =W71-V71*(X71+Y71) -> 36.640492 | AA71: =Z71/W71 -> 0.25246193 | AB71: =Z71/W71 -> 0.25246193 | AC71: 0.14847537 | AD71: 0.141
B72: T2级 | C72: 2682-20 | D72: =VLOOKUP($C72,[1]Assortment!$F:$BA,5,0) -> 268220舒洁女性湿厕纸10包装 | E72: =VLOOKUP($C72,[1]Assortment!$F:$AM,7,0) -> 4 | F72: =VLOOKUP($C72,[1]Assortment!$F:$AM,31,0) -> 40 | G72: =VLOOKUP($C72,[1]Assortment!$F:$AM,14,0) -> 255.40531 | H72: =G72/E72 -> 63.851327 | I72: 1 | K72: 2.4659681 | L72: =K72*1.13 -> 2.786544 | M72: =L72*1.12 -> 3.1209293 | N72: =M72 -> 3.1209293 | P72: =N72/1.13 -> 2.7618843 | Q72: =P72-K72 -> 0.29591618 | R72: =N72 -> 3.1209293 | V72: =G72*I72 -> 255.40531 | W72: =R72*F72*I72/1.13 -> 110.47537 | X72: ='25年版cogs'!F7 -> 0.22151094 | Y72: ='25年版cogs'!G7 -> 0.025347831 | Z72: =W72-V72*(X72+Y72) -> 47.426332 | AA72: =Z72/W72 -> 0.42929325 | AB72: =Z72/W72 -> 0.42929325 | AC72: 0.0019531766 | AD72: 0.0019531766
B73: T2级 | C73: 2674-00 | D73: =VLOOKUP($C73,[1]Assortment!$F:$BA,5,0) -> 267400舒洁山茶花系列湿厕纸60片x4包 | E73: =VLOOKUP($C73,[1]Assortment!$F:$AM,7,0) -> 1 | F73: =VLOOKUP($C73,[1]Assortment!$F:$AM,31,0) -> 4 | G73: =VLOOKUP($C73,[1]Assortment!$F:$AM,14,0) -> 41.9 | H73: =G73/E73 -> 41.9 | I73: 1 | K73: 5.384865 | L73: =K73*1.13 -> 6.0848975 | M73: =L73*1.12 -> 6.8150852 | N73: =M73 -> 6.8150852 | P73: =N73/1.13 -> 6.0310488 | Q73: =P73-K73 -> 0.64618381 | R73: =N73 -> 6.8150852 | V73: =G73*I73 -> 41.9 | W73: =R73*F73*I73/1.13 -> 24.124195 | X73: ='25年版cogs'!F8 -> 0.35939124 | Y73: ='25年版cogs'!G8 -> 0.02533352 | Z73: =W73-V73*(X73+Y73) -> 8.0042279 | AA73: =Z73/W73 -> 0.33179253 | AB73: =Z73/W73 -> 0.33179253 | AC73: 0.00051970605 | AD73: 0.00051970605
B74: T2级 | C74: 2673-00 | D74: =VLOOKUP($C74,[1]Assortment!$F:$BA,5,0) -> 267300舒洁山茶花系列湿厕纸60片 | E74: =VLOOKUP($C74,[1]Assortment!$F:$AM,7,0) -> 24 | F74: =VLOOKUP($C74,[1]Assortment!$F:$AM,31,0) -> 24 | G74: =VLOOKUP($C74,[1]Assortment!$F:$AM,14,0) -> 244.8 | H74: =G74/E74 -> 10.2 | I74: 1 | K74: 5.7647965 | L74: =K74*1.13 -> 6.51422 | M74: =L74*1.12 -> 7.2959264 | N74: =M74 -> 7.2959264 | P74: =N74/1.13 -> 6.456572 | Q74: =P74-K74 -> 0.69177558 | R74: =N74 -> 7.2959264 | V74: =G74*I74 -> 244.8 | W74: =R74*F74*I74/1.13 -> 154.95773 | X74: ='25年版cogs'!F9 -> 0.35822651 | Y74: ='25年版cogs'!G9 -> 0.025367759 | Z74: =W74-V74*(X74+Y74) -> 61.053851 | AA74: =Z74/W74 -> 0.39400326 | AB74: =Z74/W74 -> 0.39400326 | AC74: 0.0035206815 | AD74: 0.0035206815
B75: T2级 | C75: 2670-30 | D75: =VLOOKUP($C75,[1]Assortment!$F:$BA,5,0) -> 267030舒洁湿厕纸旅行装10包装 | E75: =VLOOKUP($C75,[1]Assortment!$F:$AM,7,0) -> 4 | F75: =VLOOKUP($C75,[1]Assortment!$F:$AM,31,0) -> 40 | G75: =VLOOKUP($C75,[1]Assortment!$F:$AM,14,0) -> 151.33 | H75: =G75/E75 -> 37.8325 | I75: 1 | K75: 1.0634917 | L75: =K75*1.13 -> 1.2017456 | M75: =L75*1.12 -> 1.3459551 | N75: =M75 -> 1.3459551 | P75: =N75/1.13 -> 1.1911107 | Q75: =P75-K75 -> 0.12761901 | R75: =N75 -> 1.3459551 | V75: =G75*I75 -> 151.33 | W75: =R75*F75*I75/1.13 -> 47.644429 | X75: ='25年版cogs'!F10 -> 0.18260265 | Y75: ='25年版cogs'!G10 -> 0.025370117 | Z75: =W75-V75*(X75+Y75) -> 16.17191 | AA75: =Z75/W75 -> 0.33942919 | AB75: =Z75/W75 -> 0.33942919 | AC75: 0.00056438213 | AD75: 0.00056438213
B76: T2级 | C76: 2666-00 | D76: =VLOOKUP($C76,[1]Assortment!$F:$BA,5,0) -> 266600舒洁湿厕纸100片x6包-植物双萃 | E76: =VLOOKUP($C76,[1]Assortment!$F:$AM,7,0) -> 1 | F76: =VLOOKUP($C76,[1]Assortment!$F:$AM,31,0) -> 6 | G76: =VLOOKUP($C76,[1]Assortment!$F:$AM,14,0) -> 86.8 | H76: =G76/E76 -> 86.8 | I76: 1 | K76: 7.2990383 | L76: =K76*1.13 -> 8.2479133 | M76: =L76*1.12 -> 9.2376629 | N76: =M76 -> 9.2376629 | P76: =N76/1.13 -> 8.1749229 | Q76: =P76-K76 -> 0.8758846 | R76: =N76 -> 9.2376629 | V76: =G76*I76 -> 86.8 | W76: =R76*F76*I76/1.13 -> 49.049538 | X76: ='25年版cogs'!F11 -> 0.32309188 | Y76: ='25年版cogs'!G11 -> 0.02533601 | Z76: =W76-V76*(X76+Y76) -> 18.805997 | AA76: =Z76/W76 -> 0.38340824 | AB76: =Z76/W76 -> 0.38340824 | AC76: 0.00091353072 | AD76: 0.00091353072
A77: 5.9 | B77: T2级 | C77: 2662-00 | D77: =VLOOKUP($C77,[1]Assortment!$F:$BA,5,0) -> 266200舒洁湿厕纸80片x6包 | E77: =VLOOKUP($C77,[1]Assortment!$F:$AM,7,0) -> 1 | F77: =VLOOKUP($C77,[1]Assortment!$F:$AM,31,0) -> 6 | G77: =VLOOKUP($C77,[1]Assortment!$F:$AM,14,0) -> 69.44 | H77: =G77/E77 -> 69.44 | I77: 1 | K77: 5.3209416 | L77: =K77*1.13 -> 6.012664 | M77: =L77*1.12 -> 6.7341837 | N77: =M77 -> 6.7341837 | P77: =N77/1.13 -> 5.9594546 | Q77: =P77-K77 -> 0.63851299 | R77: =N77 -> 6.7341837 | V77: =G77*I77 -> 69.44 | W77: =R77*F77*I77/1.13 -> 35.756728 | X77: ='25年版cogs'!F12 -> 0.34017628 | Y77: ='25年版cogs'!G12 -> 0.025238484 | Z77: =W77-V77*(X77+Y77) -> 10.382327 | AA77: =Z77/W77 -> 0.29036009 | AB77: =Z77/W77 -> 0.29036009 | AC77: 0.127216 | AD77: 0.156
B78: T2级 | C78: 2661-00 | D78: =VLOOKUP($C78,[1]Assortment!$F:$BA,5,0) -> 266100舒洁湿厕纸80片x3包 | E78: =VLOOKUP($C78,[1]Assortment!$F:$AM,7,0) -> 8 | F78: =VLOOKUP($C78,[1]Assortment!$F:$AM,31,0) -> 24 | G78: =VLOOKUP($C78,[1]Assortment!$F:$AM,14,0) -> 310.48 | H78: =G78/E78 -> 38.81 | I78: 1 | K78: 6.4260593 | L78: =K78*1.13 -> 7.261447 | M78: =L78*1.12 -> 8.1328206 | N78: =M78 -> 8.1328206 | P78: =N78/1.13 -> 7.1971864 | Q78: =P78-K78 -> 0.77112712 | R78: =N78 -> 8.1328206 | V78: =G78*I78 -> 310.48 | W78: =R78*F78*I78/1.13 -> 172.73247 | X78: ='25年版cogs'!F13 -> 0.30486433 | Y78: ='25年版cogs'!G13 -> 0.025424502 | Z78: =W78-V78*(X78+Y78) -> 70.184397 | AA78: =Z78/W78 -> 0.40631849 | AB78: =Z78/W78 -> 0.40631849 | AC78: 0.0045366619 | AD78: 0.0045366619
B79: T2级 | C79: 2655-00 | D79: =VLOOKUP($C79,[1]Assortment!$F:$BA,5,0) -> 265500舒洁湿厕纸7抽6包装 | E79: =VLOOKUP($C79,[1]Assortment!$F:$AM,7,0) -> 16 | F79: =VLOOKUP($C79,[1]Assortment!$F:$AM,31,0) -> 96 | G79: =VLOOKUP($C79,[1]Assortment!$F:$AM,14,0) -> 179.2 | H79: =G79/E79 -> 11.2 | I79: 1 | K79: 1.0590442 | L79: =K79*1.13 -> 1.19672 | M79: =L79*1.12 -> 1.3403264 | N79: =M79 -> 1.3403264 | P79: =N79/1.13 -> 1.1861296 | Q79: =P79-K79 -> 0.12708531 | R79: =N79 -> 1.3403264 | V79: =G79*I79 -> 179.2 | W79: =R79*F79*I79/1.13 -> 113.86844 | X79: ='25年版cogs'!F14 -> 0.27365302 | Y79: ='25年版cogs'!G14 -> 0.025424502 | Z79: =W79-V79*(X79+Y79) -> 60.273745 | AA79: =Z79/W79 -> 0.52932794 | AB79: =Z79/W79 -> 0.52932794 | AC79: 0.0046618358 | AD79: 0.02
B80: T2级 | C80: 2613-00 | D80: =VLOOKUP($C80,[1]Assortment!$F:$BA,5,0) -> 261300舒洁无香湿巾单包装 | E80: =VLOOKUP($C80,[1]Assortment!$F:$AM,7,0) -> 30 | F80: =VLOOKUP($C80,[1]Assortment!$F:$AM,31,0) -> 30 | G80: =VLOOKUP($C80,[1]Assortment!$F:$AM,14,0) -> 91.36283 | H80: =G80/E80 -> 3.0454277 | I80: 1 | K80: 1.7050973 | L80: =K80*1.13 -> 1.92676 | M80: =L80*1.12 -> 2.1579712 | N80: 1.98 | P80: =N80/1.13 -> 1.7522124 | Q80: =P80-K80 -> 0.047115042 | R80: =N80 -> 1.98 | V80: =G80*I80 -> 91.36283 | W80: =R80*F80*I80/1.13 -> 52.566372 | X80: ='25年版cogs'!F15 -> 0.33593911 | Y80: ='25年版cogs'!G15 -> 0.025420065 | Z80: =W80-V80*(X80+Y80) -> 19.551575 | AA80: =Z80/W80 -> 0.37194074 | AB80: =Z80/W80 -> 0.37194074 | AC80: 0.090805241 | AD80: 0.15
B81: T2级 | C81: 2530-00 | D81: =VLOOKUP($C81,[1]Assortment!$F:$BA,5,0) -> 253000舒洁蚕丝洗脸巾80抽3包装 | E81: =VLOOKUP($C81,[1]Assortment!$F:$AM,7,0) -> 6 | F81: =VLOOKUP($C81,[1]Assortment!$F:$AM,31,0) -> 18 | G81: =VLOOKUP($C81,[1]Assortment!$F:$AM,14,0) -> 358.2 | H81: =G81/E81 -> 59.7 | I81: 1 | K81: 7.3941504 | L81: =K81*1.13 -> 8.35539 | M81: =L81*1.12 -> 9.3580368 | N81: =M81 -> 9.3580368 | P81: =N81/1.13 -> 8.2814485 | Q81: =P81-K81 -> 0.88729805 | R81: =N81 -> 9.3580368 | V81: =G81*I81 -> 358.2 | W81: =R81*F81*I81/1.13 -> 149.06607 | X81: ='25年版cogs'!F16 -> 0.24149261 | Y81: ='25年版cogs'!G16 -> 0.025313854 | Z81: =W81-V81*(X81+Y81) -> 53.495996 | AA81: =Z81/W81 -> 0.35887439 | AB81: =Z81/W81 -> 0.35887439 | AC81: 0.0034525429 | AD81: 0.0034525429
B82: T2级 | C82: 2312-16 | D82: =VLOOKUP($C82,[1]Assortment!$F:$BA,5,0) -> 231216 舒洁马蹄莲盒面纸200抽3盒 FSC mix70% | E82: =VLOOKUP($C82,[1]Assortment!$F:$AM,7,0) -> 10 | F82: =VLOOKUP($C82,[1]Assortment!$F:$AM,31,0) -> 30 | G82: =VLOOKUP($C82,[1]Assortment!$F:$AM,14,0) -> 243.21307 | H82: =G82/E82 -> 24.321307 | I82: 1 | K82: 5.4662265 | L82: =K82*1.13 -> 6.1768359 | M82: =L82*1.12 -> 6.9180562 | N82: 6.85 | P82: =N82/1.13 -> 6.0619469 | Q82: =P82-K82 -> 0.59572044 | R82: =N82 -> 6.85 | V82: =G82*I82 -> 243.21307 | W82: =R82*F82*I82/1.13 -> 181.85841 | X82: ='25年版cogs'!F17 -> 0.38128924 | Y82: ='25年版cogs'!G17 -> 0.025408135 | Z82: =W82-V82*(X82+Y82) -> 82.94429 | AA82: =Z82/W82 -> 0.45609269 | AB82: =Z82/W82 -> 0.45609269 | AC82: 0.11037747 | AD82: 0.05
B83: T2级 | C83: 2291-60 | D83: =VLOOKUP($C83,[1]Assortment!$F:$BA,5,0) -> 229160舒洁绿茶洋甘菊印花清香卷纸10粒 | E83: =VLOOKUP($C83,[1]Assortment!$F:$AM,7,0) -> 5 | F83: =VLOOKUP($C83,[1]Assortment!$F:$AM,31,0) -> 50 | G83: =VLOOKUP($C83,[1]Assortment!$F:$AM,14,0) -> 153.64889 | H83: =G83/E83 -> 30.729778 | I83: 1 | K83: 2.2679877 | L83: =K83*1.13 -> 2.5628261 | M83: =L83*1.12 -> 2.8703652 | N83: 2.57 | P83: =N83/1.13 -> 2.2743363 | Q83: =P83-K83 -> 0.006348626 | R83: =N83 -> 2.57 | V83: =G83*I83 -> 153.64889 | W83: =R83*F83*I83/1.13 -> 113.71681 | X83: ='25年版cogs'!F18 -> 0.49468307 | Y83: ='25年版cogs'!G18 -> 0.02536674 | Z83: =W83-V83*(X83+Y83) -> 33.811739 | AA83: =Z83/W83 -> 0.2973328 | AB83: =Z83/W83 -> 0.2973328 | AC83: 0.018186358 | AD83: 0.018186358
B84: T2级 | C84: 2216-35 | D84: =VLOOKUP($C84,[1]Assortment!$F:$BA,5,0) -> 221635舒洁卷纸3层纯白10粒（蓝色） | E84: =VLOOKUP($C84,[1]Assortment!$F:$AM,7,0) -> 10 | F84: =VLOOKUP($C84,[1]Assortment!$F:$AM,31,0) -> 100 | G84: =VLOOKUP($C84,[1]Assortment!$F:$AM,14,0) -> 240.89676 | H84: =G84/E84 -> 24.089676 | I84: 1 | K84: 1.768 | L84: =K84*1.13 -> 1.99784 | M84: =L84*1.12 -> 2.2375808 | N84: 2.1 | P84: =N84/1.13 -> 1.8584071 | Q84: =P84-K84 -> 0.09040708 | R84: =N84 -> 2.1 | V84: =G84*I84 -> 240.89676 | W84: =R84*F84*I84/1.13 -> 185.84071 | X84: ='25年版cogs'!F19 -> 0.47353964 | Y84: ='25年版cogs'!G19 -> 0.025423334 | Z84: =W84-V84*(X84+Y84) -> 65.642145 | AA84: =Z84/W84 -> 0.35321726 | AB84: =Z84/W84 -> 0.35321726 | AC84: 0.079866435 | AD84: 0.02
B85: T2级 | C85: 2168-05 | D85: =VLOOKUP($C85,[1]Assortment!$F:$BA,5,0) -> 216805舒洁®北海道牛乳系列乳霜纸面巾80抽5包装 | E85: =VLOOKUP($C85,[1]Assortment!$F:$AM,7,0) -> 3 | F85: =VLOOKUP($C85,[1]Assortment!$F:$AM,31,0) -> 15 | G85: =VLOOKUP($C85,[1]Assortment!$F:$AM,14,0) -> 215.568 | H85: =G85/E85 -> 71.856 | I85: 1 | K85: 7.0024923 | L85: =K85*1.13 -> 7.9128163 | M85: =L85*1.12 -> 8.8623543 | N85: 8.45 | P85: =N85/1.13 -> 7.4778761 | Q85: =P85-K85 -> 0.47538379 | R85: =N85 -> 8.45 | V85: =G85*I85 -> 215.568 | W85: =R85*F85*I85/1.13 -> 112.16814 | X85: ='25年版cogs'!F20 -> 0.26496938 | Y85: ='25年版cogs'!G20 -> 0.025333387 | Z85: =W85-V85*(X85+Y85) -> 49.588154 | AA85: =Z85/W85 -> 0.44208768 | AB85: =Z85/W85 -> 0.44208768 | AC85: 0.023216316 | AD85: 0.02
B86: T2级 | C86: 2167-10 | D86: =VLOOKUP($C86,[1]Assortment!$F:$BA,5,0) -> 216710舒洁®牛乳系列乳霜纸面巾口袋包7抽10包装 | E86: =VLOOKUP($C86,[1]Assortment!$F:$AM,7,0) -> 12 | F86: =VLOOKUP($C86,[1]Assortment!$F:$AM,31,0) -> 120 | G86: =VLOOKUP($C86,[1]Assortment!$F:$AM,14,0) -> 202.8 | H86: =G86/E86 -> 16.9 | I86: 1 | K86: 0.80416726 | L86: =K86*1.13 -> 0.908709 | M86: =L86*1.12 -> 1.0177541 | N86: =M86 -> 1.0177541 | P86: =N86/1.13 -> 0.90066733 | Q86: =P86-K86 -> 0.096500071 | R86: =N86 -> 1.0177541 | V86: =G86*I86 -> 202.8 | W86: =R86*F86*I86/1.13 -> 108.08008 | X86: ='25年版cogs'!F21 -> 0.2909103 | Y86: ='25年版cogs'!G21 -> 0.025403037 | Z86: =W86-V86*(X86+Y86) -> 43.931734 | AA86: =Z86/W86 -> 0.40647392 | AB86: =Z86/W86 -> 0.40647392 | AC86: 0.0056779478 | AD86: 0.01
B87: T2级 | C87: 2162-08 | D87: =VLOOKUP($C87,[1]Assortment!$F:$BA,5,0) -> 216208舒洁®北海道牛乳系列乳霜纸面巾20抽8包装 | E87: =VLOOKUP($C87,[1]Assortment!$F:$AM,7,0) -> 4 | F87: =VLOOKUP($C87,[1]Assortment!$F:$AM,31,0) -> 32 | G87: =VLOOKUP($C87,[1]Assortment!$F:$AM,14,0) -> 100.4986 | H87: =G87/E87 -> 25.12465 | I87: 1 | K87: 1.601579 | L87: =K87*1.13 -> 1.8097843 | M87: =L87*1.12 -> 2.0269584 | N87: =M87 -> 2.0269584 | P87: =N87/1.13 -> 1.7937685 | Q87: =P87-K87 -> 0.19218948 | R87: =N87 -> 2.0269584 | V87: =G87*I87 -> 100.4986 | W87: =R87*F87*I87/1.13 -> 57.400592 | X87: ='25年版cogs'!F22 -> 0.29650668 | Y87: ='25年版cogs'!G22 -> 0.025358571 | Z87: =W87-V87*(X87+Y87) -> 25.053585 | AA87: =Z87/W87 -> 0.4364691 | AB87: =Z87/W87 -> 0.4364691 | AC87: 0.0058378524 | AD87: 0.0058378524
B88: T2级 | C88: 2156-10 | D88: =VLOOKUP($C88,[1]Assortment!$F:$BA,5,0) -> 215610舒洁®北海道轻牛乳系列乳霜纸面巾100抽3包装 | E88: =VLOOKUP($C88,[1]Assortment!$F:$AM,7,0) -> 6 | F88: =VLOOKUP($C88,[1]Assortment!$F:$AM,31,0) -> 18 | G88: =VLOOKUP($C88,[1]Assortment!$F:$AM,14,0) -> 215.4 | H88: =G88/E88 -> 35.9 | I88: 1 | K88: 4.5967522 | L88: =K88*1.13 -> 5.19433 | M88: =L88*1.12 -> 5.8176496 | N88: 6.2 | P88: =N88/1.13 -> 5.4867257 | Q88: =P88-K88 -> 0.88997345 | R88: =N88 -> 6.2 | V88: =G88*I88 -> 215.4 | W88: =R88*F88*I88/1.13 -> 98.761062 | X88: ='25年版cogs'!F23 -> 0.22394373 | Y88: ='25年版cogs'!G23 -> 0.02536732 | Z88: =W88-V88*(X88+Y88) -> 45.059462 | AA88: =Z88/W88 -> 0.45624724 | AB88: =Z88/W88 -> 0.45624724 | AC88: 0.0062721702 | AD88: 0.01
B89: T2级 | C89: 2155-03 | D89: =VLOOKUP($C89,[1]Assortment!$F:$BA,5,0) -> 215503舒洁®北海道轻牛乳系列乳霜纸面巾40抽3包装 | E89: =VLOOKUP($C89,[1]Assortment!$F:$AM,7,0) -> 16 | F89: =VLOOKUP($C89,[1]Assortment!$F:$AM,31,0) -> 48 | G89: =VLOOKUP($C89,[1]Assortment!$F:$AM,14,0) -> 222.4 | H89: =G89/E89 -> 13.9 | I89: 1 | K89: 1.9258968 | L89: =K89*1.13 -> 2.1762633 | M89: =L89*1.12 -> 2.4374149 | N89: =M89 -> 2.4374149 | P89: =N89/1.13 -> 2.1570044 | Q89: =P89-K89 -> 0.23110761 | R89: =N89 -> 2.4374149 | V89: =G89*I89 -> 222.4 | W89: =R89*F89*I89/1.13 -> 103.53621 | X89: ='25年版cogs'!F24 -> 0.22149679 | Y89: ='25年版cogs'!G24 -> 0.025475023 | Z89: =W89-V89*(X89+Y89) -> 48.609677 | AA89: =Z89/W89 -> 0.46949447 | AB89: =Z89/W89 -> 0.46949447 | AC89: 0.0017386837 | AD89: 0.01
B90: T2级 | C90: 2152-04 | D90: =VLOOKUP($C90,[1]Assortment!$F:$BA,5,0) -> 215204舒洁鎏金系列乳霜纸巾40抽8包 | E90: =VLOOKUP($C90,[1]Assortment!$F:$AM,7,0) -> 4 | F90: =VLOOKUP($C90,[1]Assortment!$F:$AM,31,0) -> 32 | G90: =VLOOKUP($C90,[1]Assortment!$F:$AM,14,0) -> 105.788 | H90: =G90/E90 -> 26.447 | I90: 1 | K90: 1.4882131 | L90: =K90*1.13 -> 1.6816808 | M90: =L90*1.12 -> 1.8834825 | N90: =M90 -> 1.8834825 | P90: =N90/1.13 -> 1.6667987 | Q90: =P90-K90 -> 0.17858558 | R90: =N90 -> 1.8834825 | V90: =G90*I90 -> 105.788 | W90: =R90*F90*I90/1.13 -> 53.337559 | X90: ='25年版cogs'!F25 -> 0.25536403 | Y90: ='25年版cogs'!G25 -> 0.02536136 | Z90: =W90-V90*(X90+Y90) -> 23.640181 | AA90: =Z90/W90 -> 0.44321829 | AB90: =Z90/W90 -> 0.44321829 | AC90: 0.0022587736 | AD90: 0.0022587736
B91: T2级 | C91: 2107-61 | D91: =VLOOKUP($C91,[1]Assortment!$F:$BA,5,0) -> 210761舒洁卡通系列抽纸200抽3包 FSC mix70% | E91: =VLOOKUP($C91,[1]Assortment!$F:$AM,7,0) -> 20 | F91: =VLOOKUP($C91,[1]Assortment!$F:$AM,31,0) -> 60 | G91: =VLOOKUP($C91,[1]Assortment!$F:$AM,14,0) -> 338.18199 | H91: =G91/E91 -> 16.909099 | I91: 1 | K91: 3.9400535 | L91: =K91*1.13 -> 4.4522605 | M91: =L91*1.12 -> 4.9865318 | N91: =M91 -> 4.9865318 | P91: =N91/1.13 -> 4.41286 | Q91: =P91-K91 -> 0.47280643 | R91: =N91 -> 4.9865318 | V91: =G91*I91 -> 338.18199 | W91: =R91*F91*I91/1.13 -> 264.7716 | X91: ='25年版cogs'!F26 -> 0.42805769 | Y91: ='25年版cogs'!G26 -> 0.025434118 | Z91: =W91-V91*(X91+Y91) -> 111.40884 | AA91: =Z91/W91 -> 0.42077336 | AB91: =Z91/W91 -> 0.42077336 | AC91: 0.13403529 | AD91: 0.13403529
B92: T2级 | C92: 2103-90 | D92: =VLOOKUP($C92,[1]Assortment!$F:$BA,5,0) -> 210390舒洁小熊印花抽纸3层80抽4包FSC mix70% | E92: =VLOOKUP($C92,[1]Assortment!$F:$AM,7,0) -> 24 | F92: =VLOOKUP($C92,[1]Assortment!$F:$AM,31,0) -> 96 | G92: =VLOOKUP($C92,[1]Assortment!$F:$AM,14,0) -> 287.22305 | H92: =G92/E92 -> 11.967627 | I92: 1 | K92: 2.1945358 | L92: =K92*1.13 -> 2.4798254 | M92: =L92*1.12 -> 2.7774045 | N92: 2.48 | P92: =N92/1.13 -> 2.1946903 | Q92: =P92-K92 -> 0.00015448009 | R92: =N92 -> 2.48 | V92: =G92*I92 -> 287.22305 | W92: =R92*F92*I92/1.13 -> 210.69027 | X92: ='25年版cogs'!F27 -> 0.4634207 | Y92: ='25年版cogs'!G27 -> 0.025450892 | Z92: =W92-V92*(X92+Y92) -> 70.275077 | AA92: =Z92/W92 -> 0.33354686 | AB92: =Z92/W92 -> 0.33354686 | AC92: 0.1268699 | AD92: 0.15
B93: T2经销商的价格体系申请 T2级经销商基本符合中台给到的价格指引 1.T2经销商的范围：除了T1级经销商之外的经销商 2.价格申请的逻辑：1.参考26年中台给到的T2( C)级客户的价格指引 3,T2级客户主要销售的sku为40抽、80抽湿厕纸，小熊单包湿巾和小熊80抽纸，在AD列标注预计了占比情况 4.T2级客户全年生意预计在100w-200W左右，主要服务的客户是当地的RLKA、KB/KC客户以及CVS，gp预计在35% | AD93: =SUMPRODUCT(AB69:AB92,AD69:AD92) -> 0.35085033

Sheet 25年版cogs
M1: Year | P1: DQF_2026
E3: SKU | F3: DQF COGS % VS GSV | G3: DQF DE % VS GSV | M3: 行标签 | N3: DQF COGS % VS GSV | O3: DQF DE % VS GSV | P3: 求和项:GSV(k) | Q3: 求和项:COGS | R3: 求和项:DE
D4: 2701-90 | E4: 2701-90 | F4: =VLOOKUP(E4,M:O,2,0) -> 0.42397103 | G4: =VLOOKUP(E4,M:O,3,0) -> 0.025426167 | M4: 5310 | N4: =Q4/P4 -> 0.64344709 | O4: =R4/P4 -> 0.0374714 | P4: 72.70936 | Q4: 46.784626 | R4: 2.7245215
D5: 2694-40 | E5: 2694-40 | F5: =J5/4+J6*0.75 -> 0.26981474 | G5: 0.025386209 | I5: 2694-60 | J5: 0.27411408 | K5: 0.025386209 | M5: 5701 | N5: =Q5/P5 -> 0.41704249 | O5: =R5/P5 -> 0.031337764 | P5: 7797.6323 | Q5: 3251.944 | R5: 244.36036
D6: 2694-30 | E6: 2694-30 | F6: =F5 -> 0.26981474 | G6: 0.025386209 | I6: 2694-65g | J6: 0.26838162 | K6: 0.025408885 | M6: 6001 | N6: =Q6/P6 -> 0.20493075 | O6: =R6/P6 -> 0.0064315813 | P6: 33.33 | Q6: 6.8303419 | R6: 0.2143646
D7: 2682-20 | E7: 2682-20 | F7: =VLOOKUP(E7,M:O,2,0) -> 0.22151094 | G7: =VLOOKUP(E7,M:O,3,0) -> 0.025347831 | M7: 6151 | N7: =Q7/P7 -> 0.5506546 | O7: =R7/P7 -> 0.0081293825 | P7: 833 | Q7: 458.69528 | R7: 6.7717756
D8: 2674-00 | E8: 2674-00 | F8: =VLOOKUP(E8,M:O,2,0) -> 0.35939124 | G8: =VLOOKUP(E8,M:O,3,0) -> 0.02533352 | I8: 2670-40 | J8: 0.18081218 | K8: 0.025370117 | M8: 6179 | N8: =Q8/P8 -> 0.70050213 | O8: =R8/P8 -> 0.021383596 | P8: 1657.26 | Q8: 1160.9142 | R8: 35.438178
D9: 2673-00 | E9: 2673-00 | F9: =VLOOKUP(E9,M:O,2,0) -> 0.35822651 | G9: =VLOOKUP(E9,M:O,3,0) -> 0.025367759 | I9: 2670-65g | J9: 0.18319948 | K9: 0.025345967 | M9: 6188 | N9: =Q9/P9 -> 0.29095667 | O9: =R9/P9 -> 0.0073469782 | P9: 5.9644493 | Q9: 1.7353963 | R9: 0.043820679
D10: 2670-30 | E10: 2670-30 | F10: =J8/4+J9*0.75 -> 0.18260265 | G10: 0.025370117 | I10: 2662-10 | J10: 0.30801591 | K10: 0.025238484 | M10: 6190 | N10: =Q10/P10 -> 0.26390262 | O10: =R10/P10 -> 0.018218063 | P10: 1882.6361 | Q10: 496.83259 | R10: 34.297983
D11: 2666-00 | E11: 2666-00 | F11: =VLOOKUP(E11,M:O,2,0) -> 0.32309188 | G11: =VLOOKUP(E11,M:O,3,0) -> 0.02533601 | I11: 2662-65g | J11: 0.3508964 | K11: 0.025356109 | M11: 6374 | N11: =Q11/P11 -> 0.25016071 | O11: =R11/P11 -> 0.013549876 | P11: 9135.6529 | Q11: 2285.3814 | R11: 123.78696
D12: 2662-00 | E12: 2662-00 | F12: =J10/4+J11*0.75 -> 0.34017628 | G12: 0.025238484 | I12: 2661-10 | J12: 0.28368677 | K12: 0.025424502 | M12: 6994 | N12: =Q12/P12 -> 0.4616229 | O12: =R12/P12 -> 0.033085025 | P12: 750.52226 | Q12: 346.45826 | R12: 24.831047
D13: 2661-00 | E13: 2661-00 | F13: =J12/4+J13*0.75 -> 0.30486433 | G13: 0.025424502 | I13: 2661-65g | J13: 0.31192352 | K13: 0.02534017 | M13: 7186 | N13: =Q13/P13 -> 0.25135173 | O13: =R13/P13 -> 0.0077605764 | P13: 154.05862 | Q13: 38.722901 | R13: 1.1955837
D14: 2655-00 | E14: 2655-00 | F14: =J14/4+J15*0.75 -> 0.27365302 | G14: 0.025424502 | I14: 2655-10 | J14: 0.26236461 | K14: 0.025410211 | M14: 7969 | N14: =Q14/P14 -> 0.68563862 | O14: =R14/P14 -> 0.0052307385 | P14: 46.02 | Q14: 31.553089 | R14: 0.24071859
D15: 2613-00 | E15: 2613-00 | F15: =VLOOKUP(E15,M:O,2,0) -> 0.33593911 | G15: =VLOOKUP(E15,M:O,3,0) -> 0.025420065 | I15: 2655-65g | J15: 0.27741583 | K15: 0.025370643 | M15: 8668 | N15: =Q15/P15 -> 0.43150887 | O15: =R15/P15 -> 0.040798654 | P15: 15607.932 | Q15: 6734.961 | R15: 636.78261
D16: 2530-00 | E16: 2530-00 | F16: =VLOOKUP(E16,M:O,2,0) -> 0.24149261 | G16: =VLOOKUP(E16,M:O,3,0) -> 0.025313854 | M16: 9337 | N16: =Q16/P16 -> 1.5085616 | O16: =R16/P16 -> 0.021426813 | P16: 25.62779 | Q16: 38.661099 | R16: 0.54912187
D17: 2312-16 | E17: 2312-16 | F17: =VLOOKUP(E17,M:O,2,0) -> 0.38128924 | G17: =VLOOKUP(E17,M:O,3,0) -> 0.025408135 | M17: 28610 | N17: =Q17/P17 -> 0.4840718 | O17: =R17/P17 -> 0.024173256 | P17: 4186.143 | Q17: 2026.3938 | R17: 101.19271
D18: 2291-60 | E18: 2291-60 | F18: =VLOOKUP(E18,M:O,2,0) -> 0.49468307 | G18: =VLOOKUP(E18,M:O,3,0) -> 0.02536674 | M18: 28644 | N18: =Q18/P18 -> 0.3552951 | O18: =R18/P18 -> 0.012798344 | P18: 1863.0589 | Q18: 661.93571 | R18: 23.84407
D19: 2216-35 | E19: 2216-35 | F19: =VLOOKUP(E19,M:O,2,0) -> 0.47353964 | G19: =VLOOKUP(E19,M:O,3,0) -> 0.025423334 | M19: 28660 | N19: =Q19/P19 -> 0.37233515 | O19: =R19/P19 -> 0.02154945 | P19: 306.86671 | Q19: 114.25726 | R19: 6.6128088
D20: 2168-05 | E20: 2168-05 | F20: =VLOOKUP(E20,M:O,2,0) -> 0.26496938 | G20: =VLOOKUP(E20,M:O,3,0) -> 0.025333387 | M20: 28680 | N20: =Q20/P20 -> 0.47365073 | O20: =R20/P20 -> 0.069186073 | P20: 5992.8459 | Q20: 2838.5158 | R20: 414.62147
D21: 2167-10 | E21: 2167-10 | F21: =VLOOKUP(E21,M:O,2,0) -> 0.2909103 | G21: =VLOOKUP(E21,M:O,3,0) -> 0.025403037 | M21: 29999 | N21: =Q21/P21 -> 0.527963 | O21: =R21/P21 -> 0.028360578 | P21: 1894.3871 | Q21: 1000.1663 | R21: 53.725913
D22: 2162-08 | E22: 2162-08 | F22: =VLOOKUP(E22,M:O,2,0) -> 0.29650668 | G22: =VLOOKUP(E22,M:O,3,0) -> 0.025358571 | M22: 33330 | N22: =Q22/P22 -> 0.65398817 | O22: =R22/P22 -> 0.012202277 | P22: 3046.827 | Q22: 1992.5888 | R22: 37.178226
D23: 2156-10 | E23: 2156-10 | F23: =VLOOKUP(E23,M:O,2,0) -> 0.22394373 | G23: =VLOOKUP(E23,M:O,3,0) -> 0.02536732 | M23: 33390 | N23: =Q23/P23 -> 0.77547684 | O23: =R23/P23 -> 0.0055432442 | P23: 109.278 | Q23: 84.742558 | R23: 0.60575464
D24: 2155-03 | E24: 2155-03 | F24: =VLOOKUP(E24,M:O,2,0) -> 0.22149679 | G24: =VLOOKUP(E24,M:O,3,0) -> 0.025475023 | M24: 34155 | N24: =Q24/P24 -> 0.22801768 | O24: =R24/P24 -> 0.028534257 | P24: 34027.484 | Q24: 7758.8679 | R24: 970.94899
D25: 2152-04 | E25: 2152-04 | F25: =VLOOKUP(E25,M:O,2,0) -> 0.25536403 | G25: =VLOOKUP(E25,M:O,3,0) -> 0.02536136 | M25: 34256 | N25: =Q25/P25 -> 0.44007786 | O25: =R25/P25 -> 0.032695916 | P25: 895.59978 | Q25: 394.13363 | R25: 29.282455
D26: 2107-61 | E26: 2107-61 | F26: =VLOOKUP(E26,M:O,2,0) -> 0.42805769 | G26: =VLOOKUP(E26,M:O,3,0) -> 0.025434118 | M26: 34349 | N26: =Q26/P26 -> 0.18959051 | O26: =R26/P26 -> 0.0027000033 | P26: 373.89261 | Q26: 70.88649 | R26: 1.0095113
D27: 2103-90 | E27: 2103-90 | F27: =VLOOKUP(E27,M:O,2,0) -> 0.4634207 | G27: =VLOOKUP(E27,M:O,3,0) -> 0.025450892 | M27: 34705 | N27: =Q27/P27 -> 0.52493395 | O27: =R27/P27 -> 0.025975228 | P27: 463.80225 | Q27: 243.46555 | R27: 12.047369
M28: 37680 | N28: =Q28/P28 -> 0.4317005 | O28: =R28/P28 -> 0.031811541 | P28: 33698.205 | Q28: 14547.532 | R28: 1071.9918
M29: 38714 | N29: =Q29/P29 -> 0.41548137 | O29: =R29/P29 -> 0.010522483 | P29: 782.81104 | Q29: 325.2434 | R29: 8.2371157
M30: 38715 | N30: =Q30/P30 -> 0.28131878 | O30: =R30/P30 -> 0.031410455 | P30: 171.26382 | Q30: 48.179729 | R30: 5.3794744
M31: 39000 | N31: =Q31/P31 -> 0.57038158 | O31: =R31/P31 -> 0.029242668 | P31: 1670.7418 | Q31: 952.96038 | R31: 48.856949
M32: 41412 | N32: =Q32/P32 -> 0.41158479 | O32: =R32/P32 -> 0.013182235 | P32: 272.7848 | Q32: 112.27407 | R32: 3.5959134
M33: 42031 | N33: =Q33/P33 -> 0.80973349 | O33: =R33/P33 -> 0.020012103 | P33: 495.73832 | Q33: 401.41592 | R33: 9.9207665
M34: 42877 | N34: =Q34/P34 -> 0.26683505 | O34: =R34/P34 -> 0.038178479 | P34: 69.65472 | Q34: 18.586321 | R34: 2.6593112
M35: 42921 | N35: =Q35/P35 -> 0.39449357 | O35: =R35/P35 -> 0.029626128 | P35: 1346.1657 | Q35: 531.05373 | R35: 39.881678
M36: 48568 | N36: =Q36/P36 -> 0.22202883 | O36: =R36/P36 -> 0.026194908 | P36: 5537.7329 | Q36: 1229.5364 | R36: 145.0604
M37: 52788 | N37: =Q37/P37 -> 0.46557129 | O37: =R37/P37 -> 0.020880752 | P37: 283.06072 | Q37: 131.78495 | R37: 5.9105208
M38: 53940 | N38: =Q38/P38 -> 0.20874273 | O38: =R38/P38 -> 0.010847106 | P38: 3729.1047 | Q38: 778.42349 | R38: 40.449994
M39: 53944 | N39: =Q39/P39 -> 0.42904979 | O39: =R39/P39 -> 0.0161815 | P39: 306.10454 | Q39: 131.33409 | R39: 4.9532308
... M80: 7775051 | N80: =Q80/P80 -> 0.36953299 | O80: =R80/P80 -> 0.017638117 | P80: 1280.9047 | Q80: 473.33656 | R80: 22.592748
M81: (空白) | N81: =Q81/P81 -> 0.26991422 | O81: =R81/P81 -> 0.025361762 | P81: 7182.336 | Q81: 1938.6146 | R81: 182.15669
M82: 0020-01 | N82: =Q82/P82 -> 0.51846863 | O82: =R82/P82 -> 0.052344351 | P82: 10089.009 | Q82: 5230.8345 | R82: 528.10262
M83: 0097-03 | N83: =Q83/P83 -> 0.46342668 | O83: =R83/P83 -> 0.060338959 | P83: 9012.9308 | Q83: 4176.8326 | R83: 543.83086
